Workbook

Sheet Dashboard_Premissas
A1: MODELO ACTUARIAL DE SAÚDE (RAMO DOENÇA) — SAU & SAG | DASHBOARD & PREMISSAS ACTUARIAIS
A2: Tarifação a custo técnico — mercado angolano. Células a amarelo = inputs editáveis (texto azul). Restantes células são fórmulas. Valores monetários em Kwanzas (Kz) a preços de referência 2026, projectados pela inflação médica. Documento de trabalho sujeito a validação do Actuariado, Médico Assessor e Direcção Técnica (ARSEG).
B3: Legenda: amarelo/azul = input editável | preto = fórmula | verde = ligação entre folhas | verde-claro = resultado final
B4: PAINEL EXECUTIVO — INDICADORES-CHAVE
B5: Indicador | C5: Valor
B6: Inflação médica projectada (medical trend) | C6: =med_trend -> 0.182194
B7: Factor de trend aplicado aos custos | C7: =f_trend -> 1.182194
B8: Carregamentos SAU (e_a+e_c+m) | C8: =load_SAU -> 0.3
B9: Carregamentos SAG (e_a+e_c+m) | C9: =load_SAG -> 0.21
B10: Rácio de sinistralidade alvo SAU | C10: =$D$58 -> 0.64814815
B11: Rácio de sinistralidade alvo SAG | C11: =$E$58 -> 0.75238095
B12: Câmbio USD/AOA | C12: =fx_usd -> 931.27
B13: Calculador — Prémio Total Anual da cotação | C13: =Calculador!C86 -> 2303121.5
B14: Calculador — Prestação na modalidade seleccionada | C14: =Calculador!C95 -> 199603.86
B15: SAG exemplo (censo) — Prémio total anual do grupo | C15: =Matriz_SAG!C161 -> 3.3814811e+08
B16: SAG exemplo — Factor de credibilidade Z | C16: =Matriz_SAG!C185 -> 0.63378288
B17: SAG exemplo — Prémio renovado total a pagar | C17: =Matriz_SAG!C192 -> 4.8346935e+08
B19: DECOMPOSIÇÃO DO PRÉMIO COMERCIAL — PESSOA SEGURA DE REFERÊNCIA (pacote base do plano)
B20: Célula de referência (Género | Escalão) → | C20: M|36-50
B21: Plano | C21: Prémio Puro | D21: Margem de Risco (σ) | E21: Custos Administrativos | F21: Comissões | G21: Margem do Segurador | H21: Impostos e Taxas | I21: Prémio Total | J21: Rácio Sinistr.
B22: SAU Base | C22: =INDEX(Matriz_SAU!$E$61:$E$70,MATCH($C$20,Matriz_SAU!$D$61:$D$70,0)) -> 138719.69 | D22: =C22*sig_SAU -> 11097.575 | E22: =(C22+D22)/(1-load_SAU)*ea_SAU -> 27823.207 | F22: =(C22+D22)/(1-load_SAU)*ec_SAU -> 25682.96 | G22: =(C22+D22)/(1-load_SAU)*m_SAU -> 10701.233 | H22: =(C22+D22)/(1-load_SAU)*tax_SAU -> 2140.2467 | I22: =SUM(C22:H22) -> 216164.92 | J22: =C22/(I22-H22) -> 0.64814815
B23: SAU Conforto | C23: =INDEX(Matriz_SAU!$J$61:$J$70,MATCH($C$20,Matriz_SAU!$D$61:$D$70,0)) -> 384163.62 | D23: =C23*sig_SAU -> 30733.09 | E23: =(C23+D23)/(1-load_SAU)*ea_SAU -> 77052.247 | F23: =(C23+D23)/(1-load_SAU)*ec_SAU -> 71125.151 | G23: =(C23+D23)/(1-load_SAU)*m_SAU -> 29635.48 | H23: =(C23+D23)/(1-load_SAU)*tax_SAU -> 5927.0959 | I23: =SUM(C23:H23) -> 598636.69 | J23: =C23/(I23-H23) -> 0.64814815
B24: SAU Premium | C24: =INDEX(Matriz_SAU!$O$61:$O$70,MATCH($C$20,Matriz_SAU!$D$61:$D$70,0)) -> 920081.41 | D24: =C24*sig_SAU -> 73606.513 | E24: =(C24+D24)/(1-load_SAU)*ea_SAU -> 184542.04 | F24: =(C24+D24)/(1-load_SAU)*ec_SAU -> 170346.5 | G24: =(C24+D24)/(1-load_SAU)*m_SAU -> 70977.709 | H24: =(C24+D24)/(1-load_SAU)*tax_SAU -> 14195.542 | I24: =SUM(C24:H24) -> 1433749.7 | J24: =C24/(I24-H24) -> 0.64814815
B25: SAG Colaboradores | C25: =INDEX(Matriz_SAG!$E$61:$E$70,MATCH($C$20,Matriz_SAG!$D$61:$D$70,0)) -> 333158.54 | D25: =C25*sig_SAG -> 16657.927 | E25: =(C25+D25)/(1-load_SAG)*ea_SAG -> 44280.566 | F25: =(C25+D25)/(1-load_SAG)*ec_SAG -> 30996.396 | G25: =(C25+D25)/(1-load_SAG)*m_SAG -> 17712.226 | H25: =(C25+D25)/(1-load_SAG)*tax_SAG -> 4428.0566 | I25: =SUM(C25:H25) -> 447233.71 | J25: =C25/(I25-H25) -> 0.75238095
B26: SAG Quadros Médios | C26: =INDEX(Matriz_SAG!$J$61:$J$70,MATCH($C$20,Matriz_SAG!$D$61:$D$70,0)) -> 406707.24 | D26: =C26*sig_SAG -> 20335.362 | E26: =(C26+D26)/(1-load_SAG)*ea_SAG -> 54056.026 | F26: =(C26+D26)/(1-load_SAG)*ec_SAG -> 37839.218 | G26: =(C26+D26)/(1-load_SAG)*m_SAG -> 21622.41 | H26: =(C26+D26)/(1-load_SAG)*tax_SAG -> 5405.6026 | I26: =SUM(C26:H26) -> 545965.86 | J26: =C26/(I26-H26) -> 0.75238095
B27: SAG Administração | C27: =INDEX(Matriz_SAG!$O$61:$O$70,MATCH($C$20,Matriz_SAG!$D$61:$D$70,0)) -> 907213.75 | D27: =C27*sig_SAG -> 45360.688 | E27: =(C27+D27)/(1-load_SAG)*ea_SAG -> 120579.04 | F27: =(C27+D27)/(1-load_SAG)*ec_SAG -> 84405.33 | G27: =(C27+D27)/(1-load_SAG)*m_SAG -> 48231.617 | H27: =(C27+D27)/(1-load_SAG)*tax_SAG -> 12057.904 | I27: =SUM(C27:H27) -> 1217848.3 | J27: =C27/(I27-H27) -> 0.75238095
B29: PRÉMIO TOTAL ANUAL POR ESCALÃO ETÁRIO (unisex, ponderado pela exposição) — pacote base
B30: Escalão | C30: SAU Base | D30: SAU Conforto | E30: SAU Premium | F30: SAG Colaboradores | G30: SAG Quadros Médios | H30: SAG Administração
B31: 0-17 | C31: =(INDEX(Matriz_SAU!$H$61:$H$70,MATCH("M|"&$B31,Matriz_SAU!$D$61:$D$70,0))*INDEX(Exp_M,MATCH($B31,Exp_Band,0))+INDEX(Matriz_SAU!$H$61:$H$70,MATCH("F|"&$B31,Matriz_SAU!$D$61:$D$70,0))*INDEX(Exp_F,MATCH($B31,Exp_Band,0)))/(INDEX(Exp_M,MATCH($B31,Exp_Band,0))+INDEX(Exp_F,MATCH($B31,Exp_Band,0))) -> 119291.44 | D31: =(INDEX(Matriz_SAU!$M$61:$M$70,MATCH("M|"&$B31,Matriz_SAU!$D$61:$D$70,0))*INDEX(Exp_M,MATCH($B31,Exp_Band,0))+INDEX(Matriz_SAU!$M$61:$M$70,MATCH("F|"&$B31,Matriz_SAU!$D$61:$D$70,0))*INDEX(Exp_F,MATCH($B31,Exp_Band,0)))/(INDEX(Exp_M,MATCH($B31,Exp_Band,0))+INDEX(Exp_F,MATCH($B31,Exp_Band,0))) -> 389561.17 | E31: =(INDEX(Matriz_SAU!$R$61:$R$70,MATCH("M|"&$B31,Matriz_SAU!$D$61:$D$70,0))*INDEX(Exp_M,MATCH($B31,Exp_Band,0))+INDEX(Matriz_SAU!$R$61:$R$70,MATCH("F|"&$B31,Matriz_SAU!$D$61:$D$70,0))*INDEX(Exp_F,MATCH($B31,Exp_Band,0)))/(INDEX(Exp_M,MATCH($B31,Exp_Band,0))+INDEX(Exp_F,MATCH($B31,Exp_Band,0))) -> 770884.79 | F31: =(INDEX(Matriz_SAG!$H$61:$H$70,MATCH("M|"&$B31,Matriz_SAG!$D$61:$D$70,0))*INDEX(Exp_M,MATCH($B31,Exp_Band,0))+INDEX(Matriz_SAG!$H$61:$H$70,MATCH("F|"&$B31,Matriz_SAG!$D$61:$D$70,0))*INDEX(Exp_F,MATCH($B31,Exp_Band,0)))/(INDEX(Exp_M,MATCH($B31,Exp_Band,0))+INDEX(Exp_F,MATCH($B31,Exp_Band,0))) -> 295365.14 | G31: =(INDEX(Matriz_SAG!$M$61:$M$70,MATCH("M|"&$B31,Matriz_SAG!$D$61:$D$70,0))*INDEX(Exp_M,MATCH($B31,Exp_Band,0))+INDEX(Matriz_SAG!$M$61:$M$70,MATCH("F|"&$B31,Matriz_SAG!$D$61:$D$70,0))*INDEX(Exp_F,MATCH($B31,Exp_Band,0)))/(INDEX(Exp_M,MATCH($B31,Exp_Band,0))+INDEX(Exp_F,MATCH($B31,Exp_Band,0))) -> 356491.93 | H31: =(INDEX(Matriz_SAG!$R$61:$R$70,MATCH("M|"&$B31,Matriz_SAG!$D$61:$D$70,0))*INDEX(Exp_M,MATCH($B31,Exp_Band,0))+INDEX(Matriz_SAG!$R$61:$R$70,MATCH("F|"&$B31,Matriz_SAG!$D$61:$D$70,0))*INDEX(Exp_F,MATCH($B31,Exp_Band,0)))/(INDEX(Exp_M,MATCH($B31,Exp_Band,0))+INDEX(Exp_F,MATCH($B31,Exp_Band,0))) -> 679533.5
B32: 18-35 | C32: =(INDEX(Matriz_SAU!$H$61:$H$70,MATCH("M|"&$B32,Matriz_SAU!$D$61:$D$70,0))*INDEX(Exp_M,MATCH($B32,Exp_Band,0))+INDEX(Matriz_SAU!$H$61:$H$70,MATCH("F|"&$B32,Matriz_SAU!$D$61:$D$70,0))*INDEX(Exp_F,MATCH($B32,Exp_Band,0)))/(INDEX(Exp_M,MATCH($B32,Exp_Band,0))+INDEX(Exp_F,MATCH($B32,Exp_Band,0))) -> 165586.99 | D32: =(INDEX(Matriz_SAU!$M$61:$M$70,MATCH("M|"&$B32,Matriz_SAU!$D$61:$D$70,0))*INDEX(Exp_M,MATCH($B32,Exp_Band,0))+INDEX(Matriz_SAU!$M$61:$M$70,MATCH("F|"&$B32,Matriz_SAU!$D$61:$D$70,0))*INDEX(Exp_F,MATCH($B32,Exp_Band,0)))/(INDEX(Exp_M,MATCH($B32,Exp_Band,0))+INDEX(Exp_F,MATCH($B32,Exp_Band,0))) -> 509083.85 | E32: =(INDEX(Matriz_SAU!$R$61:$R$70,MATCH("M|"&$B32,Matriz_SAU!$D$61:$D$70,0))*INDEX(Exp_M,MATCH($B32,Exp_Band,0))+INDEX(Matriz_SAU!$R$61:$R$70,MATCH("F|"&$B32,Matriz_SAU!$D$61:$D$70,0))*INDEX(Exp_F,MATCH($B32,Exp_Band,0)))/(INDEX(Exp_M,MATCH($B32,Exp_Band,0))+INDEX(Exp_F,MATCH($B32,Exp_Band,0))) -> 1194927.8 | F32: =(INDEX(Matriz_SAG!$H$61:$H$70,MATCH("M|"&$B32,Matriz_SAG!$D$61:$D$70,0))*INDEX(Exp_M,MATCH($B32,Exp_Band,0))+INDEX(Matriz_SAG!$H$61:$H$70,MATCH("F|"&$B32,Matriz_SAG!$D$61:$D$70,0))*INDEX(Exp_F,MATCH($B32,Exp_Band,0)))/(INDEX(Exp_M,MATCH($B32,Exp_Band,0))+INDEX(Exp_F,MATCH($B32,Exp_Band,0))) -> 415037.42 | G32: =(INDEX(Matriz_SAG!$M$61:$M$70,MATCH("M|"&$B32,Matriz_SAG!$D$61:$D$70,0))*INDEX(Exp_M,MATCH($B32,Exp_Band,0))+INDEX(Matriz_SAG!$M$61:$M$70,MATCH("F|"&$B32,Matriz_SAG!$D$61:$D$70,0))*INDEX(Exp_F,MATCH($B32,Exp_Band,0)))/(INDEX(Exp_M,MATCH($B32,Exp_Band,0))+INDEX(Exp_F,MATCH($B32,Exp_Band,0))) -> 511391.49 | H32: =(INDEX(Matriz_SAG!$R$61:$R$70,MATCH("M|"&$B32,Matriz_SAG!$D$61:$D$70,0))*INDEX(Exp_M,MATCH($B32,Exp_Band,0))+INDEX(Matriz_SAG!$R$61:$R$70,MATCH("F|"&$B32,Matriz_SAG!$D$61:$D$70,0))*INDEX(Exp_F,MATCH($B32,Exp_Band,0)))/(INDEX(Exp_M,MATCH($B32,Exp_Band,0))+INDEX(Exp_F,MATCH($B32,Exp_Band,0))) -> 1042517.4
B33: 36-50 | C33: =(INDEX(Matriz_SAU!$H$61:$H$70,MATCH("M|"&$B33,Matriz_SAU!$D$61:$D$70,0))*INDEX(Exp_M,MATCH($B33,Exp_Band,0))+INDEX(Matriz_SAU!$H$61:$H$70,MATCH("F|"&$B33,Matriz_SAU!$D$61:$D$70,0))*INDEX(Exp_F,MATCH($B33,Exp_Band,0)))/(INDEX(Exp_M,MATCH($B33,Exp_Band,0))+INDEX(Exp_F,MATCH($B33,Exp_Band,0))) -> 218143.5 | D33: =(INDEX(Matriz_SAU!$M$61:$M$70,MATCH("M|"&$B33,Matriz_SAU!$D$61:$D$70,0))*INDEX(Exp_M,MATCH($B33,Exp_Band,0))+INDEX(Matriz_SAU!$M$61:$M$70,MATCH("F|"&$B33,Matriz_SAU!$D$61:$D$70,0))*INDEX(Exp_F,MATCH($B33,Exp_Band,0)))/(INDEX(Exp_M,MATCH($B33,Exp_Band,0))+INDEX(Exp_F,MATCH($B33,Exp_Band,0))) -> 635595.12 | E33: =(INDEX(Matriz_SAU!$R$61:$R$70,MATCH("M|"&$B33,Matriz_SAU!$D$61:$D$70,0))*INDEX(Exp_M,MATCH($B33,Exp_Band,0))+INDEX(Matriz_SAU!$R$61:$R$70,MATCH("F|"&$B33,Matriz_SAU!$D$61:$D$70,0))*INDEX(Exp_F,MATCH($B33,Exp_Band,0)))/(INDEX(Exp_M,MATCH($B33,Exp_Band,0))+INDEX(Exp_F,MATCH($B33,Exp_Band,0))) -> 1531164.9 | F33: =(INDEX(Matriz_SAG!$H$61:$H$70,MATCH("M|"&$B33,Matriz_SAG!$D$61:$D$70,0))*INDEX(Exp_M,MATCH($B33,Exp_Band,0))+INDEX(Matriz_SAG!$H$61:$H$70,MATCH("F|"&$B33,Matriz_SAG!$D$61:$D$70,0))*INDEX(Exp_F,MATCH($B33,Exp_Band,0)))/(INDEX(Exp_M,MATCH($B33,Exp_Band,0))+INDEX(Exp_F,MATCH($B33,Exp_Band,0))) -> 486622.33 | G33: =(INDEX(Matriz_SAG!$M$61:$M$70,MATCH("M|"&$B33,Matriz_SAG!$D$61:$D$70,0))*INDEX(Exp_M,MATCH($B33,Exp_Band,0))+INDEX(Matriz_SAG!$M$61:$M$70,MATCH("F|"&$B33,Matriz_SAG!$D$61:$D$70,0))*INDEX(Exp_F,MATCH($B33,Exp_Band,0)))/(INDEX(Exp_M,MATCH($B33,Exp_Band,0))+INDEX(Exp_F,MATCH($B33,Exp_Band,0))) -> 595134.55 | H33: =(INDEX(Matriz_SAG!$R$61:$R$70,MATCH("M|"&$B33,Matriz_SAG!$D$61:$D$70,0))*INDEX(Exp_M,MATCH($B33,Exp_Band,0))+INDEX(Matriz_SAG!$R$61:$R$70,MATCH("F|"&$B33,Matriz_SAG!$D$61:$D$70,0))*INDEX(Exp_F,MATCH($B33,Exp_Band,0)))/(INDEX(Exp_M,MATCH($B33,Exp_Band,0))+INDEX(Exp_F,MATCH($B33,Exp_Band,0))) -> 1296848
B34: 51-65 | C34: =(INDEX(Matriz_SAU!$H$61:$H$70,MATCH("M|"&$B34,Matriz_SAU!$D$61:$D$70,0))*INDEX(Exp_M,MATCH($B34,Exp_Band,0))+INDEX(Matriz_SAU!$H$61:$H$70,MATCH("F|"&$B34,Matriz_SAU!$D$61:$D$70,0))*INDEX(Exp_F,MATCH($B34,Exp_Band,0)))/(INDEX(Exp_M,MATCH($B34,Exp_Band,0))+INDEX(Exp_F,MATCH($B34,Exp_Band,0))) -> 323276.03 | D34: =(INDEX(Matriz_SAU!$M$61:$M$70,MATCH("M|"&$B34,Matriz_SAU!$D$61:$D$70,0))*INDEX(Exp_M,MATCH($B34,Exp_Band,0))+INDEX(Matriz_SAU!$M$61:$M$70,MATCH("F|"&$B34,Matriz_SAU!$D$61:$D$70,0))*INDEX(Exp_F,MATCH($B34,Exp_Band,0)))/(INDEX(Exp_M,MATCH($B34,Exp_Band,0))+INDEX(Exp_F,MATCH($B34,Exp_Band,0))) -> 879736.45 | E34: =(INDEX(Matriz_SAU!$R$61:$R$70,MATCH("M|"&$B34,Matriz_SAU!$D$61:$D$70,0))*INDEX(Exp_M,MATCH($B34,Exp_Band,0))+INDEX(Matriz_SAU!$R$61:$R$70,MATCH("F|"&$B34,Matriz_SAU!$D$61:$D$70,0))*INDEX(Exp_F,MATCH($B34,Exp_Band,0)))/(INDEX(Exp_M,MATCH($B34,Exp_Band,0))+INDEX(Exp_F,MATCH($B34,Exp_Band,0))) -> 2171087.1 | F34: =(INDEX(Matriz_SAG!$H$61:$H$70,MATCH("M|"&$B34,Matriz_SAG!$D$61:$D$70,0))*INDEX(Exp_M,MATCH($B34,Exp_Band,0))+INDEX(Matriz_SAG!$H$61:$H$70,MATCH("F|"&$B34,Matriz_SAG!$D$61:$D$70,0))*INDEX(Exp_F,MATCH($B34,Exp_Band,0)))/(INDEX(Exp_M,MATCH($B34,Exp_Band,0))+INDEX(Exp_F,MATCH($B34,Exp_Band,0))) -> 655760.65 | G34: =(INDEX(Matriz_SAG!$M$61:$M$70,MATCH("M|"&$B34,Matriz_SAG!$D$61:$D$70,0))*INDEX(Exp_M,MATCH($B34,Exp_Band,0))+INDEX(Matriz_SAG!$M$61:$M$70,MATCH("F|"&$B34,Matriz_SAG!$D$61:$D$70,0))*INDEX(Exp_F,MATCH($B34,Exp_Band,0)))/(INDEX(Exp_M,MATCH($B34,Exp_Band,0))+INDEX(Exp_F,MATCH($B34,Exp_Band,0))) -> 802667.69 | H34: =(INDEX(Matriz_SAG!$R$61:$R$70,MATCH("M|"&$B34,Matriz_SAG!$D$61:$D$70,0))*INDEX(Exp_M,MATCH($B34,Exp_Band,0))+INDEX(Matriz_SAG!$R$61:$R$70,MATCH("F|"&$B34,Matriz_SAG!$D$61:$D$70,0))*INDEX(Exp_F,MATCH($B34,Exp_Band,0)))/(INDEX(Exp_M,MATCH($B34,Exp_Band,0))+INDEX(Exp_F,MATCH($B34,Exp_Band,0))) -> 1782199.3
B35: >65 | C35: =(INDEX(Matriz_SAU!$H$61:$H$70,MATCH("M|"&$B35,Matriz_SAU!$D$61:$D$70,0))*INDEX(Exp_M,MATCH($B35,Exp_Band,0))+INDEX(Matriz_SAU!$H$61:$H$70,MATCH("F|"&$B35,Matriz_SAU!$D$61:$D$70,0))*INDEX(Exp_F,MATCH($B35,Exp_Band,0)))/(INDEX(Exp_M,MATCH($B35,Exp_Band,0))+INDEX(Exp_F,MATCH($B35,Exp_Band,0))) -> 473245.18 | D35: =(INDEX(Matriz_SAU!$M$61:$M$70,MATCH("M|"&$B35,Matriz_SAU!$D$61:$D$70,0))*INDEX(Exp_M,MATCH($B35,Exp_Band,0))+INDEX(Matriz_SAU!$M$61:$M$70,MATCH("F|"&$B35,Matriz_SAU!$D$61:$D$70,0))*INDEX(Exp_F,MATCH($B35,Exp_Band,0)))/(INDEX(Exp_M,MATCH($B35,Exp_Band,0))+INDEX(Exp_F,MATCH($B35,Exp_Band,0))) -> 1191572.2 | E35: =(INDEX(Matriz_SAU!$R$61:$R$70,MATCH("M|"&$B35,Matriz_SAU!$D$61:$D$70,0))*INDEX(Exp_M,MATCH($B35,Exp_Band,0))+INDEX(Matriz_SAU!$R$61:$R$70,MATCH("F|"&$B35,Matriz_SAU!$D$61:$D$70,0))*INDEX(Exp_F,MATCH($B35,Exp_Band,0)))/(INDEX(Exp_M,MATCH($B35,Exp_Band,0))+INDEX(Exp_F,MATCH($B35,Exp_Band,0))) -> 2844468.2 | F35: =(INDEX(Matriz_SAG!$H$61:$H$70,MATCH("M|"&$B35,Matriz_SAG!$D$61:$D$70,0))*INDEX(Exp_M,MATCH($B35,Exp_Band,0))+INDEX(Matriz_SAG!$H$61:$H$70,MATCH("F|"&$B35,Matriz_SAG!$D$61:$D$70,0))*INDEX(Exp_F,MATCH($B35,Exp_Band,0)))/(INDEX(Exp_M,MATCH($B35,Exp_Band,0))+INDEX(Exp_F,MATCH($B35,Exp_Band,0))) -> 883607.93 | G35: =(INDEX(Matriz_SAG!$M$61:$M$70,MATCH("M|"&$B35,Matriz_SAG!$D$61:$D$70,0))*INDEX(Exp_M,MATCH($B35,Exp_Band,0))+INDEX(Matriz_SAG!$M$61:$M$70,MATCH("F|"&$B35,Matriz_SAG!$D$61:$D$70,0))*INDEX(Exp_F,MATCH($B35,Exp_Band,0)))/(INDEX(Exp_M,MATCH($B35,Exp_Band,0))+INDEX(Exp_F,MATCH($B35,Exp_Band,0))) -> 1087983.5 | H35: =(INDEX(Matriz_SAG!$R$61:$R$70,MATCH("M|"&$B35,Matriz_SAG!$D$61:$D$70,0))*INDEX(Exp_M,MATCH($B35,Exp_Band,0))+INDEX(Matriz_SAG!$R$61:$R$70,MATCH("F|"&$B35,Matriz_SAG!$D$61:$D$70,0))*INDEX(Exp_F,MATCH($B35,Exp_Band,0)))/(INDEX(Exp_M,MATCH($B35,Exp_Band,0))+INDEX(Exp_F,MATCH($B35,Exp_Band,0))) -> 2316177.2
B36: A. PARÂMETROS MACROECONÓMICOS E INFLAÇÃO MÉDICA (MEDICAL TREND) — ANGOLA
B37: Parâmetro | C37: Código | D37: Valor | E37: Fonte / Racional
B38: Data de referência dos custos médicos (preços base) | C38: dt_base | D38: 46203 | E38: Tabelas de preços da rede convencionada de Luanda, 1.º semestre 2026
B39: Taxa de câmbio USD/AOA | C39: fx_usd | D39: 931.27 | E39: Câmbio de mercado 01/10/2026 ≈ 931 Kz/USD (Wise / BNA). Actualizar trimestralmente
B40: Inflação geral IPC Angola (homóloga) | C40: cpi | D40: 0.109 | E40: INE Angola: 10,88% homóloga em Maio 2026 (BNA projecta ~13,5% média 2026)
B41: Excesso de inflação médica sobre IPC | C41: med_excess | D41: 0.04 | E41: Tecnologia, procura induzida, escassez de especialistas e salários clínicos
B42: Componente cambial (fármacos/dispositivos importados) | C42: fx_comp | D42: 0.025 | E42: Pass-through da depreciação do Kz em consumíveis e medicamentos importados
B43: Inflação Médica Projectada (Medical Trend) anual | C43: med_trend | D43: =(1+cpi)*(1+med_excess)*(1+fx_comp)-1 -> 0.182194 | E43: Fórmula: (1+IPC)×(1+excesso médico)×(1+componente cambial) − 1
B44: Meses de projecção (data base → ponto médio de exposição) | C44: proj_m | D44: 12 | E44: Apólices emitidas nos 12 meses seguintes → ponto médio ≈ 12 meses após data base
B45: Factor de Trend aplicado aos custos | C45: f_trend | D45: =(1+med_trend)^(proj_m/12) -> 1.182194 | E45: (1+trend)^(meses/12)
B48: B. CARREGAMENTOS ACTUARIAIS, DESPESAS, MARGEM E ENCARGOS FISCAIS
B49: Parâmetro | C49: Código | D49: SAU (Individual) | E49: SAG (Grupo) | F49: Fonte / Racional
B50: Carregamento de Segurança / Volatilidade (σ) | C50: sig | D50: 0.08 | E50: 0.05 | F50: Desvios estocásticos; SAU > SAG (menor mutualização). No SAG o σ efectivo varia com a dimensão (ver Matriz_SAG)
B51: Despesas de Gestão e Administração (e_a) | C51: ea | D51: 0.13 | E51: 0.1 | F51: Gestão de rede, TPA/cartões, auditoria médica, pré-autorizações, custos de estrutura
B52: Custos de Aquisição / Comissões de Mediação (e_c) | C52: ec | D52: 0.12 | E52: 0.07 | F52: Mediação de seguros (agentes/corretores); SAG negociado com corretores
B53: Margem do Segurador / Lucro Actuarial (m) | C53: m | D53: 0.05 | E53: 0.04 | F53: Remuneração do capital de solvência exigido pela ARSEG
B54: Soma dos carregamentos sobre o prémio comercial (e_a + e_c + m) | C54: load | D54: =ea_SAU+ec_SAU+m_SAU -> 0.3 | E54: =ea_SAG+ec_SAG+m_SAG -> 0.21
B55: Imposto do Selo sobre o prémio | C55: is | D55: 0 | E55: 0 | F55: Seguros de saúde isentos de Imposto do Selo (Código do Imposto do Selo de Angola). Parametrizável caso a isenção seja alterada
B56: Taxa ARSEG / encargos parafiscais sobre prémios | C56: arseg | D56: 0.01 | E56: 0.01 | F56: PRESSUPOSTO PRUDENCIAL a confirmar face ao Decreto Presidencial n.º 213/22 (taxas do sector segurador). IVA: operações de seguro isentas
B57: Total de impostos e encargos regulatórios | C57: tax | D57: =is_SAU+arseg_SAU -> 0.01 | E57: =is_SAG+arseg_SAG -> 0.01
B58: Rácio de sinistralidade alvo implícito (Prémio Puro / Prémio Comercial) | C58: LR_alvo | D58: =(1-load_SAU)/(1+sig_SAU) -> 0.64814815 | E58: =(1-load_SAG)/(1+sig_SAG) -> 0.75238095 | F58: Benchmark mercado angolano ramo Doença: sinistralidade 70%–85%
B60: Fraccionamento do prémio | C60: N.º prestações | D60: Encargo de fraccionamento
B61: Anual | C61: 1 | D61: 0
B62: Semestral | C62: 2 | D62: 0.015
B63: Trimestral | C63: 4 | D63: 0.025
B64: Mensal | C64: 12 | D64: 0.04
B67: C. TABELA BIOMÉTRICA — EXPOSIÇÃO POR ESCALÃO ETÁRIO E GÉNERO (CARTEIRA DE REFERÊNCIA SAU+SAG)
B68: Escalão etário | C68: Idade mín. | D68: Idade máx. | E68: Vidas expostas — M | F68: Vidas expostas — F | G68: Total vidas | H68: % da carteira | I68: % Feminino
B69: 0-17 | C69: 0 | D69: 17 | E69: 3200 | F69: 3100 | G69: =E69+F69 -> 6300 | H69: =G69/$G$74 -> 0.25557809 | I69: =F69/G69 -> 0.49206349
B70: 18-35 | C70: 18 | D70: 35 | E70: 4600 | F70: 4200 | G70: =E70+F70 -> 8800 | H70: =G70/$G$74 -> 0.35699797 | I70: =F70/G70 -> 0.47727273
B71: 36-50 | C71: 36 | D71: 50 | E71: 3300 | F71: 2700 | G71: =E71+F71 -> 6000 | H71: =G71/$G$74 -> 0.24340771 | I71: =F71/G71 -> 0.45
B72: 51-65 | C72: 51 | D72: 65 | E72: 1500 | F72: 1200 | G72: =E72+F72 -> 2700 | H72: =G72/$G$74 -> 0.10953347 | I72: =F72/G72 -> 0.44444444
B73: >65 | C73: 66 | D73: 120 | E73: 450 | F73: 400 | G73: =E73+F73 -> 850 | H73: =G73/$G$74 -> 0.034482759 | I73: =F73/G73 -> 0.47058824
B74: TOTAL | E74: =SUM(E69:E73) -> 13050 | F74: =SUM(F69:F73) -> 11600 | G74: =SUM(G69:G73) -> 24650 | H74: =SUM(H69:H73) -> 1 | I74: =F74/G74 -> 0.47058824
B75: Exposição em vidas-ano da carteira de referência (pressuposto). Substituir pela exposição real da carteira (Sistema de Gestão de Apólices) na calibração.
B77: D. FREQUÊNCIA ESPERADA (λ) E CUSTO MÉDIO POR ACTO (μ) — POR COBERTURA (preços 2026, Kz)
B78: Cobertura | C78: Código | D78: Grupo | E78: Unidade de λ | F78: Célula de referência | G78: Frequência λ (célula ref.) | H78: λ por 1.000 vidas | I78: μ Rede Convencionada (Kz) | J78: μ Livre Escolha / Reembolso (Kz) | K78: % utilização Rede | L78: μ Ponderado (Kz) | M78: CV severidade anual | N78: Aplica factor de rede (S/N) | O78: Fundamentação técnica — mercado angolano
B79: Internamento Hospitalar Médico (incl. malária grave) | C79: HOSP_INT | D79: Principal | E79: internamentos/vida/ano | F79: M|18-35 | G79: 0.045 | H79: =G79*1000 -> 45 | I79: 820000 | J79: 1050000 | K79: 0.85 | L79: =K79*I79+(1-K79)*J79 -> 854500 | M79: 1.5 | N79: S | O79: ≈45‰ vidas. Malária grave, gastroenterites, pneumonias e complicações de HTA dominam os internamentos médicos na rede privada de Luanda. Estadia média ≈4 dias.
B80: Cirurgia (com internamento e de ambulatório) | C80: HOSP_CIR | D80: Principal | E80: cirurgias/vida/ano | F80: M|18-35 | G80: 0.024 | H80: =G80*1000 -> 24 | I80: 1950000 | J80: 2500000 | K80: 0.85 | L80: =K80*I80+(1-K80)*J80 -> 2032500 | M80: 1.3 | N80: S | O80: Inclui bloco, honorários, anestesia e próteses intra-operatórias. Elevado peso de consumíveis importados (sensíveis ao câmbio).
B81: Cuidados Intensivos (UCI) | C81: HOSP_UCI | D81: Principal | E81: episódios UCI/vida/ano | F81: M|18-35 | G81: 0.0035 | H81: =G81*1000 -> 3.5 | I81: 2750000 | J81: 3600000 | K81: 0.9 | L81: =K81*I81+(1-K81)*J81 -> 2835000 | M81: 1.2 | N81: S | O81: ≈5 dias × Kz 550 mil/dia (oferta UCI privada concentrada em Luanda).
B82: Consultas de Clínica Geral e Especialidade (incl. teleconsulta) | C82: AMB_CONS | D82: Principal | E82: consultas/vida/ano | F82: M|18-35 | G82: 2.6 | H82: =G82*1000 -> 2600 | I82: 22000 | J82: 32000 | K82: 0.8 | L82: =K82*I82+(1-K82)*J82 -> 24000 | M82: 1 | N82: S | O82: Consulta CG rede ≈ Kz 15–20 mil; especialidade ≈ Kz 25–40 mil (Luanda, 2026).
B83: MCDT — Exames, Análises e Imagiologia | C83: AMB_MCDT | D83: Principal | E83: actos/vida/ano | F83: M|18-35 | G83: 3.8 | H83: =G83*1000 -> 3800 | I83: 13500 | J83: 19000 | K83: 0.8 | L83: =K83*I83+(1-K83)*J83 -> 14600 | M83: 1.5 | N83: S | O83: Análises clínicas, ecografia, RX; TAC/RM com custo muito superior (cauda pesada).
B84: Malária e Doenças Endémicas (ambulatório) | C84: MAL | D84: Principal | E84: episódios/vida/ano | F84: M|18-35 | G84: 0.3 | H84: =G84*1000 -> 300 | I84: 35000 | J84: 45000 | K84: 0.85 | L84: =K84*I84+(1-K84)*J84 -> 36500 | M84: 0.8 | N84: S | O84: Malária é a 1.ª causa de consulta e de morbilidade em Angola; episódio = consulta + teste (TDR/gota espessa) + ACT.
B85: Maternidade e Parto (Normal e Cesariana) | C85: MAT | D85: Principal | E85: partos/mulher fértil/ano | F85: F|18-35 | G85: 0.075 | H85: =G85*1000 -> 75 | I85: =(1-tx_ces)*pn_R+tx_ces*pc_R -> 835400 | J85: =(1-tx_ces)*pn_L+tx_ces*pc_L -> 1086600 | K85: 0.8 | L85: =K85*I85+(1-K85)*J85 -> 885640 | M85: 0.5 | N85: S | O85: ≈75 partos/1000 mulheres 18–35 seguradas (fecundidade urbana segurada < média nacional). Custo misto normal/cesariana — ver parâmetros auxiliares.
B86: Urgência Hospitalar | C86: URG | D86: Principal | E86: episódios/vida/ano | F86: M|18-35 | G86: 0.42 | H86: =G86*1000 -> 420 | I86: 42000 | J86: 55000 | K86: 0.9 | L86: =K86*I86+(1-K86)*J86 -> 43300 | M86: 1 | N86: S | O86: Elevada utilização de urgência como porta de entrada (cultura de acesso directo em Luanda).
B87: Transporte em Ambulância / Emergência Médica | C87: AMBUL | D87: Principal | E87: transportes/vida/ano | F87: M|18-35 | G87: 0.018 | H87: =G87*1000 -> 18 | I87: 75000 | J87: 95000 | K87: 0.95 | L87: =K87*I87+(1-K87)*J87 -> 76000 | M87: 0.6 | N87: N | O87: Ambulância privada urbana; transferências inter-provinciais têm custo superior.
B88: Medicamentos em Ambulatório (Farmácia) | C88: MED | D88: Principal | E88: receitas/vida/ano | F88: M|18-35 | G88: 3.4 | H88: =G88*1000 -> 3400 | I88: 16500 | J88: 19500 | K88: 0.7 | L88: =K88*I88+(1-K88)*J88 -> 17400 | M88: 1.2 | N88: N | O88: Fármacos maioritariamente importados — forte transmissão cambial (USD/AOA).
B89: Estomatologia (tratamentos) | C89: DENT | D89: Extensão | E89: actos/vida/ano | F89: M|18-35 | G89: 0.85 | H89: =G89*1000 -> 850 | I89: 32000 | J89: 42000 | K89: 0.75 | L89: =K89*I89+(1-K89)*J89 -> 34500 | M89: 1 | N89: S | O89: Consultas, destartarização, restaurações, endodontia.
B90: Próteses Dentárias | C90: PROT | D90: Extensão | E90: próteses/vida/ano | F90: M|18-35 | G90: 0.02 | H90: =G90*1000 -> 20 | I90: 280000 | J90: 360000 | K90: 0.7 | L90: =K90*I90+(1-K90)*J90 -> 304000 | M90: 0.7 | N90: N | O90: Sublimite dentro de Estomatologia; forte anti-selecção → carência 180 dias.
B91: Óptica — Lentes e Armações | C91: OPT | D91: Extensão | E91: pares/vida/ano | F91: M|18-35 | G91: 0.22 | H91: =G91*1000 -> 220 | I91: 95000 | J91: 120000 | K91: 0.7 | L91: =K91*I91+(1-K91)*J91 -> 102500 | M91: 0.5 | N91: N | O91: Renovação típica de 2 em 2 anos.
B92: Medicina Preventiva e Check-up Anual | C92: PREV | D92: Extensão | E92: check-ups/vida/ano | F92: M|18-35 | G92: 0.55 | H92: =G92*1000 -> 550 | I92: 75000 | J92: 95000 | K92: 0.95 | L92: =K92*I92+(1-K92)*J92 -> 76000 | M92: 0.3 | N92: N | O92: Taxa de adesão ≈55%; pacote análises + ECG + consulta.
B93: Evacuação Médica e Cobertura no Estrangeiro | C93: EVAC | D93: Extensão | E93: evacuações/vida/ano | F93: M|18-35 | G93: 0.0012 | H93: =G93*1000 -> 1.2 | I93: =evac_usd*fx_usd -> 44700960 | J93: =evac_usd*fx_usd -> 44700960 | K93: 1 | L93: =K93*I93+(1-K93)*J93 -> 44700960 | M93: 1 | N93: N | O93: Destinos habituais: África do Sul, Namíbia, Portugal. Custo em USD × câmbio (risco cambial integral).
B94: Doenças Graves — Oncologia | C94: ONCO | D94: Extensão | E94: casos/vida/ano | F94: M|18-35 | G94: 0.00055 | H94: =G94*1000 -> 0.55 | I94: 16000000 | J94: 22000000 | K94: 0.6 | L94: =K94*I94+(1-K94)*J94 -> 18400000 | M94: 1 | N94: N | O94: Oferta oncológica nacional limitada (radioterapia escassa) → elevado recurso ao estrangeiro.
B95: Doenças Crónicas — Hemodiálise | C95: HEMO | D95: Extensão | E95: doentes/vida/ano | F95: M|18-35 | G95: 0.00025 | H95: =G95*1000 -> 0.25 | I95: =hemo_ses*hemo_R -> 14040000 | J95: =hemo_ses*hemo_L -> 17160000 | K95: 0.9 | L95: =K95*I95+(1-K95)*J95 -> 14352000 | M95: 0.4 | N95: N | O95: Prevalência IRC terminal segurada; custo anual = sessões × preço/sessão.
B97: D2. Parâmetros auxiliares de severidade | C97: Código | D97: Valor | E97: Racional
B98: Parto normal — Rede (Kz) | C98: pn_R | D98: 520000 | E98: Pacote parto normal 48h, clínica privada Luanda
B99: Parto normal — Livre escolha (Kz) | C99: pn_L | D99: 680000
B100: Cesariana — Rede (Kz) | C100: pc_R | D100: 1350000 | E100: Pacote cesariana 72–96h
B101: Cesariana — Livre escolha (Kz) | C101: pc_L | D101: 1750000
B102: Taxa de cesarianas no sector privado | C102: tx_ces | D102: 0.38 | E102: Prática privada urbana muito acima da recomendação OMS (10–15%)
B103: Hemodiálise — sessões por ano | C103: hemo_ses | D103: 156 | E103: 3 sessões/semana × 52
B104: Hemodiálise — custo por sessão Rede (Kz) | C104: hemo_R | D104: 90000
B105: Hemodiálise — custo por sessão Livre escolha (Kz) | C105: hemo_L | D105: 110000
B106: Evacuação — custo médio por caso (USD) | C106: evac_usd | D106: 48000 | E106: Ambulância aérea + tratamento + estadia (RSA/Namíbia/Portugal)
B107: Duração média internamento médico (dias) | C107: los_int | D107: 4
B108: Duração média internamento cirúrgico (dias) | C108: los_cir | D108: 2.5
B109: Preço médio diária de quarto na rede (Kz) | C109: room_ref | D109: 110000 | E109: Usado para apurar a dedução do sublimite de quarto/dia por plano
...

Sheet Matriz_SAU
A1: MATRIZ TARIFÁRIA SAU — SEGURO DE SAÚDE INDIVIDUAL E FAMILIAR | TARIFAÇÃO A CUSTO TÉCNICO
A2: Construção da tarifa por Pessoa Segura / anuidade, por Plano (Base = Hospitalização; Conforto = Médio; Premium = Superior) e por cobertura. Estatuto: B = base incluída, O = opcional (extensão modular), — = não disponível. Capitais conforme ficha técnica SAU (editáveis).
A3: Parâmetros aplicados → | B3: σ | C3: =sig_SAU -> 0.08 | D3: e_a+e_c+m | E3: =load_SAU -> 0.3 | F3: Impostos | G3: =tax_SAU -> 0.01 | H3: Trend | I3: =f_trend -> 1.182194
A4: Fórmulas: Prémio Puro = λ × μ ajustado × Trend × Factor LEV | Prémio de Risco Técnico = Prémio Puro × (1+σ) | Prémio Comercial Bruto = PRT / (1 − (e_a+e_c+m)) | Prémio Total = PCB × (1 + impostos). Valores por Pessoa Segura/anuidade na célula de referência da cobertura (ver Premissas §D).
A5: Chave | B5: Plano / Categoria | C5: Código | D5: Cobertura | E5: Grupo | F5: Estatuto (B/O/—) | G5: Capital / Sublimite anual (Kz) | H5: Frequência λ | I5: μ Ponderado (Kz) | J5: Factor de Rede | K5: Dedução sublimite quarto (Kz) | L5: μ Ajustado (Kz) | M5: Factor Trend | N5: Custo médio por sinistrado (Kz) | O5: CV | P5: σ ln | Q5: μ ln | R5: Factor Limitação de Capital (LEV) | S5: PRÉMIO PURO (Kz) | T5: Carregamento Volatilidade σ (Kz) | U5: PRÉMIO DE RISCO TÉCNICO (Kz) | V5: PRÉMIO COMERCIAL BRUTO (Kz) | W5: Despesas Gestão e_a (Kz) | X5: Comissões e_c (Kz) | Y5: Margem m (Kz) | Z5: Impostos e Taxas (Kz) | AA5: PRÉMIO TOTAL ANUAL (Kz) | AB5: Taxa de Risco Pura (‰ do capital)
A6: =B6&"|"&C6 -> Base|HOSP_INT | B6: Base | C6: HOSP_INT | D6: =INDEX(Cov_Nome,MATCH(C6,Cov_Cod,0)) -> Internamento Hospitalar Médico (incl. malária grave) | E6: =INDEX(Cov_Grupo,MATCH(C6,Cov_Cod,0)) -> Principal | F6: B | G6: 5000000 | H6: =INDEX(Cov_Lambda,MATCH(C6,Cov_Cod,0)) -> 0.045 | I6: =INDEX(Cov_Mu,MATCH(C6,Cov_Cod,0)) -> 854500 | J6: =IF(INDEX(Cov_FR,MATCH(C6,Cov_Cod,0))="S",INDEX(PF_Factor,MATCH("SAU|"&B6,PF_Key,0)),1) -> 0.85 | K6: =IF(C6="HOSP_INT",los_int,IF(C6="HOSP_CIR",los_cir,0))*MAX(0,room_ref*J6-INDEX(PF_Room,MATCH("SAU|"&B6,PF_Key,0))) -> 74000 | L6: =MAX(0,I6*J6-K6) -> 652325 | M6: =f_trend -> 1.182194 | N6: =H6*L6*M6/(1-EXP(-H6)) -> 788656.26 | O6: =INDEX(Cov_CV,MATCH(C6,Cov_Cod,0)) -> 1.5 | P6: =SQRT(LN(1+O6^2)) -> 1.0856588 | Q6: =LN(N6)-P6^2/2 -> 12.988758 | R6: =IF(G6<=0,1,NORMSDIST((LN(G6)-Q6-P6^2)/P6)+G6/N6*(1-NORMSDIST((LN(G6)-Q6)/P6))) -> 0.95535503 | S6: =IF(F6="—",0,H6*L6*M6*R6) -> 33153.553 | T6: =S6*sig_SAU -> 2652.2843 | U6: =S6+T6 -> 35805.838 | V6: =U6/(1-load_SAU) -> 51151.197 | W6: =V6*ea_SAU -> 6649.6556 | X6: =V6*ec_SAU -> 6138.1436 | Y6: =V6*m_SAU -> 2557.5598 | Z6: =V6*tax_SAU -> 511.51197 | AA6: =V6+Z6 -> 51662.709 | AB6: =IF(G6>0,S6/G6*1000,"n.a.") -> 6.6307107
A7: =B7&"|"&C7 -> Base|HOSP_CIR | B7: Base | C7: HOSP_CIR | D7: =INDEX(Cov_Nome,MATCH(C7,Cov_Cod,0)) -> Cirurgia (com internamento e de ambulatório) | E7: =INDEX(Cov_Grupo,MATCH(C7,Cov_Cod,0)) -> Principal | F7: B | G7: 5000000 | H7: =INDEX(Cov_Lambda,MATCH(C7,Cov_Cod,0)) -> 0.024 | I7: =INDEX(Cov_Mu,MATCH(C7,Cov_Cod,0)) -> 2032500 | J7: =IF(INDEX(Cov_FR,MATCH(C7,Cov_Cod,0))="S",INDEX(PF_Factor,MATCH("SAU|"&B7,PF_Key,0)),1) -> 0.85 | K7: =IF(C7="HOSP_INT",los_int,IF(C7="HOSP_CIR",los_cir,0))*MAX(0,room_ref*J7-INDEX(PF_Room,MATCH("SAU|"&B7,PF_Key,0))) -> 46250 | L7: =MAX(0,I7*J7-K7) -> 1681375 | M7: =f_trend -> 1.182194 | N7: =H7*L7*M7/(1-EXP(-H7)) -> 2011659.4 | O7: =INDEX(Cov_CV,MATCH(C7,Cov_Cod,0)) -> 1.3 | P7: =SQRT(LN(1+O7^2)) -> 0.99475685 | Q7: =LN(N7)-P7^2/2 -> 14.0197 | R7: =IF(G7<=0,1,NORMSDIST((LN(G7)-Q7-P7^2)/P7)+G7/N7*(1-NORMSDIST((LN(G7)-Q7)/P7))) -> 0.85804276 | S7: =IF(F7="—",0,H7*L7*M7*R7) -> 40932.994 | T7: =S7*sig_SAU -> 3274.6395 | U7: =S7+T7 -> 44207.633 | V7: =U7/(1-load_SAU) -> 63153.762 | W7: =V7*ea_SAU -> 8209.989 | X7: =V7*ec_SAU -> 7578.4514 | Y7: =V7*m_SAU -> 3157.6881 | Z7: =V7*tax_SAU -> 631.53762 | AA7: =V7+Z7 -> 63785.3 | AB7: =IF(G7>0,S7/G7*1000,"n.a.") -> 8.1865988
A8: =B8&"|"&C8 -> Base|HOSP_UCI | B8: Base | C8: HOSP_UCI | D8: =INDEX(Cov_Nome,MATCH(C8,Cov_Cod,0)) -> Cuidados Intensivos (UCI) | E8: =INDEX(Cov_Grupo,MATCH(C8,Cov_Cod,0)) -> Principal | F8: B | G8: =INDEX(PF_UCI,MATCH("SAU|"&B8,PF_Key,0)) -> 2500000 | H8: =INDEX(Cov_Lambda,MATCH(C8,Cov_Cod,0)) -> 0.0035 | I8: =INDEX(Cov_Mu,MATCH(C8,Cov_Cod,0)) -> 2835000 | J8: =IF(INDEX(Cov_FR,MATCH(C8,Cov_Cod,0))="S",INDEX(PF_Factor,MATCH("SAU|"&B8,PF_Key,0)),1) -> 0.85 | K8: =IF(C8="HOSP_INT",los_int,IF(C8="HOSP_CIR",los_cir,0))*MAX(0,room_ref*J8-INDEX(PF_Room,MATCH("SAU|"&B8,PF_Key,0))) -> 0 | L8: =MAX(0,I8*J8-K8) -> 2409750 | M8: =f_trend -> 1.182194 | N8: =H8*L8*M8/(1-EXP(-H8)) -> 2853780.3 | O8: =INDEX(Cov_CV,MATCH(C8,Cov_Cod,0)) -> 1.2 | P8: =SQRT(LN(1+O8^2)) -> 0.94445648 | Q8: =LN(N8)-P8^2/2 -> 14.418156 | R8: =IF(G8<=0,1,NORMSDIST((LN(G8)-Q8-P8^2)/P8)+G8/N8*(1-NORMSDIST((LN(G8)-Q8)/P8))) -> 0.59420086 | S8: =IF(F8="—",0,H8*L8*M8*R8) -> 5924.6412 | T8: =S8*sig_SAU -> 473.9713 | U8: =S8+T8 -> 6398.6125 | V8: =U8/(1-load_SAU) -> 9140.875 | W8: =V8*ea_SAU -> 1188.3138 | X8: =V8*ec_SAU -> 1096.905 | Y8: =V8*m_SAU -> 457.04375 | Z8: =V8*tax_SAU -> 91.40875 | AA8: =V8+Z8 -> 9232.2838 | AB8: =IF(G8>0,S8/G8*1000,"n.a.") -> 2.3698565
A9: =B9&"|"&C9 -> Base|AMB_CONS | B9: Base | C9: AMB_CONS | D9: =INDEX(Cov_Nome,MATCH(C9,Cov_Cod,0)) -> Consultas de Clínica Geral e Especialidade (incl. teleconsulta) | E9: =INDEX(Cov_Grupo,MATCH(C9,Cov_Cod,0)) -> Principal | F9: O | G9: 1500000 | H9: =INDEX(Cov_Lambda,MATCH(C9,Cov_Cod,0)) -> 2.6 | I9: =INDEX(Cov_Mu,MATCH(C9,Cov_Cod,0)) -> 24000 | J9: =IF(INDEX(Cov_FR,MATCH(C9,Cov_Cod,0))="S",INDEX(PF_Factor,MATCH("SAU|"&B9,PF_Key,0)),1) -> 0.85 | K9: =IF(C9="HOSP_INT",los_int,IF(C9="HOSP_CIR",los_cir,0))*MAX(0,room_ref*J9-INDEX(PF_Room,MATCH("SAU|"&B9,PF_Key,0))) -> 0 | L9: =MAX(0,I9*J9-K9) -> 20400 | M9: =f_trend -> 1.182194 | N9: =H9*L9*M9/(1-EXP(-H9)) -> 67734.45 | O9: =INDEX(Cov_CV,MATCH(C9,Cov_Cod,0)) -> 1 | P9: =SQRT(LN(1+O9^2)) -> 0.83255461 | Q9: =LN(N9)-P9^2/2 -> 10.776777 | R9: =IF(G9<=0,1,NORMSDIST((LN(G9)-Q9-P9^2)/P9)+G9/N9*(1-NORMSDIST((LN(G9)-Q9)/P9))) -> 0.9999138 | S9: =IF(F9="—",0,H9*L9*M9*R9) -> 62698.165 | T9: =S9*sig_SAU -> 5015.8532 | U9: =S9+T9 -> 67714.018 | V9: =U9/(1-load_SAU) -> 96734.311 | W9: =V9*ea_SAU -> 12575.46 | X9: =V9*ec_SAU -> 11608.117 | Y9: =V9*m_SAU -> 4836.7156 | Z9: =V9*tax_SAU -> 967.34311 | AA9: =V9+Z9 -> 97701.654 | AB9: =IF(G9>0,S9/G9*1000,"n.a.") -> 41.798776
A10: =B10&"|"&C10 -> Base|AMB_MCDT | B10: Base | C10: AMB_MCDT | D10: =INDEX(Cov_Nome,MATCH(C10,Cov_Cod,0)) -> MCDT — Exames, Análises e Imagiologia | E10: =INDEX(Cov_Grupo,MATCH(C10,Cov_Cod,0)) -> Principal | F10: O | G10: 1500000 | H10: =INDEX(Cov_Lambda,MATCH(C10,Cov_Cod,0)) -> 3.8 | I10: =INDEX(Cov_Mu,MATCH(C10,Cov_Cod,0)) -> 14600 | J10: =IF(INDEX(Cov_FR,MATCH(C10,Cov_Cod,0))="S",INDEX(PF_Factor,MATCH("SAU|"&B10,PF_Key,0)),1) -> 0.85 | K10: =IF(C10="HOSP_INT",los_int,IF(C10="HOSP_CIR",los_cir,0))*MAX(0,room_ref*J10-INDEX(PF_Room,MATCH("SAU|"&B10,PF_Key,0))) -> 0 | L10: =MAX(0,I10*J10-K10) -> 12410 | M10: =f_trend -> 1.182194 | N10: =H10*L10*M10/(1-EXP(-H10)) -> 57025.612 | O10: =INDEX(Cov_CV,MATCH(C10,Cov_Cod,0)) -> 1.5 | P10: =SQRT(LN(1+O10^2)) -> 1.0856588 | Q10: =LN(N10)-P10^2/2 -> 10.361928 | R10: =IF(G10<=0,1,NORMSDIST((LN(G10)-Q10-P10^2)/P10)+G10/N10*(1-NORMSDIST((LN(G10)-Q10)/P10))) -> 0.99820307 | S10: =IF(F10="—",0,H10*L10*M10*R10) -> 55649.726 | T10: =S10*sig_SAU -> 4451.9781 | U10: =S10+T10 -> 60101.704 | V10: =U10/(1-load_SAU) -> 85859.577 | W10: =V10*ea_SAU -> 11161.745 | X10: =V10*ec_SAU -> 10303.149 | Y10: =V10*m_SAU -> 4292.9789 | Z10: =V10*tax_SAU -> 858.59577 | AA10: =V10+Z10 -> 86718.173 | AB10: =IF(G10>0,S10/G10*1000,"n.a.") -> 37.099817
A11: =B11&"|"&C11 -> Base|MAL | B11: Base | C11: MAL | D11: =INDEX(Cov_Nome,MATCH(C11,Cov_Cod,0)) -> Malária e Doenças Endémicas (ambulatório) | E11: =INDEX(Cov_Grupo,MATCH(C11,Cov_Cod,0)) -> Principal | F11: O | G11: 1500000 | H11: =INDEX(Cov_Lambda,MATCH(C11,Cov_Cod,0)) -> 0.3 | I11: =INDEX(Cov_Mu,MATCH(C11,Cov_Cod,0)) -> 36500 | J11: =IF(INDEX(Cov_FR,MATCH(C11,Cov_Cod,0))="S",INDEX(PF_Factor,MATCH("SAU|"&B11,PF_Key,0)),1) -> 0.85 | K11: =IF(C11="HOSP_INT",los_int,IF(C11="HOSP_CIR",los_cir,0))*MAX(0,room_ref*J11-INDEX(PF_Room,MATCH("SAU|"&B11,PF_Key,0))) -> 0 | L11: =MAX(0,I11*J11-K11) -> 31025 | M11: =f_trend -> 1.182194 | N11: =H11*L11*M11/(1-EXP(-H11)) -> 42453.874 | O11: =INDEX(Cov_CV,MATCH(C11,Cov_Cod,0)) -> 0.8 | P11: =SQRT(LN(1+O11^2)) -> 0.70334646 | Q11: =LN(N11)-P11^2/2 -> 10.408825 | R11: =IF(G11<=0,1,NORMSDIST((LN(G11)-Q11-P11^2)/P11)+G11/N11*(1-NORMSDIST((LN(G11)-Q11)/P11))) -> 0.99999985 | S11: =IF(F11="—",0,H11*L11*M11*R11) -> 11003.269 | T11: =S11*sig_SAU -> 880.26152 | U11: =S11+T11 -> 11883.531 | V11: =U11/(1-load_SAU) -> 16976.472 | W11: =V11*ea_SAU -> 2206.9414 | X11: =V11*ec_SAU -> 2037.1767 | Y11: =V11*m_SAU -> 848.82361 | Z11: =V11*tax_SAU -> 169.76472 | AA11: =V11+Z11 -> 17146.237 | AB11: =IF(G11>0,S11/G11*1000,"n.a.") -> 7.3355127
A12: =B12&"|"&C12 -> Base|MAT | B12: Base | C12: MAT | D12: =INDEX(Cov_Nome,MATCH(C12,Cov_Cod,0)) -> Maternidade e Parto (Normal e Cesariana) | E12: =INDEX(Cov_Grupo,MATCH(C12,Cov_Cod,0)) -> Principal | F12: — | G12: 0 | H12: =INDEX(Cov_Lambda,MATCH(C12,Cov_Cod,0)) -> 0.075 | I12: =INDEX(Cov_Mu,MATCH(C12,Cov_Cod,0)) -> 885640 | J12: =IF(INDEX(Cov_FR,MATCH(C12,Cov_Cod,0))="S",INDEX(PF_Factor,MATCH("SAU|"&B12,PF_Key,0)),1) -> 0.85 | K12: =IF(C12="HOSP_INT",los_int,IF(C12="HOSP_CIR",los_cir,0))*MAX(0,room_ref*J12-INDEX(PF_Room,MATCH("SAU|"&B12,PF_Key,0))) -> 0 | L12: =MAX(0,I12*J12-K12) -> 752794 | M12: =f_trend -> 1.182194 | N12: =H12*L12*M12/(1-EXP(-H12)) -> 923738.74 | O12: =INDEX(Cov_CV,MATCH(C12,Cov_Cod,0)) -> 0.5 | P12: =SQRT(LN(1+O12^2)) -> 0.47238073 | Q12: =LN(N12)-P12^2/2 -> 13.624613 | R12: =IF(G12<=0,1,NORMSDIST((LN(G12)-Q12-P12^2)/P12)+G12/N12*(1-NORMSDIST((LN(G12)-Q12)/P12))) -> 1 | S12: =IF(F12="—",0,H12*L12*M12*R12) -> 0 | T12: =S12*sig_SAU -> 0 | U12: =S12+T12 -> 0 | V12: =U12/(1-load_SAU) -> 0 | W12: =V12*ea_SAU -> 0 | X12: =V12*ec_SAU -> 0 | Y12: =V12*m_SAU -> 0 | Z12: =V12*tax_SAU -> 0 | AA12: =V12+Z12 -> 0 | AB12: =IF(G12>0,S12/G12*1000,"n.a.") -> n.a.
A13: =B13&"|"&C13 -> Base|URG | B13: Base | C13: URG | D13: =INDEX(Cov_Nome,MATCH(C13,Cov_Cod,0)) -> Urgência Hospitalar | E13: =INDEX(Cov_Grupo,MATCH(C13,Cov_Cod,0)) -> Principal | F13: B | G13: 250000 | H13: =INDEX(Cov_Lambda,MATCH(C13,Cov_Cod,0)) -> 0.42 | I13: =INDEX(Cov_Mu,MATCH(C13,Cov_Cod,0)) -> 43300 | J13: =IF(INDEX(Cov_FR,MATCH(C13,Cov_Cod,0))="S",INDEX(PF_Factor,MATCH("SAU|"&B13,PF_Key,0)),1) -> 0.85 | K13: =IF(C13="HOSP_INT",los_int,IF(C13="HOSP_CIR",los_cir,0))*MAX(0,room_ref*J13-INDEX(PF_Room,MATCH("SAU|"&B13,PF_Key,0))) -> 0 | L13: =MAX(0,I13*J13-K13) -> 36805 | M13: =f_trend -> 1.182194 | N13: =H13*L13*M13/(1-EXP(-H13)) -> 53285.621 | O13: =INDEX(Cov_CV,MATCH(C13,Cov_Cod,0)) -> 1 | P13: =SQRT(LN(1+O13^2)) -> 0.83255461 | Q13: =LN(N13)-P13^2/2 -> 10.536848 | R13: =IF(G13<=0,1,NORMSDIST((LN(G13)-Q13-P13^2)/P13)+G13/N13*(1-NORMSDIST((LN(G13)-Q13)/P13))) -> 0.97914522 | S13: =IF(F13="—",0,H13*L13*M13*R13) -> 17893.363 | T13: =S13*sig_SAU -> 1431.469 | U13: =S13+T13 -> 19324.832 | V13: =U13/(1-load_SAU) -> 27606.903 | W13: =V13*ea_SAU -> 3588.8974 | X13: =V13*ec_SAU -> 3312.8283 | Y13: =V13*m_SAU -> 1380.3451 | Z13: =V13*tax_SAU -> 276.06903 | AA13: =V13+Z13 -> 27882.972 | AB13: =IF(G13>0,S13/G13*1000,"n.a.") -> 71.573452
A14: =B14&"|"&C14 -> Base|AMBUL | B14: Base | C14: AMBUL | D14: =INDEX(Cov_Nome,MATCH(C14,Cov_Cod,0)) -> Transporte em Ambulância / Emergência Médica | E14: =INDEX(Cov_Grupo,MATCH(C14,Cov_Cod,0)) -> Principal | F14: B | G14: 150000 | H14: =INDEX(Cov_Lambda,MATCH(C14,Cov_Cod,0)) -> 0.018 | I14: =INDEX(Cov_Mu,MATCH(C14,Cov_Cod,0)) -> 76000 | J14: =IF(INDEX(Cov_FR,MATCH(C14,Cov_Cod,0))="S",INDEX(PF_Factor,MATCH("SAU|"&B14,PF_Key,0)),1) -> 1 | K14: =IF(C14="HOSP_INT",los_int,IF(C14="HOSP_CIR",los_cir,0))*MAX(0,room_ref*J14-INDEX(PF_Room,MATCH("SAU|"&B14,PF_Key,0))) -> 0 | L14: =MAX(0,I14*J14-K14) -> 76000 | M14: =f_trend -> 1.182194 | N14: =H14*L14*M14/(1-EXP(-H14)) -> 90657.791 | O14: =INDEX(Cov_CV,MATCH(C14,Cov_Cod,0)) -> 0.6 | P14: =SQRT(LN(1+O14^2)) -> 0.55451303 | Q14: =LN(N14)-P14^2/2 -> 11.261105 | R14: =IF(G14<=0,1,NORMSDIST((LN(G14)-Q14-P14^2)/P14)+G14/N14*(1-NORMSDIST((LN(G14)-Q14)/P14))) -> 0.93106611 | S14: =IF(F14="—",0,H14*L14*M14*R14) -> 1505.7587 | T14: =S14*sig_SAU -> 120.46069 | U14: =S14+T14 -> 1626.2193 | V14: =U14/(1-load_SAU) -> 2323.1705 | W14: =V14*ea_SAU -> 302.01216 | X14: =V14*ec_SAU -> 278.78046 | Y14: =V14*m_SAU -> 116.15852 | Z14: =V14*tax_SAU -> 23.231705 | AA14: =V14+Z14 -> 2346.4022 | AB14: =IF(G14>0,S14/G14*1000,"n.a.") -> 10.038391
A15: =B15&"|"&C15 -> Base|MED | B15: Base | C15: MED | D15: =INDEX(Cov_Nome,MATCH(C15,Cov_Cod,0)) -> Medicamentos em Ambulatório (Farmácia) | E15: =INDEX(Cov_Grupo,MATCH(C15,Cov_Cod,0)) -> Principal | F15: — | G15: 0 | H15: =INDEX(Cov_Lambda,MATCH(C15,Cov_Cod,0)) -> 3.4 | I15: =INDEX(Cov_Mu,MATCH(C15,Cov_Cod,0)) -> 17400 | J15: =IF(INDEX(Cov_FR,MATCH(C15,Cov_Cod,0))="S",INDEX(PF_Factor,MATCH("SAU|"&B15,PF_Key,0)),1) -> 1 | K15: =IF(C15="HOSP_INT",los_int,IF(C15="HOSP_CIR",los_cir,0))*MAX(0,room_ref*J15-INDEX(PF_Room,MATCH("SAU|"&B15,PF_Key,0))) -> 0 | L15: =MAX(0,I15*J15-K15) -> 17400 | M15: =f_trend -> 1.182194 | N15: =H15*L15*M15/(1-EXP(-H15)) -> 72353.262 | O15: =INDEX(Cov_CV,MATCH(C15,Cov_Cod,0)) -> 1.2 | P15: =SQRT(LN(1+O15^2)) -> 0.94445648 | Q15: =LN(N15)-P15^2/2 -> 10.743317 | R15: =IF(G15<=0,1,NORMSDIST((LN(G15)-Q15-P15^2)/P15)+G15/N15*(1-NORMSDIST((LN(G15)-Q15)/P15))) -> 1 | S15: =IF(F15="—",0,H15*L15*M15*R15) -> 0 | T15: =S15*sig_SAU -> 0 | U15: =S15+T15 -> 0 | V15: =U15/(1-load_SAU) -> 0 | W15: =V15*ea_SAU -> 0 | X15: =V15*ec_SAU -> 0 | Y15: =V15*m_SAU -> 0 | Z15: =V15*tax_SAU -> 0 | AA15: =V15+Z15 -> 0 | AB15: =IF(G15>0,S15/G15*1000,"n.a.") -> n.a.
A16: =B16&"|"&C16 -> Base|DENT | B16: Base | C16: DENT | D16: =INDEX(Cov_Nome,MATCH(C16,Cov_Cod,0)) -> Estomatologia (tratamentos) | E16: =INDEX(Cov_Grupo,MATCH(C16,Cov_Cod,0)) -> Extensão | F16: — | G16: 0 | H16: =INDEX(Cov_Lambda,MATCH(C16,Cov_Cod,0)) -> 0.85 | I16: =INDEX(Cov_Mu,MATCH(C16,Cov_Cod,0)) -> 34500 | J16: =IF(INDEX(Cov_FR,MATCH(C16,Cov_Cod,0))="S",INDEX(PF_Factor,MATCH("SAU|"&B16,PF_Key,0)),1) -> 0.85 | K16: =IF(C16="HOSP_INT",los_int,IF(C16="HOSP_CIR",los_cir,0))*MAX(0,room_ref*J16-INDEX(PF_Room,MATCH("SAU|"&B16,PF_Key,0))) -> 0 | L16: =MAX(0,I16*J16-K16) -> 29325 | M16: =f_trend -> 1.182194 | N16: =H16*L16*M16/(1-EXP(-H16)) -> 51464.254 | O16: =INDEX(Cov_CV,MATCH(C16,Cov_Cod,0)) -> 1 | P16: =SQRT(LN(1+O16^2)) -> 0.83255461 | Q16: =LN(N16)-P16^2/2 -> 10.502069 | R16: =IF(G16<=0,1,NORMSDIST((LN(G16)-Q16-P16^2)/P16)+G16/N16*(1-NORMSDIST((LN(G16)-Q16)/P16))) -> 1 | S16: =IF(F16="—",0,H16*L16*M16*R16) -> 0 | T16: =S16*sig_SAU -> 0 | U16: =S16+T16 -> 0 | V16: =U16/(1-load_SAU) -> 0 | W16: =V16*ea_SAU -> 0 | X16: =V16*ec_SAU -> 0 | Y16: =V16*m_SAU -> 0 | Z16: =V16*tax_SAU -> 0 | AA16: =V16+Z16 -> 0 | AB16: =IF(G16>0,S16/G16*1000,"n.a.") -> n.a.
A17: =B17&"|"&C17 -> Base|PROT | B17: Base | C17: PROT | D17: =INDEX(Cov_Nome,MATCH(C17,Cov_Cod,0)) -> Próteses Dentárias | E17: =INDEX(Cov_Grupo,MATCH(C17,Cov_Cod,0)) -> Extensão | F17: — | G17: 0 | H17: =INDEX(Cov_Lambda,MATCH(C17,Cov_Cod,0)) -> 0.02 | I17: =INDEX(Cov_Mu,MATCH(C17,Cov_Cod,0)) -> 304000 | J17: =IF(INDEX(Cov_FR,MATCH(C17,Cov_Cod,0))="S",INDEX(PF_Factor,MATCH("SAU|"&B17,PF_Key,0)),1) -> 1 | K17: =IF(C17="HOSP_INT",los_int,IF(C17="HOSP_CIR",los_cir,0))*MAX(0,room_ref*J17-INDEX(PF_Room,MATCH("SAU|"&B17,PF_Key,0))) -> 0 | L17: =MAX(0,I17*J17-K17) -> 304000 | M17: =f_trend -> 1.182194 | N17: =H17*L17*M17/(1-EXP(-H17)) -> 362992.83 | O17: =INDEX(Cov_CV,MATCH(C17,Cov_Cod,0)) -> 0.7 | P17: =SQRT(LN(1+O17^2)) -> 0.63148723 | Q17: =LN(N17)-P17^2/2 -> 12.60275 | R17: =IF(G17<=0,1,NORMSDIST((LN(G17)-Q17-P17^2)/P17)+G17/N17*(1-NORMSDIST((LN(G17)-Q17)/P17))) -> 1 | S17: =IF(F17="—",0,H17*L17*M17*R17) -> 0 | T17: =S17*sig_SAU -> 0 | U17: =S17+T17 -> 0 | V17: =U17/(1-load_SAU) -> 0 | W17: =V17*ea_SAU -> 0 | X17: =V17*ec_SAU -> 0 | Y17: =V17*m_SAU -> 0 | Z17: =V17*tax_SAU -> 0 | AA17: =V17+Z17 -> 0 | AB17: =IF(G17>0,S17/G17*1000,"n.a.") -> n.a.
A18: =B18&"|"&C18 -> Base|OPT | B18: Base | C18: OPT | D18: =INDEX(Cov_Nome,MATCH(C18,Cov_Cod,0)) -> Óptica — Lentes e Armações | E18: =INDEX(Cov_Grupo,MATCH(C18,Cov_Cod,0)) -> Extensão | F18: — | G18: 0 | H18: =INDEX(Cov_Lambda,MATCH(C18,Cov_Cod,0)) -> 0.22 | I18: =INDEX(Cov_Mu,MATCH(C18,Cov_Cod,0)) -> 102500 | J18: =IF(INDEX(Cov_FR,MATCH(C18,Cov_Cod,0))="S",INDEX(PF_Factor,MATCH("SAU|"&B18,PF_Key,0)),1) -> 1 | K18: =IF(C18="HOSP_INT",los_int,IF(C18="HOSP_CIR",los_cir,0))*MAX(0,room_ref*J18-INDEX(PF_Room,MATCH("SAU|"&B18,PF_Key,0))) -> 0 | L18: =MAX(0,I18*J18-K18) -> 102500 | M18: =f_trend -> 1.182194 | N18: =H18*L18*M18/(1-EXP(-H18)) -> 134992.47 | O18: =INDEX(Cov_CV,MATCH(C18,Cov_Cod,0)) -> 0.5 | P18: =SQRT(LN(1+O18^2)) -> 0.47238073 | Q18: =LN(N18)-P18^2/2 -> 11.701402 | R18: =IF(G18<=0,1,NORMSDIST((LN(G18)-Q18-P18^2)/P18)+G18/N18*(1-NORMSDIST((LN(G18)-Q18)/P18))) -> 1 | S18: =IF(F18="—",0,H18*L18*M18*R18) -> 0 | T18: =S18*sig_SAU -> 0 | U18: =S18+T18 -> 0 | V18: =U18/(1-load_SAU) -> 0 | W18: =V18*ea_SAU -> 0 | X18: =V18*ec_SAU -> 0 | Y18: =V18*m_SAU -> 0 | Z18: =V18*tax_SAU -> 0 | AA18: =V18+Z18 -> 0 | AB18: =IF(G18>0,S18/G18*1000,"n.a.") -> n.a.
A19: =B19&"|"&C19 -> Base|PREV | B19: Base | C19: PREV | D19: =INDEX(Cov_Nome,MATCH(C19,Cov_Cod,0)) -> Medicina Preventiva e Check-up Anual | E19: =INDEX(Cov_Grupo,MATCH(C19,Cov_Cod,0)) -> Extensão | F19: — | G19: 0 | H19: =INDEX(Cov_Lambda,MATCH(C19,Cov_Cod,0)) -> 0.55 | I19: =INDEX(Cov_Mu,MATCH(C19,Cov_Cod,0)) -> 76000 | J19: =IF(INDEX(Cov_FR,MATCH(C19,Cov_Cod,0))="S",INDEX(PF_Factor,MATCH("SAU|"&B19,PF_Key,0)),1) -> 1 | K19: =IF(C19="HOSP_INT",los_int,IF(C19="HOSP_CIR",los_cir,0))*MAX(0,room_ref*J19-INDEX(PF_Room,MATCH("SAU|"&B19,PF_Key,0))) -> 0 | L19: =MAX(0,I19*J19-K19) -> 76000 | M19: =f_trend -> 1.182194 | N19: =H19*L19*M19/(1-EXP(-H19)) -> 116808.15 | O19: =INDEX(Cov_CV,MATCH(C19,Cov_Cod,0)) -> 0.3 | P19: =SQRT(LN(1+O19^2)) -> 0.29356038 | Q19: =LN(N19)-P19^2/2 -> 11.625199 | R19: =IF(G19<=0,1,NORMSDIST((LN(G19)-Q19-P19^2)/P19)+G19/N19*(1-NORMSDIST((LN(G19)-Q19)/P19))) -> 1 | S19: =IF(F19="—",0,H19*L19*M19*R19) -> 0 | T19: =S19*sig_SAU -> 0 | U19: =S19+T19 -> 0 | V19: =U19/(1-load_SAU) -> 0 | W19: =V19*ea_SAU -> 0 | X19: =V19*ec_SAU -> 0 | Y19: =V19*m_SAU -> 0 | Z19: =V19*tax_SAU -> 0 | AA19: =V19+Z19 -> 0 | AB19: =IF(G19>0,S19/G19*1000,"n.a.") -> n.a.
A20: =B20&"|"&C20 -> Base|EVAC | B20: Base | C20: EVAC | D20: =INDEX(Cov_Nome,MATCH(C20,Cov_Cod,0)) -> Evacuação Médica e Cobertura no Estrangeiro | E20: =INDEX(Cov_Grupo,MATCH(C20,Cov_Cod,0)) -> Extensão | F20: — | G20: 0 | H20: =INDEX(Cov_Lambda,MATCH(C20,Cov_Cod,0)) -> 0.0012 | I20: =INDEX(Cov_Mu,MATCH(C20,Cov_Cod,0)) -> 44700960 | J20: =IF(INDEX(Cov_FR,MATCH(C20,Cov_Cod,0))="S",INDEX(PF_Factor,MATCH("SAU|"&B20,PF_Key,0)),1) -> 1 | K20: =IF(C20="HOSP_INT",los_int,IF(C20="HOSP_CIR",los_cir,0))*MAX(0,room_ref*J20-INDEX(PF_Room,MATCH("SAU|"&B20,PF_Key,0))) -> 0 | L20: =MAX(0,I20*J20-K20) -> 44700960 | M20: =f_trend -> 1.182194 | N20: =H20*L20*M20/(1-EXP(-H20)) -> 52876920 | O20: =INDEX(Cov_CV,MATCH(C20,Cov_Cod,0)) -> 1 | P20: =SQRT(LN(1+O20^2)) -> 0.83255461 | Q20: =LN(N20)-P20^2/2 -> 17.436904 | R20: =IF(G20<=0,1,NORMSDIST((LN(G20)-Q20-P20^2)/P20)+G20/N20*(1-NORMSDIST((LN(G20)-Q20)/P20))) -> 1 | S20: =IF(F20="—",0,H20*L20*M20*R20) -> 0 | T20: =S20*sig_SAU -> 0 | U20: =S20+T20 -> 0 | V20: =U20/(1-load_SAU) -> 0 | W20: =V20*ea_SAU -> 0 | X20: =V20*ec_SAU -> 0 | Y20: =V20*m_SAU -> 0 | Z20: =V20*tax_SAU -> 0 | AA20: =V20+Z20 -> 0 | AB20: =IF(G20>0,S20/G20*1000,"n.a.") -> n.a.
... A24: =B24&"|"&C24 -> Conforto|HOSP_CIR | B24: Conforto | C24: HOSP_CIR | D24: =INDEX(Cov_Nome,MATCH(C24,Cov_Cod,0)) -> Cirurgia (com internamento e de ambulatório) | E24: =INDEX(Cov_Grupo,MATCH(C24,Cov_Cod,0)) -> Principal | F24: B | G24: 15000000 | H24: =INDEX(Cov_Lambda,MATCH(C24,Cov_Cod,0)) -> 0.024 | I24: =INDEX(Cov_Mu,MATCH(C24,Cov_Cod,0)) -> 2032500 | J24: =IF(INDEX(Cov_FR,MATCH(C24,Cov_Cod,0))="S",INDEX(PF_Factor,MATCH("SAU|"&B24,PF_Key,0)),1) -> 1 | K24: =IF(C24="HOSP_INT",los_int,IF(C24="HOSP_CIR",los_cir,0))*MAX(0,room_ref*J24-INDEX(PF_Room,MATCH("SAU|"&B24,PF_Key,0))) -> 0 | L24: =MAX(0,I24*J24-K24) -> 2032500 | M24: =f_trend -> 1.182194 | N24: =H24*L24*M24/(1-EXP(-H24)) -> 2431758.4 | O24: =INDEX(Cov_CV,MATCH(C24,Cov_Cod,0)) -> 1.3 | P24: =SQRT(LN(1+O24^2)) -> 0.99475685 | Q24: =LN(N24)-P24^2/2 -> 14.209355 | R24: =IF(G24<=0,1,NORMSDIST((LN(G24)-Q24-P24^2)/P24)+G24/N24*(1-NORMSDIST((LN(G24)-Q24)/P24))) -> 0.97018645 | S24: =IF(F24="—",0,H24*L24*M24*R24) -> 55948.153 | T24: =S24*sig_SAU -> 4475.8522 | U24: =S24+T24 -> 60424.005 | V24: =U24/(1-load_SAU) -> 86320.007 | W24: =V24*ea_SAU -> 11221.601 | X24: =V24*ec_SAU -> 10358.401 | Y24: =V24*m_SAU -> 4316.0004 | Z24: =V24*tax_SAU -> 863.20007 | AA24: =V24+Z24 -> 87183.207 | AB24: =IF(G24>0,S24/G24*1000,"n.a.") -> 3.7298769
A25: =B25&"|"&C25 -> Conforto|HOSP_UCI | B25: Conforto | C25: HOSP_UCI | D25: =INDEX(Cov_Nome,MATCH(C25,Cov_Cod,0)) -> Cuidados Intensivos (UCI) | E25: =INDEX(Cov_Grupo,MATCH(C25,Cov_Cod,0)) -> Principal | F25: B | G25: =INDEX(PF_UCI,MATCH("SAU|"&B25,PF_Key,0)) -> 6000000 | H25: =INDEX(Cov_Lambda,MATCH(C25,Cov_Cod,0)) -> 0.0035 | I25: =INDEX(Cov_Mu,MATCH(C25,Cov_Cod,0)) -> 2835000 | J25: =IF(INDEX(Cov_FR,MATCH(C25,Cov_Cod,0))="S",INDEX(PF_Factor,MATCH("SAU|"&B25,PF_Key,0)),1) -> 1 | K25: =IF(C25="HOSP_INT",los_int,IF(C25="HOSP_CIR",los_cir,0))*MAX(0,room_ref*J25-INDEX(PF_Room,MATCH("SAU|"&B25,PF_Key,0))) -> 0 | L25: =MAX(0,I25*J25-K25) -> 2835000 | M25: =f_trend -> 1.182194 | N25: =H25*L25*M25/(1-EXP(-H25)) -> 3357388.6 | O25: =INDEX(Cov_CV,MATCH(C25,Cov_Cod,0)) -> 1.2 | P25: =SQRT(LN(1+O25^2)) -> 0.94445648 | Q25: =LN(N25)-P25^2/2 -> 14.580675 | R25: =IF(G25<=0,1,NORMSDIST((LN(G25)-Q25-P25^2)/P25)+G25/N25*(1-NORMSDIST((LN(G25)-Q25)/P25))) -> 0.80422134 | S25: =IF(F25="—",0,H25*L25*M25*R25) -> 9433.7736 | T25: =S25*sig_SAU -> 754.70189 | U25: =S25+T25 -> 10188.476 | V25: =U25/(1-load_SAU) -> 14554.965 | W25: =V25*ea_SAU -> 1892.1455 | X25: =V25*ec_SAU -> 1746.5958 | Y25: =V25*m_SAU -> 727.74825 | Z25: =V25*tax_SAU -> 145.54965 | AA25: =V25+Z25 -> 14700.515 | AB25: =IF(G25>0,S25/G25*1000,"n.a.") -> 1.5722956
A26: =B26&"|"&C26 -> Conforto|AMB_CONS | B26: Conforto | C26: AMB_CONS | D26: =INDEX(Cov_Nome,MATCH(C26,Cov_Cod,0)) -> Consultas de Clínica Geral e Especialidade (incl. teleconsulta) | E26: =INDEX(Cov_Grupo,MATCH(C26,Cov_Cod,0)) -> Principal | F26: B | G26: 3000000 | H26: =INDEX(Cov_Lambda,MATCH(C26,Cov_Cod,0)) -> 2.6 | I26: =INDEX(Cov_Mu,MATCH(C26,Cov_Cod,0)) -> 24000 | J26: =IF(INDEX(Cov_FR,MATCH(C26,Cov_Cod,0))="S",INDEX(PF_Factor,MATCH("SAU|"&B26,PF_Key,0)),1) -> 1 | K26: =IF(C26="HOSP_INT",los_int,IF(C26="HOSP_CIR",los_cir,0))*MAX(0,room_ref*J26-INDEX(PF_Room,MATCH("SAU|"&B26,PF_Key,0))) -> 0 | L26: =MAX(0,I26*J26-K26) -> 24000 | M26: =f_trend -> 1.182194 | N26: =H26*L26*M26/(1-EXP(-H26)) -> 79687.588 | O26: =INDEX(Cov_CV,MATCH(C26,Cov_Cod,0)) -> 1 | P26: =SQRT(LN(1+O26^2)) -> 0.83255461 | Q26: =LN(N26)-P26^2/2 -> 10.939296 | R26: =IF(G26<=0,1,NORMSDIST((LN(G26)-Q26-P26^2)/P26)+G26/N26*(1-NORMSDIST((LN(G26)-Q26)/P26))) -> 0.9999935 | S26: =IF(F26="—",0,H26*L26*M26*R26) -> 73768.426 | T26: =S26*sig_SAU -> 5901.4741 | U26: =S26+T26 -> 79669.9 | V26: =U26/(1-load_SAU) -> 113814.14 | W26: =V26*ea_SAU -> 14795.839 | X26: =V26*ec_SAU -> 13657.697 | Y26: =V26*m_SAU -> 5690.7072 | Z26: =V26*tax_SAU -> 1138.1414 | AA26: =V26+Z26 -> 114952.28 | AB26: =IF(G26>0,S26/G26*1000,"n.a.") -> 24.589475
A27: =B27&"|"&C27 -> Conforto|AMB_MCDT | B27: Conforto | C27: AMB_MCDT | D27: =INDEX(Cov_Nome,MATCH(C27,Cov_Cod,0)) -> MCDT — Exames, Análises e Imagiologia | E27: =INDEX(Cov_Grupo,MATCH(C27,Cov_Cod,0)) -> Principal | F27: B | G27: 3000000 | H27: =INDEX(Cov_Lambda,MATCH(C27,Cov_Cod,0)) -> 3.8 | I27: =INDEX(Cov_Mu,MATCH(C27,Cov_Cod,0)) -> 14600 | J27: =IF(INDEX(Cov_FR,MATCH(C27,Cov_Cod,0))="S",INDEX(PF_Factor,MATCH("SAU|"&B27,PF_Key,0)),1) -> 1 | K27: =IF(C27="HOSP_INT",los_int,IF(C27="HOSP_CIR",los_cir,0))*MAX(0,room_ref*J27-INDEX(PF_Room,MATCH("SAU|"&B27,PF_Key,0))) -> 0 | L27: =MAX(0,I27*J27-K27) -> 14600 | M27: =f_trend -> 1.182194 | N27: =H27*L27*M27/(1-EXP(-H27)) -> 67088.955 | O27: =INDEX(Cov_CV,MATCH(C27,Cov_Cod,0)) -> 1.5 | P27: =SQRT(LN(1+O27^2)) -> 1.0856588 | Q27: =LN(N27)-P27^2/2 -> 10.524447 | R27: =IF(G27<=0,1,NORMSDIST((LN(G27)-Q27-P27^2)/P27)+G27/N27*(1-NORMSDIST((LN(G27)-Q27)/P27))) -> 0.99962836 | S27: =IF(F27="—",0,H27*L27*M27*R27) -> 65563.748 | T27: =S27*sig_SAU -> 5245.0999 | U27: =S27+T27 -> 70808.848 | V27: =U27/(1-load_SAU) -> 101155.5 | W27: =V27*ea_SAU -> 13150.215 | X27: =V27*ec_SAU -> 12138.66 | Y27: =V27*m_SAU -> 5057.7749 | Z27: =V27*tax_SAU -> 1011.555 | AA27: =V27+Z27 -> 102167.05 | AB27: =IF(G27>0,S27/G27*1000,"n.a.") -> 21.854583
A28: =B28&"|"&C28 -> Conforto|MAL | B28: Conforto | C28: MAL | D28: =INDEX(Cov_Nome,MATCH(C28,Cov_Cod,0)) -> Malária e Doenças Endémicas (ambulatório) | E28: =INDEX(Cov_Grupo,MATCH(C28,Cov_Cod,0)) -> Principal | F28: B | G28: 3000000 | H28: =INDEX(Cov_Lambda,MATCH(C28,Cov_Cod,0)) -> 0.3 | I28: =INDEX(Cov_Mu,MATCH(C28,Cov_Cod,0)) -> 36500 | J28: =IF(INDEX(Cov_FR,MATCH(C28,Cov_Cod,0))="S",INDEX(PF_Factor,MATCH("SAU|"&B28,PF_Key,0)),1) -> 1 | K28: =IF(C28="HOSP_INT",los_int,IF(C28="HOSP_CIR",los_cir,0))*MAX(0,room_ref*J28-INDEX(PF_Room,MATCH("SAU|"&B28,PF_Key,0))) -> 0 | L28: =MAX(0,I28*J28-K28) -> 36500 | M28: =f_trend -> 1.182194 | N28: =H28*L28*M28/(1-EXP(-H28)) -> 49945.734 | O28: =INDEX(Cov_CV,MATCH(C28,Cov_Cod,0)) -> 0.8 | P28: =SQRT(LN(1+O28^2)) -> 0.70334646 | Q28: =LN(N28)-P28^2/2 -> 10.571344 | R28: =IF(G28<=0,1,NORMSDIST((LN(G28)-Q28-P28^2)/P28)+G28/N28*(1-NORMSDIST((LN(G28)-Q28)/P28))) -> 1 | S28: =IF(F28="—",0,H28*L28*M28*R28) -> 12945.024 | T28: =S28*sig_SAU -> 1035.6019 | U28: =S28+T28 -> 13980.626 | V28: =U28/(1-load_SAU) -> 19972.323 | W28: =V28*ea_SAU -> 2596.402 | X28: =V28*ec_SAU -> 2396.6788 | Y28: =V28*m_SAU -> 998.61616 | Z28: =V28*tax_SAU -> 199.72323 | AA28: =V28+Z28 -> 20172.046 | AB28: =IF(G28>0,S28/G28*1000,"n.a.") -> 4.3150081
A29: =B29&"|"&C29 -> Conforto|MAT | B29: Conforto | C29: MAT | D29: =INDEX(Cov_Nome,MATCH(C29,Cov_Cod,0)) -> Maternidade e Parto (Normal e Cesariana) | E29: =INDEX(Cov_Grupo,MATCH(C29,Cov_Cod,0)) -> Principal | F29: O | G29: 1000000 | H29: =INDEX(Cov_Lambda,MATCH(C29,Cov_Cod,0)) -> 0.075 | I29: =INDEX(Cov_Mu,MATCH(C29,Cov_Cod,0)) -> 885640 | J29: =IF(INDEX(Cov_FR,MATCH(C29,Cov_Cod,0))="S",INDEX(PF_Factor,MATCH("SAU|"&B29,PF_Key,0)),1) -> 1 | K29: =IF(C29="HOSP_INT",los_int,IF(C29="HOSP_CIR",los_cir,0))*MAX(0,room_ref*J29-INDEX(PF_Room,MATCH("SAU|"&B29,PF_Key,0))) -> 0 | L29: =MAX(0,I29*J29-K29) -> 885640 | M29: =f_trend -> 1.182194 | N29: =H29*L29*M29/(1-EXP(-H29)) -> 1086751.5 | O29: =INDEX(Cov_CV,MATCH(C29,Cov_Cod,0)) -> 0.5 | P29: =SQRT(LN(1+O29^2)) -> 0.47238073 | Q29: =LN(N29)-P29^2/2 -> 13.787132 | R29: =IF(G29<=0,1,NORMSDIST((LN(G29)-Q29-P29^2)/P29)+G29/N29*(1-NORMSDIST((LN(G29)-Q29)/P29))) -> 0.77810443 | S29: =IF(F29="—",0,H29*L29*M29*R29) -> 61100.551 | T29: =S29*sig_SAU -> 4888.0441 | U29: =S29+T29 -> 65988.595 | V29: =U29/(1-load_SAU) -> 94269.421 | W29: =V29*ea_SAU -> 12255.025 | X29: =V29*ec_SAU -> 11312.331 | Y29: =V29*m_SAU -> 4713.4711 | Z29: =V29*tax_SAU -> 942.69421 | AA29: =V29+Z29 -> 95212.115 | AB29: =IF(G29>0,S29/G29*1000,"n.a.") -> 61.100551
A30: =B30&"|"&C30 -> Conforto|URG | B30: Conforto | C30: URG | D30: =INDEX(Cov_Nome,MATCH(C30,Cov_Cod,0)) -> Urgência Hospitalar | E30: =INDEX(Cov_Grupo,MATCH(C30,Cov_Cod,0)) -> Principal | F30: B | G30: 500000 | H30: =INDEX(Cov_Lambda,MATCH(C30,Cov_Cod,0)) -> 0.42 | I30: =INDEX(Cov_Mu,MATCH(C30,Cov_Cod,0)) -> 43300 | J30: =IF(INDEX(Cov_FR,MATCH(C30,Cov_Cod,0))="S",INDEX(PF_Factor,MATCH("SAU|"&B30,PF_Key,0)),1) -> 1 | K30: =IF(C30="HOSP_INT",los_int,IF(C30="HOSP_CIR",los_cir,0))*MAX(0,room_ref*J30-INDEX(PF_Room,MATCH("SAU|"&B30,PF_Key,0))) -> 0 | L30: =MAX(0,I30*J30-K30) -> 43300 | M30: =f_trend -> 1.182194 | N30: =H30*L30*M30/(1-EXP(-H30)) -> 62688.966 | O30: =INDEX(Cov_CV,MATCH(C30,Cov_Cod,0)) -> 1 | P30: =SQRT(LN(1+O30^2)) -> 0.83255461 | Q30: =LN(N30)-P30^2/2 -> 10.699367 | R30: =IF(G30<=0,1,NORMSDIST((LN(G30)-Q30-P30^2)/P30)+G30/N30*(1-NORMSDIST((LN(G30)-Q30)/P30))) -> 0.99553333 | S30: =IF(F30="—",0,H30*L30*M30*R30) -> 21403.35 | T30: =S30*sig_SAU -> 1712.268 | U30: =S30+T30 -> 23115.618 | V30: =U30/(1-load_SAU) -> 33022.311 | W30: =V30*ea_SAU -> 4292.9004 | X30: =V30*ec_SAU -> 3962.6773 | Y30: =V30*m_SAU -> 1651.1155 | Z30: =V30*tax_SAU -> 330.22311 | AA30: =V30+Z30 -> 33352.534 | AB30: =IF(G30>0,S30/G30*1000,"n.a.") -> 42.806699
A31: =B31&"|"&C31 -> Conforto|AMBUL | B31: Conforto | C31: AMBUL | D31: =INDEX(Cov_Nome,MATCH(C31,Cov_Cod,0)) -> Transporte em Ambulância / Emergência Médica | E31: =INDEX(Cov_Grupo,MATCH(C31,Cov_Cod,0)) -> Principal | F31: B | G31: 300000 | H31: =INDEX(Cov_Lambda,MATCH(C31,Cov_Cod,0)) -> 0.018 | I31: =INDEX(Cov_Mu,MATCH(C31,Cov_Cod,0)) -> 76000 | J31: =IF(INDEX(Cov_FR,MATCH(C31,Cov_Cod,0))="S",INDEX(PF_Factor,MATCH("SAU|"&B31,PF_Key,0)),1) -> 1 | K31: =IF(C31="HOSP_INT",los_int,IF(C31="HOSP_CIR",los_cir,0))*MAX(0,room_ref*J31-INDEX(PF_Room,MATCH("SAU|"&B31,PF_Key,0))) -> 0 | L31: =MAX(0,I31*J31-K31) -> 76000 | M31: =f_trend -> 1.182194 | N31: =H31*L31*M31/(1-EXP(-H31)) -> 90657.791 | O31: =INDEX(Cov_CV,MATCH(C31,Cov_Cod,0)) -> 0.6 | P31: =SQRT(LN(1+O31^2)) -> 0.55451303 | Q31: =LN(N31)-P31^2/2 -> 11.261105 | R31: =IF(G31<=0,1,NORMSDIST((LN(G31)-Q31-P31^2)/P31)+G31/N31*(1-NORMSDIST((LN(G31)-Q31)/P31))) -> 0.99461869 | S31: =IF(F31="—",0,H31*L31*M31*R31) -> 1608.5385 | T31: =S31*sig_SAU -> 128.68308 | U31: =S31+T31 -> 1737.2216 | V31: =U31/(1-load_SAU) -> 2481.7451 | W31: =V31*ea_SAU -> 322.62687 | X31: =V31*ec_SAU -> 297.80942 | Y31: =V31*m_SAU -> 124.08726 | Z31: =V31*tax_SAU -> 24.817451 | AA31: =V31+Z31 -> 2506.5626 | AB31: =IF(G31>0,S31/G31*1000,"n.a.") -> 5.3617951
A32: =B32&"|"&C32 -> Conforto|MED | B32: Conforto | C32: MED | D32: =INDEX(Cov_Nome,MATCH(C32,Cov_Cod,0)) -> Medicamentos em Ambulatório (Farmácia) | E32: =INDEX(Cov_Grupo,MATCH(C32,Cov_Cod,0)) -> Principal | F32: O | G32: 400000 | H32: =INDEX(Cov_Lambda,MATCH(C32,Cov_Cod,0)) -> 3.4 | I32: =INDEX(Cov_Mu,MATCH(C32,Cov_Cod,0)) -> 17400 | J32: =IF(INDEX(Cov_FR,MATCH(C32,Cov_Cod,0))="S",INDEX(PF_Factor,MATCH("SAU|"&B32,PF_Key,0)),1) -> 1 | K32: =IF(C32="HOSP_INT",los_int,IF(C32="HOSP_CIR",los_cir,0))*MAX(0,room_ref*J32-INDEX(PF_Room,MATCH("SAU|"&B32,PF_Key,0))) -> 0 | L32: =MAX(0,I32*J32-K32) -> 17400 | M32: =f_trend -> 1.182194 | N32: =H32*L32*M32/(1-EXP(-H32)) -> 72353.262 | O32: =INDEX(Cov_CV,MATCH(C32,Cov_Cod,0)) -> 1.2 | P32: =SQRT(LN(1+O32^2)) -> 0.94445648 | Q32: =LN(N32)-P32^2/2 -> 10.743317 | R32: =IF(G32<=0,1,NORMSDIST((LN(G32)-Q32-P32^2)/P32)+G32/N32*(1-NORMSDIST((LN(G32)-Q32)/P32))) -> 0.9716427 | S32: =IF(F32="—",0,H32*L32*M32*R32) -> 67955.327 | T32: =S32*sig_SAU -> 5436.4262 | U32: =S32+T32 -> 73391.753 | V32: =U32/(1-load_SAU) -> 104845.36 | W32: =V32*ea_SAU -> 13629.897 | X32: =V32*ec_SAU -> 12581.443 | Y32: =V32*m_SAU -> 5242.2681 | Z32: =V32*tax_SAU -> 1048.4536 | AA32: =V32+Z32 -> 105893.82 | AB32: =IF(G32>0,S32/G32*1000,"n.a.") -> 169.88832
A33: =B33&"|"&C33 -> Conforto|DENT | B33: Conforto | C33: DENT | D33: =INDEX(Cov_Nome,MATCH(C33,Cov_Cod,0)) -> Estomatologia (tratamentos) | E33: =INDEX(Cov_Grupo,MATCH(C33,Cov_Cod,0)) -> Extensão | F33: O | G33: 250000 | H33: =INDEX(Cov_Lambda,MATCH(C33,Cov_Cod,0)) -> 0.85 | I33: =INDEX(Cov_Mu,MATCH(C33,Cov_Cod,0)) -> 34500 | J33: =IF(INDEX(Cov_FR,MATCH(C33,Cov_Cod,0))="S",INDEX(PF_Factor,MATCH("SAU|"&B33,PF_Key,0)),1) -> 1 | K33: =IF(C33="HOSP_INT",los_int,IF(C33="HOSP_CIR",los_cir,0))*MAX(0,room_ref*J33-INDEX(PF_Room,MATCH("SAU|"&B33,PF_Key,0))) -> 0 | L33: =MAX(0,I33*J33-K33) -> 34500 | M33: =f_trend -> 1.182194 | N33: =H33*L33*M33/(1-EXP(-H33)) -> 60546.181 | O33: =INDEX(Cov_CV,MATCH(C33,Cov_Cod,0)) -> 1 | P33: =SQRT(LN(1+O33^2)) -> 0.83255461 | Q33: =LN(N33)-P33^2/2 -> 10.664588 | R33: =IF(G33<=0,1,NORMSDIST((LN(G33)-Q33-P33^2)/P33)+G33/N33*(1-NORMSDIST((LN(G33)-Q33)/P33))) -> 0.97123727 | S33: =IF(F33="—",0,H33*L33*M33*R33) -> 33670.697 | T33: =S33*sig_SAU -> 2693.6558 | U33: =S33+T33 -> 36364.353 | V33: =U33/(1-load_SAU) -> 51949.076 | W33: =V33*ea_SAU -> 6753.3799 | X33: =V33*ec_SAU -> 6233.8891 | Y33: =V33*m_SAU -> 2597.4538 | Z33: =V33*tax_SAU -> 519.49076 | AA33: =V33+Z33 -> 52468.567 | AB33: =IF(G33>0,S33/G33*1000,"n.a.") -> 134.68279
A34: =B34&"|"&C34 -> Conforto|PROT | B34: Conforto | C34: PROT | D34: =INDEX(Cov_Nome,MATCH(C34,Cov_Cod,0)) -> Próteses Dentárias | E34: =INDEX(Cov_Grupo,MATCH(C34,Cov_Cod,0)) -> Extensão | F34: O | G34: 150000 | H34: =INDEX(Cov_Lambda,MATCH(C34,Cov_Cod,0)) -> 0.02 | I34: =INDEX(Cov_Mu,MATCH(C34,Cov_Cod,0)) -> 304000 | J34: =IF(INDEX(Cov_FR,MATCH(C34,Cov_Cod,0))="S",INDEX(PF_Factor,MATCH("SAU|"&B34,PF_Key,0)),1) -> 1 | K34: =IF(C34="HOSP_INT",los_int,IF(C34="HOSP_CIR",los_cir,0))*MAX(0,room_ref*J34-INDEX(PF_Room,MATCH("SAU|"&B34,PF_Key,0))) -> 0 | L34: =MAX(0,I34*J34-K34) -> 304000 | M34: =f_trend -> 1.182194 | N34: =H34*L34*M34/(1-EXP(-H34)) -> 362992.83 | O34: =INDEX(Cov_CV,MATCH(C34,Cov_Cod,0)) -> 0.7 | P34: =SQRT(LN(1+O34^2)) -> 0.63148723 | Q34: =LN(N34)-P34^2/2 -> 12.60275 | R34: =IF(G34<=0,1,NORMSDIST((LN(G34)-Q34-P34^2)/P34)+G34/N34*(1-NORMSDIST((LN(G34)-Q34)/P34))) -> 0.39884475 | S34: =IF(F34="—",0,H34*L34*M34*R34) -> 2866.7922 | T34: =S34*sig_SAU -> 229.34337 | U34: =S34+T34 -> 3096.1355 | V34: =U34/(1-load_SAU) -> 4423.0508 | W34: =V34*ea_SAU -> 574.9966 | X34: =V34*ec_SAU -> 530.76609 | Y34: =V34*m_SAU -> 221.15254 | Z34: =V34*tax_SAU -> 44.230508 | AA34: =V34+Z34 -> 4467.2813 | AB34: =IF(G34>0,S34/G34*1000,"n.a.") -> 19.111948
A35: =B35&"|"&C35 -> Conforto|OPT | B35: Conforto | C35: OPT | D35: =INDEX(Cov_Nome,MATCH(C35,Cov_Cod,0)) -> Óptica — Lentes e Armações | E35: =INDEX(Cov_Grupo,MATCH(C35,Cov_Cod,0)) -> Extensão | F35: O | G35: 100000 | H35: =INDEX(Cov_Lambda,MATCH(C35,Cov_Cod,0)) -> 0.22 | I35: =INDEX(Cov_Mu,MATCH(C35,Cov_Cod,0)) -> 102500 | J35: =IF(INDEX(Cov_FR,MATCH(C35,Cov_Cod,0))="S",INDEX(PF_Factor,MATCH("SAU|"&B35,PF_Key,0)),1) -> 1 | K35: =IF(C35="HOSP_INT",los_int,IF(C35="HOSP_CIR",los_cir,0))*MAX(0,room_ref*J35-INDEX(PF_Room,MATCH("SAU|"&B35,PF_Key,0))) -> 0 | L35: =MAX(0,I35*J35-K35) -> 102500 | M35: =f_trend -> 1.182194 | N35: =H35*L35*M35/(1-EXP(-H35)) -> 134992.47 | O35: =INDEX(Cov_CV,MATCH(C35,Cov_Cod,0)) -> 0.5 | P35: =SQRT(LN(1+O35^2)) -> 0.47238073 | Q35: =LN(N35)-P35^2/2 -> 11.701402 | R35: =IF(G35<=0,1,NORMSDIST((LN(G35)-Q35-P35^2)/P35)+G35/N35*(1-NORMSDIST((LN(G35)-Q35)/P35))) -> 0.67702497 | S35: =IF(F35="—",0,H35*L35*M35*R35) -> 18048.453 | T35: =S35*sig_SAU -> 1443.8762 | U35: =S35+T35 -> 19492.329 | V35: =U35/(1-load_SAU) -> 27846.185 | W35: =V35*ea_SAU -> 3620.004 | X35: =V35*ec_SAU -> 3341.5422 | Y35: =V35*m_SAU -> 1392.3092 | Z35: =V35*tax_SAU -> 278.46185 | AA35: =V35+Z35 -> 28124.646 | AB35: =IF(G35>0,S35/G35*1000,"n.a.") -> 180.48453
A36: =B36&"|"&C36 -> Conforto|PREV | B36: Conforto | C36: PREV | D36: =INDEX(Cov_Nome,MATCH(C36,Cov_Cod,0)) -> Medicina Preventiva e Check-up Anual | E36: =INDEX(Cov_Grupo,MATCH(C36,Cov_Cod,0)) -> Extensão | F36: O | G36: 120000 | H36: =INDEX(Cov_Lambda,MATCH(C36,Cov_Cod,0)) -> 0.55 | I36: =INDEX(Cov_Mu,MATCH(C36,Cov_Cod,0)) -> 76000 | J36: =IF(INDEX(Cov_FR,MATCH(C36,Cov_Cod,0))="S",INDEX(PF_Factor,MATCH("SAU|"&B36,PF_Key,0)),1) -> 1 | K36: =IF(C36="HOSP_INT",los_int,IF(C36="HOSP_CIR",los_cir,0))*MAX(0,room_ref*J36-INDEX(PF_Room,MATCH("SAU|"&B36,PF_Key,0))) -> 0 | L36: =MAX(0,I36*J36-K36) -> 76000 | M36: =f_trend -> 1.182194 | N36: =H36*L36*M36/(1-EXP(-H36)) -> 116808.15 | O36: =INDEX(Cov_CV,MATCH(C36,Cov_Cod,0)) -> 0.3 | P36: =SQRT(LN(1+O36^2)) -> 0.29356038 | Q36: =LN(N36)-P36^2/2 -> 11.625199 | R36: =IF(G36<=0,1,NORMSDIST((LN(G36)-Q36-P36^2)/P36)+G36/N36*(1-NORMSDIST((LN(G36)-Q36)/P36))) -> 0.89487911 | S36: =IF(F36="—",0,H36*L36*M36*R36) -> 44221.086 | T36: =S36*sig_SAU -> 3537.6869 | U36: =S36+T36 -> 47758.772 | V36: =U36/(1-load_SAU) -> 68226.818 | W36: =V36*ea_SAU -> 8869.4863 | X36: =V36*ec_SAU -> 8187.2181 | Y36: =V36*m_SAU -> 3411.3409 | Z36: =V36*tax_SAU -> 682.26818 | AA36: =V36+Z36 -> 68909.086 | AB36: =IF(G36>0,S36/G36*1000,"n.a.") -> 368.50905
A37: =B37&"|"&C37 -> Conforto|EVAC | B37: Conforto | C37: EVAC | D37: =INDEX(Cov_Nome,MATCH(C37,Cov_Cod,0)) -> Evacuação Médica e Cobertura no Estrangeiro | E37: =INDEX(Cov_Grupo,MATCH(C37,Cov_Cod,0)) -> Extensão | F37: O | G37: 20000000 | H37: =INDEX(Cov_Lambda,MATCH(C37,Cov_Cod,0)) -> 0.0012 | I37: =INDEX(Cov_Mu,MATCH(C37,Cov_Cod,0)) -> 44700960 | J37: =IF(INDEX(Cov_FR,MATCH(C37,Cov_Cod,0))="S",INDEX(PF_Factor,MATCH("SAU|"&B37,PF_Key,0)),1) -> 1 | K37: =IF(C37="HOSP_INT",los_int,IF(C37="HOSP_CIR",los_cir,0))*MAX(0,room_ref*J37-INDEX(PF_Room,MATCH("SAU|"&B37,PF_Key,0))) -> 0 | L37: =MAX(0,I37*J37-K37) -> 44700960 | M37: =f_trend -> 1.182194 | N37: =H37*L37*M37/(1-EXP(-H37)) -> 52876920 | O37: =INDEX(Cov_CV,MATCH(C37,Cov_Cod,0)) -> 1 | P37: =SQRT(LN(1+O37^2)) -> 0.83255461 | Q37: =LN(N37)-P37^2/2 -> 17.436904 | R37: =IF(G37<=0,1,NORMSDIST((LN(G37)-Q37-P37^2)/P37)+G37/N37*(1-NORMSDIST((LN(G37)-Q37)/P37))) -> 0.34927944 | S37: =IF(F37="—",0,H37*L37*M37*R37) -> 22149.293 | T37: =S37*sig_SAU -> 1771.9434 | U37: =S37+T37 -> 23921.236 | V37: =U37/(1-load_SAU) -> 34173.195 | W37: =V37*ea_SAU -> 4442.5153 | X37: =V37*ec_SAU -> 4100.7834 | Y37: =V37*m_SAU -> 1708.6597 | Z37: =V37*tax_SAU -> 341.73195 | AA37: =V37+Z37 -> 34514.927 | AB37: =IF(G37>0,S37/G37*1000,"n.a.") -> 1.1074647
... A41: =B41&"|"&C41 -> Premium|HOSP_CIR | B41: Premium | C41: HOSP_CIR | D41: =INDEX(Cov_Nome,MATCH(C41,Cov_Cod,0)) -> Cirurgia (com internamento e de ambulatório) | E41: =INDEX(Cov_Grupo,MATCH(C41,Cov_Cod,0)) -> Principal | F41: B | G41: 40000000 | H41: =INDEX(Cov_Lambda,MATCH(C41,Cov_Cod,0)) -> 0.024 | I41: =INDEX(Cov_Mu,MATCH(C41,Cov_Cod,0)) -> 2032500 | J41: =IF(INDEX(Cov_FR,MATCH(C41,Cov_Cod,0))="S",INDEX(PF_Factor,MATCH("SAU|"&B41,PF_Key,0)),1) -> 1.3 | K41: =IF(C41="HOSP_INT",los_int,IF(C41="HOSP_CIR",los_cir,0))*MAX(0,room_ref*J41-INDEX(PF_Room,MATCH("SAU|"&B41,PF_Key,0))) -> 0 | L41: =MAX(0,I41*J41-K41) -> 2642250 | M41: =f_trend -> 1.182194 | N41: =H41*L41*M41/(1-EXP(-H41)) -> 3161285.9 | O41: =INDEX(Cov_CV,MATCH(C41,Cov_Cod,0)) -> 1.3 | P41: =SQRT(LN(1+O41^2)) -> 0.99475685 | Q41: =LN(N41)-P41^2/2 -> 14.471719 | R41: =IF(G41<=0,1,NORMSDIST((LN(G41)-Q41-P41^2)/P41)+G41/N41*(1-NORMSDIST((LN(G41)-Q41)/P41))) -> 0.99454993 | S41: =IF(F41="—",0,H41*L41*M41*R41) -> 74559.072 | T41: =S41*sig_SAU -> 5964.7257 | U41: =S41+T41 -> 80523.797 | V41: =U41/(1-load_SAU) -> 115034 | W41: =V41*ea_SAU -> 14954.42 | X41: =V41*ec_SAU -> 13804.08 | Y41: =V41*m_SAU -> 5751.6998 | Z41: =V41*tax_SAU -> 1150.34 | AA41: =V41+Z41 -> 116184.34 | AB41: =IF(G41>0,S41/G41*1000,"n.a.") -> 1.8639768
A42: =B42&"|"&C42 -> Premium|HOSP_UCI | B42: Premium | C42: HOSP_UCI | D42: =INDEX(Cov_Nome,MATCH(C42,Cov_Cod,0)) -> Cuidados Intensivos (UCI) | E42: =INDEX(Cov_Grupo,MATCH(C42,Cov_Cod,0)) -> Principal | F42: B | G42: =INDEX(PF_UCI,MATCH("SAU|"&B42,PF_Key,0)) -> 15000000 | H42: =INDEX(Cov_Lambda,MATCH(C42,Cov_Cod,0)) -> 0.0035 | I42: =INDEX(Cov_Mu,MATCH(C42,Cov_Cod,0)) -> 2835000 | J42: =IF(INDEX(Cov_FR,MATCH(C42,Cov_Cod,0))="S",INDEX(PF_Factor,MATCH("SAU|"&B42,PF_Key,0)),1) -> 1.3 | K42: =IF(C42="HOSP_INT",los_int,IF(C42="HOSP_CIR",los_cir,0))*MAX(0,room_ref*J42-INDEX(PF_Room,MATCH("SAU|"&B42,PF_Key,0))) -> 0 | L42: =MAX(0,I42*J42-K42) -> 3685500 | M42: =f_trend -> 1.182194 | N42: =H42*L42*M42/(1-EXP(-H42)) -> 4364605.1 | O42: =INDEX(Cov_CV,MATCH(C42,Cov_Cod,0)) -> 1.2 | P42: =SQRT(LN(1+O42^2)) -> 0.94445648 | Q42: =LN(N42)-P42^2/2 -> 14.843039 | R42: =IF(G42<=0,1,NORMSDIST((LN(G42)-Q42-P42^2)/P42)+G42/N42*(1-NORMSDIST((LN(G42)-Q42)/P42))) -> 0.92730223 | S42: =IF(F42="—",0,H42*L42*M42*R42) -> 14140.817 | T42: =S42*sig_SAU -> 1131.2654 | U42: =S42+T42 -> 15272.083 | V42: =U42/(1-load_SAU) -> 21817.261 | W42: =V42*ea_SAU -> 2836.244 | X42: =V42*ec_SAU -> 2618.0714 | Y42: =V42*m_SAU -> 1090.8631 | Z42: =V42*tax_SAU -> 218.17261 | AA42: =V42+Z42 -> 22035.434 | AB42: =IF(G42>0,S42/G42*1000,"n.a.") -> 0.94272117
A43: =B43&"|"&C43 -> Premium|AMB_CONS | B43: Premium | C43: AMB_CONS | D43: =INDEX(Cov_Nome,MATCH(C43,Cov_Cod,0)) -> Consultas de Clínica Geral e Especialidade (incl. teleconsulta) | E43: =INDEX(Cov_Grupo,MATCH(C43,Cov_Cod,0)) -> Principal | F43: B | G43: 8000000 | H43: =INDEX(Cov_Lambda,MATCH(C43,Cov_Cod,0)) -> 2.6 | I43: =INDEX(Cov_Mu,MATCH(C43,Cov_Cod,0)) -> 24000 | J43: =IF(INDEX(Cov_FR,MATCH(C43,Cov_Cod,0))="S",INDEX(PF_Factor,MATCH("SAU|"&B43,PF_Key,0)),1) -> 1.3 | K43: =IF(C43="HOSP_INT",los_int,IF(C43="HOSP_CIR",los_cir,0))*MAX(0,room_ref*J43-INDEX(PF_Room,MATCH("SAU|"&B43,PF_Key,0))) -> 0 | L43: =MAX(0,I43*J43-K43) -> 31200 | M43: =f_trend -> 1.182194 | N43: =H43*L43*M43/(1-EXP(-H43)) -> 103593.86 | O43: =INDEX(Cov_CV,MATCH(C43,Cov_Cod,0)) -> 1 | P43: =SQRT(LN(1+O43^2)) -> 0.83255461 | Q43: =LN(N43)-P43^2/2 -> 11.20166 | R43: =IF(G43<=0,1,NORMSDIST((LN(G43)-Q43-P43^2)/P43)+G43/N43*(1-NORMSDIST((LN(G43)-Q43)/P43))) -> 0.99999989 | S43: =IF(F43="—",0,H43*L43*M43*R43) -> 95899.567 | T43: =S43*sig_SAU -> 7671.9654 | U43: =S43+T43 -> 103571.53 | V43: =U43/(1-load_SAU) -> 147959.33 | W43: =V43*ea_SAU -> 19234.713 | X43: =V43*ec_SAU -> 17755.12 | Y43: =V43*m_SAU -> 7397.9666 | Z43: =V43*tax_SAU -> 1479.5933 | AA43: =V43+Z43 -> 149438.93 | AB43: =IF(G43>0,S43/G43*1000,"n.a.") -> 11.987446
A44: =B44&"|"&C44 -> Premium|AMB_MCDT | B44: Premium | C44: AMB_MCDT | D44: =INDEX(Cov_Nome,MATCH(C44,Cov_Cod,0)) -> MCDT — Exames, Análises e Imagiologia | E44: =INDEX(Cov_Grupo,MATCH(C44,Cov_Cod,0)) -> Principal | F44: B | G44: 8000000 | H44: =INDEX(Cov_Lambda,MATCH(C44,Cov_Cod,0)) -> 3.8 | I44: =INDEX(Cov_Mu,MATCH(C44,Cov_Cod,0)) -> 14600 | J44: =IF(INDEX(Cov_FR,MATCH(C44,Cov_Cod,0))="S",INDEX(PF_Factor,MATCH("SAU|"&B44,PF_Key,0)),1) -> 1.3 | K44: =IF(C44="HOSP_INT",los_int,IF(C44="HOSP_CIR",los_cir,0))*MAX(0,room_ref*J44-INDEX(PF_Room,MATCH("SAU|"&B44,PF_Key,0))) -> 0 | L44: =MAX(0,I44*J44-K44) -> 18980 | M44: =f_trend -> 1.182194 | N44: =H44*L44*M44/(1-EXP(-H44)) -> 87215.641 | O44: =INDEX(Cov_CV,MATCH(C44,Cov_Cod,0)) -> 1.5 | P44: =SQRT(LN(1+O44^2)) -> 1.0856588 | Q44: =LN(N44)-P44^2/2 -> 10.786811 | R44: =IF(G44<=0,1,NORMSDIST((LN(G44)-Q44-P44^2)/P44)+G44/N44*(1-NORMSDIST((LN(G44)-Q44)/P44))) -> 0.99996875 | S44: =IF(F44="—",0,H44*L44*M44*R44) -> 85261.896 | T44: =S44*sig_SAU -> 6820.9517 | U44: =S44+T44 -> 92082.848 | V44: =U44/(1-load_SAU) -> 131546.93 | W44: =V44*ea_SAU -> 17101.1 | X44: =V44*ec_SAU -> 15785.631 | Y44: =V44*m_SAU -> 6577.3463 | Z44: =V44*tax_SAU -> 1315.4693 | AA44: =V44+Z44 -> 132862.39 | AB44: =IF(G44>0,S44/G44*1000,"n.a.") -> 10.657737
A45: =B45&"|"&C45 -> Premium|MAL | B45: Premium | C45: MAL | D45: =INDEX(Cov_Nome,MATCH(C45,Cov_Cod,0)) -> Malária e Doenças Endémicas (ambulatório) | E45: =INDEX(Cov_Grupo,MATCH(C45,Cov_Cod,0)) -> Principal | F45: B | G45: 8000000 | H45: =INDEX(Cov_Lambda,MATCH(C45,Cov_Cod,0)) -> 0.3 | I45: =INDEX(Cov_Mu,MATCH(C45,Cov_Cod,0)) -> 36500 | J45: =IF(INDEX(Cov_FR,MATCH(C45,Cov_Cod,0))="S",INDEX(PF_Factor,MATCH("SAU|"&B45,PF_Key,0)),1) -> 1.3 | K45: =IF(C45="HOSP_INT",los_int,IF(C45="HOSP_CIR",los_cir,0))*MAX(0,room_ref*J45-INDEX(PF_Room,MATCH("SAU|"&B45,PF_Key,0))) -> 0 | L45: =MAX(0,I45*J45-K45) -> 47450 | M45: =f_trend -> 1.182194 | N45: =H45*L45*M45/(1-EXP(-H45)) -> 64929.455 | O45: =INDEX(Cov_CV,MATCH(C45,Cov_Cod,0)) -> 0.8 | P45: =SQRT(LN(1+O45^2)) -> 0.70334646 | Q45: =LN(N45)-P45^2/2 -> 10.833709 | R45: =IF(G45<=0,1,NORMSDIST((LN(G45)-Q45-P45^2)/P45)+G45/N45*(1-NORMSDIST((LN(G45)-Q45)/P45))) -> 1 | S45: =IF(F45="—",0,H45*L45*M45*R45) -> 16828.532 | T45: =S45*sig_SAU -> 1346.2825 | U45: =S45+T45 -> 18174.814 | V45: =U45/(1-load_SAU) -> 25964.02 | W45: =V45*ea_SAU -> 3375.3226 | X45: =V45*ec_SAU -> 3115.6824 | Y45: =V45*m_SAU -> 1298.201 | Z45: =V45*tax_SAU -> 259.6402 | AA45: =V45+Z45 -> 26223.66 | AB45: =IF(G45>0,S45/G45*1000,"n.a.") -> 2.1035664
A46: =B46&"|"&C46 -> Premium|MAT | B46: Premium | C46: MAT | D46: =INDEX(Cov_Nome,MATCH(C46,Cov_Cod,0)) -> Maternidade e Parto (Normal e Cesariana) | E46: =INDEX(Cov_Grupo,MATCH(C46,Cov_Cod,0)) -> Principal | F46: B | G46: 2500000 | H46: =INDEX(Cov_Lambda,MATCH(C46,Cov_Cod,0)) -> 0.075 | I46: =INDEX(Cov_Mu,MATCH(C46,Cov_Cod,0)) -> 885640 | J46: =IF(INDEX(Cov_FR,MATCH(C46,Cov_Cod,0))="S",INDEX(PF_Factor,MATCH("SAU|"&B46,PF_Key,0)),1) -> 1.3 | K46: =IF(C46="HOSP_INT",los_int,IF(C46="HOSP_CIR",los_cir,0))*MAX(0,room_ref*J46-INDEX(PF_Room,MATCH("SAU|"&B46,PF_Key,0))) -> 0 | L46: =MAX(0,I46*J46-K46) -> 1151332 | M46: =f_trend -> 1.182194 | N46: =H46*L46*M46/(1-EXP(-H46)) -> 1412776.9 | O46: =INDEX(Cov_CV,MATCH(C46,Cov_Cod,0)) -> 0.5 | P46: =SQRT(LN(1+O46^2)) -> 0.47238073 | Q46: =LN(N46)-P46^2/2 -> 14.049496 | R46: =IF(G46<=0,1,NORMSDIST((LN(G46)-Q46-P46^2)/P46)+G46/N46*(1-NORMSDIST((LN(G46)-Q46)/P46))) -> 0.96598161 | S46: =IF(F46="—",0,H46*L46*M46*R46) -> 98609.657 | T46: =S46*sig_SAU -> 7888.7725 | U46: =S46+T46 -> 106498.43 | V46: =U46/(1-load_SAU) -> 152140.61 | W46: =V46*ea_SAU -> 19778.28 | X46: =V46*ec_SAU -> 18256.874 | Y46: =V46*m_SAU -> 7607.0307 | Z46: =V46*tax_SAU -> 1521.4061 | AA46: =V46+Z46 -> 153662.02 | AB46: =IF(G46>0,S46/G46*1000,"n.a.") -> 39.443863
A47: =B47&"|"&C47 -> Premium|URG | B47: Premium | C47: URG | D47: =INDEX(Cov_Nome,MATCH(C47,Cov_Cod,0)) -> Urgência Hospitalar | E47: =INDEX(Cov_Grupo,MATCH(C47,Cov_Cod,0)) -> Principal | F47: B | G47: 1000000 | H47: =INDEX(Cov_Lambda,MATCH(C47,Cov_Cod,0)) -> 0.42 | I47: =INDEX(Cov_Mu,MATCH(C47,Cov_Cod,0)) -> 43300 | J47: =IF(INDEX(Cov_FR,MATCH(C47,Cov_Cod,0))="S",INDEX(PF_Factor,MATCH("SAU|"&B47,PF_Key,0)),1) -> 1.3 | K47: =IF(C47="HOSP_INT",los_int,IF(C47="HOSP_CIR",los_cir,0))*MAX(0,room_ref*J47-INDEX(PF_Room,MATCH("SAU|"&B47,PF_Key,0))) -> 0 | L47: =MAX(0,I47*J47-K47) -> 56290 | M47: =f_trend -> 1.182194 | N47: =H47*L47*M47/(1-EXP(-H47)) -> 81495.655 | O47: =INDEX(Cov_CV,MATCH(C47,Cov_Cod,0)) -> 1 | P47: =SQRT(LN(1+O47^2)) -> 0.83255461 | Q47: =LN(N47)-P47^2/2 -> 10.961731 | R47: =IF(G47<=0,1,NORMSDIST((LN(G47)-Q47-P47^2)/P47)+G47/N47*(1-NORMSDIST((LN(G47)-Q47)/P47))) -> 0.99900712 | S47: =IF(F47="—",0,H47*L47*M47*R47) -> 27921.444 | T47: =S47*sig_SAU -> 2233.7155 | U47: =S47+T47 -> 30155.159 | V47: =U47/(1-load_SAU) -> 43078.799 | W47: =V47*ea_SAU -> 5600.2439 | X47: =V47*ec_SAU -> 5169.4559 | Y47: =V47*m_SAU -> 2153.94 | Z47: =V47*tax_SAU -> 430.78799 | AA47: =V47+Z47 -> 43509.587 | AB47: =IF(G47>0,S47/G47*1000,"n.a.") -> 27.921444
A48: =B48&"|"&C48 -> Premium|AMBUL | B48: Premium | C48: AMBUL | D48: =INDEX(Cov_Nome,MATCH(C48,Cov_Cod,0)) -> Transporte em Ambulância / Emergência Médica | E48: =INDEX(Cov_Grupo,MATCH(C48,Cov_Cod,0)) -> Principal | F48: B | G48: 600000 | H48: =INDEX(Cov_Lambda,MATCH(C48,Cov_Cod,0)) -> 0.018 | I48: =INDEX(Cov_Mu,MATCH(C48,Cov_Cod,0)) -> 76000 | J48: =IF(INDEX(Cov_FR,MATCH(C48,Cov_Cod,0))="S",INDEX(PF_Factor,MATCH("SAU|"&B48,PF_Key,0)),1) -> 1 | K48: =IF(C48="HOSP_INT",los_int,IF(C48="HOSP_CIR",los_cir,0))*MAX(0,room_ref*J48-INDEX(PF_Room,MATCH("SAU|"&B48,PF_Key,0))) -> 0 | L48: =MAX(0,I48*J48-K48) -> 76000 | M48: =f_trend -> 1.182194 | N48: =H48*L48*M48/(1-EXP(-H48)) -> 90657.791 | O48: =INDEX(Cov_CV,MATCH(C48,Cov_Cod,0)) -> 0.6 | P48: =SQRT(LN(1+O48^2)) -> 0.55451303 | Q48: =LN(N48)-P48^2/2 -> 11.261105 | R48: =IF(G48<=0,1,NORMSDIST((LN(G48)-Q48-P48^2)/P48)+G48/N48*(1-NORMSDIST((LN(G48)-Q48)/P48))) -> 0.99988423 | S48: =IF(F48="—",0,H48*L48*M48*R48) -> 1617.0542 | T48: =S48*sig_SAU -> 129.36433 | U48: =S48+T48 -> 1746.4185 | V48: =U48/(1-load_SAU) -> 2494.8836 | W48: =V48*ea_SAU -> 324.33486 | X48: =V48*ec_SAU -> 299.38603 | Y48: =V48*m_SAU -> 124.74418 | Z48: =V48*tax_SAU -> 24.948836 | AA48: =V48+Z48 -> 2519.8324 | AB48: =IF(G48>0,S48/G48*1000,"n.a.") -> 2.6950903
A49: =B49&"|"&C49 -> Premium|MED | B49: Premium | C49: MED | D49: =INDEX(Cov_Nome,MATCH(C49,Cov_Cod,0)) -> Medicamentos em Ambulatório (Farmácia) | E49: =INDEX(Cov_Grupo,MATCH(C49,Cov_Cod,0)) -> Principal | F49: B | G49: 1000000 | H49: =INDEX(Cov_Lambda,MATCH(C49,Cov_Cod,0)) -> 3.4 | I49: =INDEX(Cov_Mu,MATCH(C49,Cov_Cod,0)) -> 17400 | J49: =IF(INDEX(Cov_FR,MATCH(C49,Cov_Cod,0))="S",INDEX(PF_Factor,MATCH("SAU|"&B49,PF_Key,0)),1) -> 1 | K49: =IF(C49="HOSP_INT",los_int,IF(C49="HOSP_CIR",los_cir,0))*MAX(0,room_ref*J49-INDEX(PF_Room,MATCH("SAU|"&B49,PF_Key,0))) -> 0 | L49: =MAX(0,I49*J49-K49) -> 17400 | M49: =f_trend -> 1.182194 | N49: =H49*L49*M49/(1-EXP(-H49)) -> 72353.262 | O49: =INDEX(Cov_CV,MATCH(C49,Cov_Cod,0)) -> 1.2 | P49: =SQRT(LN(1+O49^2)) -> 0.94445648 | Q49: =LN(N49)-P49^2/2 -> 10.743317 | R49: =IF(G49<=0,1,NORMSDIST((LN(G49)-Q49-P49^2)/P49)+G49/N49*(1-NORMSDIST((LN(G49)-Q49)/P49))) -> 0.99740692 | S49: =IF(F49="—",0,H49*L49*M49*R49) -> 69757.241 | T49: =S49*sig_SAU -> 5580.5793 | U49: =S49+T49 -> 75337.82 | V49: =U49/(1-load_SAU) -> 107625.46 | W49: =V49*ea_SAU -> 13991.309 | X49: =V49*ec_SAU -> 12915.055 | Y49: =V49*m_SAU -> 5381.2729 | Z49: =V49*tax_SAU -> 1076.2546 | AA49: =V49+Z49 -> 108701.71 | AB49: =IF(G49>0,S49/G49*1000,"n.a.") -> 69.757241
A50: =B50&"|"&C50 -> Premium|DENT | B50: Premium | C50: DENT | D50: =INDEX(Cov_Nome,MATCH(C50,Cov_Cod,0)) -> Estomatologia (tratamentos) | E50: =INDEX(Cov_Grupo,MATCH(C50,Cov_Cod,0)) -> Extensão | F50: B | G50: 750000 | H50: =INDEX(Cov_Lambda,MATCH(C50,Cov_Cod,0)) -> 0.85 | I50: =INDEX(Cov_Mu,MATCH(C50,Cov_Cod,0)) -> 34500 | J50: =IF(INDEX(Cov_FR,MATCH(C50,Cov_Cod,0))="S",INDEX(PF_Factor,MATCH("SAU|"&B50,PF_Key,0)),1) -> 1.3 | K50: =IF(C50="HOSP_INT",los_int,IF(C50="HOSP_CIR",los_cir,0))*MAX(0,room_ref*J50-INDEX(PF_Room,MATCH("SAU|"&B50,PF_Key,0))) -> 0 | L50: =MAX(0,I50*J50-K50) -> 44850 | M50: =f_trend -> 1.182194 | N50: =H50*L50*M50/(1-EXP(-H50)) -> 78710.035 | O50: =INDEX(Cov_CV,MATCH(C50,Cov_Cod,0)) -> 1 | P50: =SQRT(LN(1+O50^2)) -> 0.83255461 | Q50: =LN(N50)-P50^2/2 -> 10.926952 | R50: =IF(G50<=0,1,NORMSDIST((LN(G50)-Q50-P50^2)/P50)+G50/N50*(1-NORMSDIST((LN(G50)-Q50)/P50))) -> 0.99753122 | S50: =IF(F50="—",0,H50*L50*M50*R50) -> 44956.927 | T50: =S50*sig_SAU -> 3596.5542 | U50: =S50+T50 -> 48553.481 | V50: =U50/(1-load_SAU) -> 69362.116 | W50: =V50*ea_SAU -> 9017.0751 | X50: =V50*ec_SAU -> 8323.4539 | Y50: =V50*m_SAU -> 3468.1058 | Z50: =V50*tax_SAU -> 693.62116 | AA50: =V50+Z50 -> 70055.737 | AB50: =IF(G50>0,S50/G50*1000,"n.a.") -> 59.94257
A51: =B51&"|"&C51 -> Premium|PROT | B51: Premium | C51: PROT | D51: =INDEX(Cov_Nome,MATCH(C51,Cov_Cod,0)) -> Próteses Dentárias | E51: =INDEX(Cov_Grupo,MATCH(C51,Cov_Cod,0)) -> Extensão | F51: B | G51: 400000 | H51: =INDEX(Cov_Lambda,MATCH(C51,Cov_Cod,0)) -> 0.02 | I51: =INDEX(Cov_Mu,MATCH(C51,Cov_Cod,0)) -> 304000 | J51: =IF(INDEX(Cov_FR,MATCH(C51,Cov_Cod,0))="S",INDEX(PF_Factor,MATCH("SAU|"&B51,PF_Key,0)),1) -> 1 | K51: =IF(C51="HOSP_INT",los_int,IF(C51="HOSP_CIR",los_cir,0))*MAX(0,room_ref*J51-INDEX(PF_Room,MATCH("SAU|"&B51,PF_Key,0))) -> 0 | L51: =MAX(0,I51*J51-K51) -> 304000 | M51: =f_trend -> 1.182194 | N51: =H51*L51*M51/(1-EXP(-H51)) -> 362992.83 | O51: =INDEX(Cov_CV,MATCH(C51,Cov_Cod,0)) -> 0.7 | P51: =SQRT(LN(1+O51^2)) -> 0.63148723 | Q51: =LN(N51)-P51^2/2 -> 12.60275 | R51: =IF(G51<=0,1,NORMSDIST((LN(G51)-Q51-P51^2)/P51)+G51/N51*(1-NORMSDIST((LN(G51)-Q51)/P51))) -> 0.78757251 | S51: =IF(F51="—",0,H51*L51*M51*R51) -> 5660.866 | T51: =S51*sig_SAU -> 452.86928 | U51: =S51+T51 -> 6113.7353 | V51: =U51/(1-load_SAU) -> 8733.9076 | W51: =V51*ea_SAU -> 1135.408 | X51: =V51*ec_SAU -> 1048.0689 | Y51: =V51*m_SAU -> 436.69538 | Z51: =V51*tax_SAU -> 87.339076 | AA51: =V51+Z51 -> 8821.2467 | AB51: =IF(G51>0,S51/G51*1000,"n.a.") -> 14.152165
A52: =B52&"|"&C52 -> Premium|OPT | B52: Premium | C52: OPT | D52: =INDEX(Cov_Nome,MATCH(C52,Cov_Cod,0)) -> Óptica — Lentes e Armações | E52: =INDEX(Cov_Grupo,MATCH(C52,Cov_Cod,0)) -> Extensão | F52: B | G52: 300000 | H52: =INDEX(Cov_Lambda,MATCH(C52,Cov_Cod,0)) -> 0.22 | I52: =INDEX(Cov_Mu,MATCH(C52,Cov_Cod,0)) -> 102500 | J52: =IF(INDEX(Cov_FR,MATCH(C52,Cov_Cod,0))="S",INDEX(PF_Factor,MATCH("SAU|"&B52,PF_Key,0)),1) -> 1 | K52: =IF(C52="HOSP_INT",los_int,IF(C52="HOSP_CIR",los_cir,0))*MAX(0,room_ref*J52-INDEX(PF_Room,MATCH("SAU|"&B52,PF_Key,0))) -> 0 | L52: =MAX(0,I52*J52-K52) -> 102500 | M52: =f_trend -> 1.182194 | N52: =H52*L52*M52/(1-EXP(-H52)) -> 134992.47 | O52: =INDEX(Cov_CV,MATCH(C52,Cov_Cod,0)) -> 0.5 | P52: =SQRT(LN(1+O52^2)) -> 0.47238073 | Q52: =LN(N52)-P52^2/2 -> 11.701402 | R52: =IF(G52<=0,1,NORMSDIST((LN(G52)-Q52-P52^2)/P52)+G52/N52*(1-NORMSDIST((LN(G52)-Q52)/P52))) -> 0.98709336 | S52: =IF(F52="—",0,H52*L52*M52*R52) -> 26314.403 | T52: =S52*sig_SAU -> 2105.1523 | U52: =S52+T52 -> 28419.556 | V52: =U52/(1-load_SAU) -> 40599.365 | W52: =V52*ea_SAU -> 5277.9175 | X52: =V52*ec_SAU -> 4871.9238 | Y52: =V52*m_SAU -> 2029.9683 | Z52: =V52*tax_SAU -> 405.99365 | AA52: =V52+Z52 -> 41005.359 | AB52: =IF(G52>0,S52/G52*1000,"n.a.") -> 87.714678
A53: =B53&"|"&C53 -> Premium|PREV | B53: Premium | C53: PREV | D53: =INDEX(Cov_Nome,MATCH(C53,Cov_Cod,0)) -> Medicina Preventiva e Check-up Anual | E53: =INDEX(Cov_Grupo,MATCH(C53,Cov_Cod,0)) -> Extensão | F53: B | G53: 250000 | H53: =INDEX(Cov_Lambda,MATCH(C53,Cov_Cod,0)) -> 0.55 | I53: =INDEX(Cov_Mu,MATCH(C53,Cov_Cod,0)) -> 76000 | J53: =IF(INDEX(Cov_FR,MATCH(C53,Cov_Cod,0))="S",INDEX(PF_Factor,MATCH("SAU|"&B53,PF_Key,0)),1) -> 1 | K53: =IF(C53="HOSP_INT",los_int,IF(C53="HOSP_CIR",los_cir,0))*MAX(0,room_ref*J53-INDEX(PF_Room,MATCH("SAU|"&B53,PF_Key,0))) -> 0 | L53: =MAX(0,I53*J53-K53) -> 76000 | M53: =f_trend -> 1.182194 | N53: =H53*L53*M53/(1-EXP(-H53)) -> 116808.15 | O53: =INDEX(Cov_CV,MATCH(C53,Cov_Cod,0)) -> 0.3 | P53: =SQRT(LN(1+O53^2)) -> 0.29356038 | Q53: =LN(N53)-P53^2/2 -> 11.625199 | R53: =IF(G53<=0,1,NORMSDIST((LN(G53)-Q53-P53^2)/P53)+G53/N53*(1-NORMSDIST((LN(G53)-Q53)/P53))) -> 0.99936104 | S53: =IF(F53="—",0,H53*L53*M53*R53) -> 49384.135 | T53: =S53*sig_SAU -> 3950.7308 | U53: =S53+T53 -> 53334.866 | V53: =U53/(1-load_SAU) -> 76192.665 | W53: =V53*ea_SAU -> 9905.0465 | X53: =V53*ec_SAU -> 9143.1198 | Y53: =V53*m_SAU -> 3809.6333 | Z53: =V53*tax_SAU -> 761.92665 | AA53: =V53+Z53 -> 76954.592 | AB53: =IF(G53>0,S53/G53*1000,"n.a.") -> 197.53654
A54: =B54&"|"&C54 -> Premium|EVAC | B54: Premium | C54: EVAC | D54: =INDEX(Cov_Nome,MATCH(C54,Cov_Cod,0)) -> Evacuação Médica e Cobertura no Estrangeiro | E54: =INDEX(Cov_Grupo,MATCH(C54,Cov_Cod,0)) -> Extensão | F54: B | G54: 100000000 | H54: =INDEX(Cov_Lambda,MATCH(C54,Cov_Cod,0)) -> 0.0012 | I54: =INDEX(Cov_Mu,MATCH(C54,Cov_Cod,0)) -> 44700960 | J54: =IF(INDEX(Cov_FR,MATCH(C54,Cov_Cod,0))="S",INDEX(PF_Factor,MATCH("SAU|"&B54,PF_Key,0)),1) -> 1 | K54: =IF(C54="HOSP_INT",los_int,IF(C54="HOSP_CIR",los_cir,0))*MAX(0,room_ref*J54-INDEX(PF_Room,MATCH("SAU|"&B54,PF_Key,0))) -> 0 | L54: =MAX(0,I54*J54-K54) -> 44700960 | M54: =f_trend -> 1.182194 | N54: =H54*L54*M54/(1-EXP(-H54)) -> 52876920 | O54: =INDEX(Cov_CV,MATCH(C54,Cov_Cod,0)) -> 1 | P54: =SQRT(LN(1+O54^2)) -> 0.83255461 | Q54: =LN(N54)-P54^2/2 -> 17.436904 | R54: =IF(G54<=0,1,NORMSDIST((LN(G54)-Q54-P54^2)/P54)+G54/N54*(1-NORMSDIST((LN(G54)-Q54)/P54))) -> 0.86092234 | S54: =IF(F54="—",0,H54*L54*M54*R54) -> 54594.743 | T54: =S54*sig_SAU -> 4367.5794 | U54: =S54+T54 -> 58962.322 | V54: =U54/(1-load_SAU) -> 84231.889 | W54: =V54*ea_SAU -> 10950.146 | X54: =V54*ec_SAU -> 10107.827 | Y54: =V54*m_SAU -> 4211.5945 | Z54: =V54*tax_SAU -> 842.31889 | AA54: =V54+Z54 -> 85074.208 | AB54: =IF(G54>0,S54/G54*1000,"n.a.") -> 0.54594743
... A56: =B56&"|"&C56 -> Premium|HEMO | B56: Premium | C56: HEMO | D56: =INDEX(Cov_Nome,MATCH(C56,Cov_Cod,0)) -> Doenças Crónicas — Hemodiálise | E56: =INDEX(Cov_Grupo,MATCH(C56,Cov_Cod,0)) -> Extensão | F56: B | G56: 25000000 | H56: =INDEX(Cov_Lambda,MATCH(C56,Cov_Cod,0)) -> 0.00025 | I56: =INDEX(Cov_Mu,MATCH(C56,Cov_Cod,0)) -> 14352000 | J56: =IF(INDEX(Cov_FR,MATCH(C56,Cov_Cod,0))="S",INDEX(PF_Factor,MATCH("SAU|"&B56,PF_Key,0)),1) -> 1 | K56: =IF(C56="HOSP_INT",los_int,IF(C56="HOSP_CIR",los_cir,0))*MAX(0,room_ref*J56-INDEX(PF_Room,MATCH("SAU|"&B56,PF_Key,0))) -> 0 | L56: =MAX(0,I56*J56-K56) -> 14352000 | M56: =f_trend -> 1.182194 | N56: =H56*L56*M56/(1-EXP(-H56)) -> 16968969 | O56: =INDEX(Cov_CV,MATCH(C56,Cov_Cod,0)) -> 0.4 | P56: =SQRT(LN(1+O56^2)) -> 0.38525317 | Q56: =LN(N56)-P56^2/2 -> 16.572687 | R56: =IF(G56<=0,1,NORMSDIST((LN(G56)-Q56-P56^2)/P56)+G56/N56*(1-NORMSDIST((LN(G56)-Q56)/P56))) -> 0.9619208 | S56: =IF(F56="—",0,H56*L56*M56*R56) -> 4080.1911 | T56: =S56*sig_SAU -> 326.41528 | U56: =S56+T56 -> 4406.6063 | V56: =U56/(1-load_SAU) -> 6295.1519 | W56: =V56*ea_SAU -> 818.36975 | X56: =V56*ec_SAU -> 755.41823 | Y56: =V56*m_SAU -> 314.7576 | Z56: =V56*tax_SAU -> 62.951519 | AA56: =V56+Z56 -> 6358.1034 | AB56: =IF(G56>0,S56/G56*1000,"n.a.") -> 0.16320764
A59: 2. TARIFA DO PACOTE BASE (coberturas "B") POR ESCALÃO ETÁRIO E GÉNERO — por Pessoa Segura / anuidade
B60: Escalão | C60: Género | D60: Chave célula | E60: Base — Prémio Puro | F60: Base — Prémio Risco Técnico | G60: Base — Prémio Comercial Bruto | H60: Base — Prémio Total Anual | I60: Base — Mensal (c/ fracc.) | J60: Conforto — Prémio Puro | K60: Conforto — Prémio Risco Técnico | L60: Conforto — Prémio Comercial Bruto | M60: Conforto — Prémio Total Anual | N60: Conforto — Mensal (c/ fracc.) | O60: Premium — Prémio Puro | P60: Premium — Prémio Risco Técnico | Q60: Premium — Prémio Comercial Bruto | R60: Premium — Prémio Total Anual | S60: Premium — Mensal (c/ fracc.) | T60: Vidas expostas (peso)
B61: 0-17 | C61: M | D61: =C61&"|"&B61 -> M|0-17 | E61: =SUMPRODUCT(--($F$6:$F$22="B"),$S$6:$S$22,INDEX(RelMatrix,0,MATCH($D61,Rel_Keys,0))) -> 78961.761 | F61: =E61*(1+sig_SAU) -> 85278.702 | G61: =F61/(1-load_SAU) -> 121826.72 | H61: =G61*(1+tax_SAU) -> 123044.98 | I61: =H61*(1+INDEX(Frac_Enc,4))/12 -> 10663.899 | J61: =SUMPRODUCT(--($F$23:$F$39="B"),$S$23:$S$39,INDEX(RelMatrix,0,MATCH($D61,Rel_Keys,0))) -> 255371.3 | K61: =J61*(1+sig_SAU) -> 275801 | L61: =K61/(1-load_SAU) -> 394001.43 | M61: =L61*(1+tax_SAU) -> 397941.44 | N61: =M61*(1+INDEX(Frac_Enc,4))/12 -> 34488.259 | O61: =SUMPRODUCT(--($F$40:$F$56="B"),$S$40:$S$56,INDEX(RelMatrix,0,MATCH($D61,Rel_Keys,0))) -> 498721.84 | P61: =O61*(1+sig_SAU) -> 538619.59 | Q61: =P61/(1-load_SAU) -> 769456.55 | R61: =Q61*(1+tax_SAU) -> 777151.12 | S61: =R61*(1+INDEX(Frac_Enc,4))/12 -> 67353.097 | T61: =IF(C61="M",INDEX(Exp_M,MATCH(B61,Exp_Band,0)),INDEX(Exp_F,MATCH(B61,Exp_Band,0))) -> 3200
B62: 0-17 | C62: F | D62: =C62&"|"&B62 -> F|0-17 | E62: =SUMPRODUCT(--($F$6:$F$22="B"),$S$6:$S$22,INDEX(RelMatrix,0,MATCH($D62,Rel_Keys,0))) -> 74066.533 | F62: =E62*(1+sig_SAU) -> 79991.856 | G62: =F62/(1-load_SAU) -> 114274.08 | H62: =G62*(1+tax_SAU) -> 115416.82 | I62: =H62*(1+INDEX(Frac_Enc,4))/12 -> 10002.791 | J62: =SUMPRODUCT(--($F$23:$F$39="B"),$S$23:$S$39,INDEX(RelMatrix,0,MATCH($D62,Rel_Keys,0))) -> 244442.06 | K62: =J62*(1+sig_SAU) -> 263997.43 | L62: =K62/(1-load_SAU) -> 377139.18 | M62: =L62*(1+tax_SAU) -> 380910.57 | N62: =M62*(1+INDEX(Frac_Enc,4))/12 -> 33012.25 | O62: =SUMPRODUCT(--($F$40:$F$56="B"),$S$40:$S$56,INDEX(RelMatrix,0,MATCH($D62,Rel_Keys,0))) -> 490549.52 | P62: =O62*(1+sig_SAU) -> 529793.48 | Q62: =P62/(1-load_SAU) -> 756847.83 | R62: =Q62*(1+tax_SAU) -> 764416.31 | S62: =R62*(1+INDEX(Frac_Enc,4))/12 -> 66249.414 | T62: =IF(C62="M",INDEX(Exp_M,MATCH(B62,Exp_Band,0)),INDEX(Exp_F,MATCH(B62,Exp_Band,0))) -> 3100
B63: 18-35 | C63: M | D63: =C63&"|"&B63 -> M|18-35 | E63: =SUMPRODUCT(--($F$6:$F$22="B"),$S$6:$S$22,INDEX(RelMatrix,0,MATCH($D63,Rel_Keys,0))) -> 99410.31 | F63: =E63*(1+sig_SAU) -> 107363.13 | G63: =F63/(1-load_SAU) -> 153375.91 | H63: =G63*(1+tax_SAU) -> 154909.67 | I63: =H63*(1+INDEX(Frac_Enc,4))/12 -> 13425.504 | J63: =SUMPRODUCT(--($F$23:$F$39="B"),$S$23:$S$39,INDEX(RelMatrix,0,MATCH($D63,Rel_Keys,0))) -> 285757.02 | K63: =J63*(1+sig_SAU) -> 308617.58 | L63: =K63/(1-load_SAU) -> 440882.26 | M63: =L63*(1+tax_SAU) -> 445291.08 | N63: =M63*(1+INDEX(Frac_Enc,4))/12 -> 38591.894 | O63: =SUMPRODUCT(--($F$40:$F$56="B"),$S$40:$S$56,INDEX(RelMatrix,0,MATCH($D63,Rel_Keys,0))) -> 640769.31 | P63: =O63*(1+sig_SAU) -> 692030.85 | Q63: =P63/(1-load_SAU) -> 988615.51 | R63: =Q63*(1+tax_SAU) -> 998501.66 | S63: =R63*(1+INDEX(Frac_Enc,4))/12 -> 86536.811 | T63: =IF(C63="M",INDEX(Exp_M,MATCH(B63,Exp_Band,0)),INDEX(Exp_F,MATCH(B63,Exp_Band,0))) -> 4600
B64: 18-35 | C64: F | D64: =C64&"|"&B64 -> F|18-35 | E64: =SUMPRODUCT(--($F$6:$F$22="B"),$S$6:$S$22,INDEX(RelMatrix,0,MATCH($D64,Rel_Keys,0))) -> 113766.81 | F64: =E64*(1+sig_SAU) -> 122868.16 | G64: =F64/(1-load_SAU) -> 175525.94 | H64: =G64*(1+tax_SAU) -> 177281.2 | I64: =H64*(1+INDEX(Frac_Enc,4))/12 -> 15364.371 | J64: =SUMPRODUCT(--($F$23:$F$39="B"),$S$23:$S$39,INDEX(RelMatrix,0,MATCH($D64,Rel_Keys,0))) -> 371531.43 | K64: =J64*(1+sig_SAU) -> 401253.94 | L64: =K64/(1-load_SAU) -> 573219.92 | M64: =L64*(1+tax_SAU) -> 578952.12 | N64: =M64*(1+INDEX(Frac_Enc,4))/12 -> 50175.85 | O64: =SUMPRODUCT(--($F$40:$F$56="B"),$S$40:$S$56,INDEX(RelMatrix,0,MATCH($D64,Rel_Keys,0))) -> 904879.78 | P64: =O64*(1+sig_SAU) -> 977270.16 | Q64: =P64/(1-load_SAU) -> 1396100.2 | R64: =Q64*(1+tax_SAU) -> 1410061.2 | S64: =R64*(1+INDEX(Frac_Enc,4))/12 -> 122205.31 | T64: =IF(C64="M",INDEX(Exp_M,MATCH(B64,Exp_Band,0)),INDEX(Exp_F,MATCH(B64,Exp_Band,0))) -> 4200
B65: 36-50 | C65: M | D65: =C65&"|"&B65 -> M|36-50 | E65: =SUMPRODUCT(--($F$6:$F$22="B"),$S$6:$S$22,INDEX(RelMatrix,0,MATCH($D65,Rel_Keys,0))) -> 138719.69 | F65: =E65*(1+sig_SAU) -> 149817.27 | G65: =F65/(1-load_SAU) -> 214024.67 | H65: =G65*(1+tax_SAU) -> 216164.92 | I65: =H65*(1+INDEX(Frac_Enc,4))/12 -> 18734.293 | J65: =SUMPRODUCT(--($F$23:$F$39="B"),$S$23:$S$39,INDEX(RelMatrix,0,MATCH($D65,Rel_Keys,0))) -> 384163.62 | K65: =J65*(1+sig_SAU) -> 414896.71 | L65: =K65/(1-load_SAU) -> 592709.59 | M65: =L65*(1+tax_SAU) -> 598636.69 | N65: =M65*(1+INDEX(Frac_Enc,4))/12 -> 51881.846 | O65: =SUMPRODUCT(--($F$40:$F$56="B"),$S$40:$S$56,INDEX(RelMatrix,0,MATCH($D65,Rel_Keys,0))) -> 920081.41 | P65: =O65*(1+sig_SAU) -> 993687.93 | Q65: =P65/(1-load_SAU) -> 1419554.2 | R65: =Q65*(1+tax_SAU) -> 1433749.7 | S65: =R65*(1+INDEX(Frac_Enc,4))/12 -> 124258.31 | T65: =IF(C65="M",INDEX(Exp_M,MATCH(B65,Exp_Band,0)),INDEX(Exp_F,MATCH(B65,Exp_Band,0))) -> 3300
B66: 36-50 | C66: F | D66: =C66&"|"&B66 -> F|36-50 | E66: =SUMPRODUCT(--($F$6:$F$22="B"),$S$6:$S$22,INDEX(RelMatrix,0,MATCH($D66,Rel_Keys,0))) -> 141541.3 | F66: =E66*(1+sig_SAU) -> 152864.6 | G66: =F66/(1-load_SAU) -> 218378 | H66: =G66*(1+tax_SAU) -> 220561.78 | I66: =H66*(1+INDEX(Frac_Enc,4))/12 -> 19115.354 | J66: =SUMPRODUCT(--($F$23:$F$39="B"),$S$23:$S$39,INDEX(RelMatrix,0,MATCH($D66,Rel_Keys,0))) -> 436868.88 | K66: =J66*(1+sig_SAU) -> 471818.39 | L66: =K66/(1-load_SAU) -> 674026.27 | M66: =L66*(1+tax_SAU) -> 680766.54 | N66: =M66*(1+INDEX(Frac_Enc,4))/12 -> 58999.766 | O66: =SUMPRODUCT(--($F$40:$F$56="B"),$S$40:$S$56,INDEX(RelMatrix,0,MATCH($D66,Rel_Keys,0))) -> 1059002.2 | P66: =O66*(1+sig_SAU) -> 1143722.3 | Q66: =P66/(1-load_SAU) -> 1633889.1 | R66: =Q66*(1+tax_SAU) -> 1650227.9 | S66: =R66*(1+INDEX(Frac_Enc,4))/12 -> 143019.76 | T66: =IF(C66="M",INDEX(Exp_M,MATCH(B66,Exp_Band,0)),INDEX(Exp_F,MATCH(B66,Exp_Band,0))) -> 2700
B67: 51-65 | C67: M | D67: =C67&"|"&B67 -> M|51-65 | E67: =SUMPRODUCT(--($F$6:$F$22="B"),$S$6:$S$22,INDEX(RelMatrix,0,MATCH($D67,Rel_Keys,0))) -> 214621.51 | F67: =E67*(1+sig_SAU) -> 231791.23 | G67: =F67/(1-load_SAU) -> 331130.33 | H67: =G67*(1+tax_SAU) -> 334441.64 | I67: =H67*(1+INDEX(Frac_Enc,4))/12 -> 28984.942 | J67: =SUMPRODUCT(--($F$23:$F$39="B"),$S$23:$S$39,INDEX(RelMatrix,0,MATCH($D67,Rel_Keys,0))) -> 565158.17 | K67: =J67*(1+sig_SAU) -> 610370.82 | L67: =K67/(1-load_SAU) -> 871958.32 | M67: =L67*(1+tax_SAU) -> 880677.9 | N67: =M67*(1+INDEX(Frac_Enc,4))/12 -> 76325.418 | O67: =SUMPRODUCT(--($F$40:$F$56="B"),$S$40:$S$56,INDEX(RelMatrix,0,MATCH($D67,Rel_Keys,0))) -> 1400285 | P67: =O67*(1+sig_SAU) -> 1512307.8 | Q67: =P67/(1-load_SAU) -> 2160439.8 | R67: =Q67*(1+tax_SAU) -> 2182044.1 | S67: =R67*(1+INDEX(Frac_Enc,4))/12 -> 189110.49 | T67: =IF(C67="M",INDEX(Exp_M,MATCH(B67,Exp_Band,0)),INDEX(Exp_F,MATCH(B67,Exp_Band,0))) -> 1500
B68: 51-65 | C68: F | D68: =C68&"|"&B68 -> F|51-65 | E68: =SUMPRODUCT(--($F$6:$F$22="B"),$S$6:$S$22,INDEX(RelMatrix,0,MATCH($D68,Rel_Keys,0))) -> 198499.56 | F68: =E68*(1+sig_SAU) -> 214379.52 | G68: =F68/(1-load_SAU) -> 306256.46 | H68: =G68*(1+tax_SAU) -> 309319.03 | I68: =H68*(1+INDEX(Frac_Enc,4))/12 -> 26807.649 | J68: =SUMPRODUCT(--($F$23:$F$39="B"),$S$23:$S$39,INDEX(RelMatrix,0,MATCH($D68,Rel_Keys,0))) -> 563798.81 | K68: =J68*(1+sig_SAU) -> 608902.72 | L68: =K68/(1-load_SAU) -> 869861.02 | M68: =L68*(1+tax_SAU) -> 878559.63 | N68: =M68*(1+INDEX(Frac_Enc,4))/12 -> 76141.835 | O68: =SUMPRODUCT(--($F$40:$F$56="B"),$S$40:$S$56,INDEX(RelMatrix,0,MATCH($D68,Rel_Keys,0))) -> 1384464.2 | P68: =O68*(1+sig_SAU) -> 1495221.4 | Q68: =P68/(1-load_SAU) -> 2136030.6 | R68: =Q68*(1+tax_SAU) -> 2157390.9 | S68: =R68*(1+INDEX(Frac_Enc,4))/12 -> 186973.87 | T68: =IF(C68="M",INDEX(Exp_M,MATCH(B68,Exp_Band,0)),INDEX(Exp_F,MATCH(B68,Exp_Band,0))) -> 1200
B69: >65 | C69: M | D69: =C69&"|"&B69 -> M|>65 | E69: =SUMPRODUCT(--($F$6:$F$22="B"),$S$6:$S$22,INDEX(RelMatrix,0,MATCH($D69,Rel_Keys,0))) -> 316385.76 | F69: =E69*(1+sig_SAU) -> 341696.62 | G69: =F69/(1-load_SAU) -> 488138.02 | H69: =G69*(1+tax_SAU) -> 493019.4 | I69: =H69*(1+INDEX(Frac_Enc,4))/12 -> 42728.348 | J69: =SUMPRODUCT(--($F$23:$F$39="B"),$S$23:$S$39,INDEX(RelMatrix,0,MATCH($D69,Rel_Keys,0))) -> 779012.37 | K69: =J69*(1+sig_SAU) -> 841333.35 | L69: =K69/(1-load_SAU) -> 1201904.8 | M69: =L69*(1+tax_SAU) -> 1213923.8 | N69: =M69*(1+INDEX(Frac_Enc,4))/12 -> 105206.73 | O69: =SUMPRODUCT(--($F$40:$F$56="B"),$S$40:$S$56,INDEX(RelMatrix,0,MATCH($D69,Rel_Keys,0))) -> 1866078.8 | P69: =O69*(1+sig_SAU) -> 2015365.1 | Q69: =P69/(1-load_SAU) -> 2879093 | R69: =Q69*(1+tax_SAU) -> 2907884 | S69: =R69*(1+INDEX(Frac_Enc,4))/12 -> 252016.61 | T69: =IF(C69="M",INDEX(Exp_M,MATCH(B69,Exp_Band,0)),INDEX(Exp_F,MATCH(B69,Exp_Band,0))) -> 450
B70: >65 | C70: F | D70: =C70&"|"&B70 -> F|>65 | E70: =SUMPRODUCT(--($F$6:$F$22="B"),$S$6:$S$22,INDEX(RelMatrix,0,MATCH($D70,Rel_Keys,0))) -> 289420.08 | F70: =E70*(1+sig_SAU) -> 312573.69 | G70: =F70/(1-load_SAU) -> 446533.84 | H70: =G70*(1+tax_SAU) -> 450999.17 | I70: =H70*(1+INDEX(Frac_Enc,4))/12 -> 39086.595 | J70: =SUMPRODUCT(--($F$23:$F$39="B"),$S$23:$S$39,INDEX(RelMatrix,0,MATCH($D70,Rel_Keys,0))) -> 748531.94 | K70: =J70*(1+sig_SAU) -> 808414.5 | L70: =K70/(1-load_SAU) -> 1154877.9 | M70: =L70*(1+tax_SAU) -> 1166426.6 | N70: =M70*(1+INDEX(Frac_Enc,4))/12 -> 101090.31 | O70: =SUMPRODUCT(--($F$40:$F$56="B"),$S$40:$S$56,INDEX(RelMatrix,0,MATCH($D70,Rel_Keys,0))) -> 1779600.1 | P70: =O70*(1+sig_SAU) -> 1921968.1 | Q70: =P70/(1-load_SAU) -> 2745668.7 | R70: =Q70*(1+tax_SAU) -> 2773125.4 | S70: =R70*(1+INDEX(Frac_Enc,4))/12 -> 240337.53 | T70: =IF(C70="M",INDEX(Exp_M,MATCH(B70,Exp_Band,0)),INDEX(Exp_F,MATCH(B70,Exp_Band,0))) -> 400
B71: Média ponderada pela carteira | E71: =SUMPRODUCT(E61:E70,$T$61:$T$70)/SUM($T$61:$T$70) -> 124770.86 | F71: =SUMPRODUCT(F61:F70,$T$61:$T$70)/SUM($T$61:$T$70) -> 134752.53 | G71: =SUMPRODUCT(G61:G70,$T$61:$T$70)/SUM($T$61:$T$70) -> 192503.62 | H71: =SUMPRODUCT(H61:H70,$T$61:$T$70)/SUM($T$61:$T$70) -> 194428.65 | I71: =SUMPRODUCT(I61:I70,$T$61:$T$70)/SUM($T$61:$T$70) -> 16850.483 | J71: =SUMPRODUCT(J61:J70,$T$61:$T$70)/SUM($T$61:$T$70) -> 368009.04 | K71: =SUMPRODUCT(K61:K70,$T$61:$T$70)/SUM($T$61:$T$70) -> 397449.77 | L71: =SUMPRODUCT(L61:L70,$T$61:$T$70)/SUM($T$61:$T$70) -> 567785.38 | ... S71: =SUMPRODUCT(S61:S70,$T$61:$T$70)/SUM($T$61:$T$70) -> 115457.09 | T71: =SUM(T61:T70) -> 24650
A74: 3. TARIFA DAS COBERTURAS OPCIONAIS / EXTENSÕES MODULARES — Prémio Total Anual por Pessoa Segura (unisex), por escalão
C75: Cobertura | D75: Base | I75: Conforto | N75: Premium
B76: Código | C76: Cobertura | D76: 0-17 | E76: 18-35 | F76: 36-50 | G76: 51-65 | H76: >65 | I76: 0-17 | J76: 18-35 | K76: 36-50 | L76: 51-65 | M76: >65 | N76: 0-17 | O76: 18-35 | P76: 36-50 | Q76: 51-65 | R76: >65
B77: HOSP_INT | C77: =INDEX(Cov_Nome,MATCH(B77,Cov_Cod,0)) -> Internamento Hospitalar Médico (incl. malária grave) | D77: =IF(INDEX(SAU_Status,MATCH("Base|"&$B77,SAU_Key,0))="O",INDEX(SAU_PP,MATCH("Base|"&$B77,SAU_Key,0))*INDEX(RelUni,MATCH($B77,Cov_Cod,0),1)*(1+sig_SAU)/(1-load_SAU)*(1+tax_SAU),IF(INDEX(SAU_Status,MATCH("Base|"&$B77,SAU_Key,0))="B","Incluída","n.d.")) -> Incluída | E77: =IF(INDEX(SAU_Status,MATCH("Base|"&$B77,SAU_Key,0))="O",INDEX(SAU_PP,MATCH("Base|"&$B77,SAU_Key,0))*INDEX(RelUni,MATCH($B77,Cov_Cod,0),2)*(1+sig_SAU)/(1-load_SAU)*(1+tax_SAU),IF(INDEX(SAU_Status,MATCH("Base|"&$B77,SAU_Key,0))="B","Incluída","n.d.")) -> Incluída | F77: =IF(INDEX(SAU_Status,MATCH("Base|"&$B77,SAU_Key,0))="O",INDEX(SAU_PP,MATCH("Base|"&$B77,SAU_Key,0))*INDEX(RelUni,MATCH($B77,Cov_Cod,0),3)*(1+sig_SAU)/(1-load_SAU)*(1+tax_SAU),IF(INDEX(SAU_Status,MATCH("Base|"&$B77,SAU_Key,0))="B","Incluída","n.d.")) -> Incluída | G77: =IF(INDEX(SAU_Status,MATCH("Base|"&$B77,SAU_Key,0))="O",INDEX(SAU_PP,MATCH("Base|"&$B77,SAU_Key,0))*INDEX(RelUni,MATCH($B77,Cov_Cod,0),4)*(1+sig_SAU)/(1-load_SAU)*(1+tax_SAU),IF(INDEX(SAU_Status,MATCH("Base|"&$B77,SAU_Key,0))="B","Incluída","n.d.")) -> Incluída | H77: =IF(INDEX(SAU_Status,MATCH("Base|"&$B77,SAU_Key,0))="O",INDEX(SAU_PP,MATCH("Base|"&$B77,SAU_Key,0))*INDEX(RelUni,MATCH($B77,Cov_Cod,0),5)*(1+sig_SAU)/(1-load_SAU)*(1+tax_SAU),IF(INDEX(SAU_Status,MATCH("Base|"&$B77,SAU_Key,0))="B","Incluída","n.d.")) -> Incluída | I77: =IF(INDEX(SAU_Status,MATCH("Conforto|"&$B77,SAU_Key,0))="O",INDEX(SAU_PP,MATCH("Conforto|"&$B77,SAU_Key,0))*INDEX(RelUni,MATCH($B77,Cov_Cod,0),1)*(1+sig_SAU)/(1-load_SAU)*(1+tax_SAU),IF(INDEX(SAU_Status,MATCH("Conforto|"&$B77,SAU_Key,0))="B","Incluída","n.d.")) -> Incluída | J77: =IF(INDEX(SAU_Status,MATCH("Conforto|"&$B77,SAU_Key,0))="O",INDEX(SAU_PP,MATCH("Conforto|"&$B77,SAU_Key,0))*INDEX(RelUni,MATCH($B77,Cov_Cod,0),2)*(1+sig_SAU)/(1-load_SAU)*(1+tax_SAU),IF(INDEX(SAU_Status,MATCH("Conforto|"&$B77,SAU_Key,0))="B","Incluída","n.d.")) -> Incluída | K77: =IF(INDEX(SAU_Status,MATCH("Conforto|"&$B77,SAU_Key,0))="O",INDEX(SAU_PP,MATCH("Conforto|"&$B77,SAU_Key,0))*INDEX(RelUni,MATCH($B77,Cov_Cod,0),3)*(1+sig_SAU)/(1-load_SAU)*(1+tax_SAU),IF(INDEX(SAU_Status,MATCH("Conforto|"&$B77,SAU_Key,0))="B","Incluída","n.d.")) -> Incluída | L77: =IF(INDEX(SAU_Status,MATCH("Conforto|"&$B77,SAU_Key,0))="O",INDEX(SAU_PP,MATCH("Conforto|"&$B77,SAU_Key,0))*INDEX(RelUni,MATCH($B77,Cov_Cod,0),4)*(1+sig_SAU)/(1-load_SAU)*(1+tax_SAU),IF(INDEX(SAU_Status,MATCH("Conforto|"&$B77,SAU_Key,0))="B","Incluída","n.d.")) -> Incluída | M77: =IF(INDEX(SAU_Status,MATCH("Conforto|"&$B77,SAU_Key,0))="O",INDEX(SAU_PP,MATCH("Conforto|"&$B77,SAU_Key,0))*INDEX(RelUni,MATCH($B77,Cov_Cod,0),5)*(1+sig_SAU)/(1-load_SAU)*(1+tax_SAU),IF(INDEX(SAU_Status,MATCH("Conforto|"&$B77,SAU_Key,0))="B","Incluída","n.d.")) -> Incluída | N77: =IF(INDEX(SAU_Status,MATCH("Premium|"&$B77,SAU_Key,0))="O",INDEX(SAU_PP,MATCH("Premium|"&$B77,SAU_Key,0))*INDEX(RelUni,MATCH($B77,Cov_Cod,0),1)*(1+sig_SAU)/(1-load_SAU)*(1+tax_SAU),IF(INDEX(SAU_Status,MATCH("Premium|"&$B77,SAU_Key,0))="B","Incluída","n.d.")) -> Incluída | O77: =IF(INDEX(SAU_Status,MATCH("Premium|"&$B77,SAU_Key,0))="O",INDEX(SAU_PP,MATCH("Premium|"&$B77,SAU_Key,0))*INDEX(RelUni,MATCH($B77,Cov_Cod,0),2)*(1+sig_SAU)/(1-load_SAU)*(1+tax_SAU),IF(INDEX(SAU_Status,MATCH("Premium|"&$B77,SAU_Key,0))="B","Incluída","n.d.")) -> Incluída | P77: =IF(INDEX(SAU_Status,MATCH("Premium|"&$B77,SAU_Key,0))="O",INDEX(SAU_PP,MATCH("Premium|"&$B77,SAU_Key,0))*INDEX(RelUni,MATCH($B77,Cov_Cod,0),3)*(1+sig_SAU)/(1-load_SAU)*(1+tax_SAU),IF(INDEX(SAU_Status,MATCH("Premium|"&$B77,SAU_Key,0))="B","Incluída","n.d.")) -> Incluída | Q77: =IF(INDEX(SAU_Status,MATCH("Premium|"&$B77,SAU_Key,0))="O",INDEX(SAU_PP,MATCH("Premium|"&$B77,SAU_Key,0))*INDEX(RelUni,MATCH($B77,Cov_Cod,0),4)*(1+sig_SAU)/(1-load_SAU)*(1+tax_SAU),IF(INDEX(SAU_Status,MATCH("Premium|"&$B77,SAU_Key,0))="B","Incluída","n.d.")) -> Incluída | R77: =IF(INDEX(SAU_Status,MATCH("Premium|"&$B77,SAU_Key,0))="O",INDEX(SAU_PP,MATCH("Premium|"&$B77,SAU_Key,0))*INDEX(RelUni,MATCH($B77,Cov_Cod,0),5)*(1+sig_SAU)/(1-load_SAU)*(1+tax_SAU),IF(INDEX(SAU_Status,MATCH("Premium|"&$B77,SAU_Key,0))="B","Incluída","n.d.")) -> Incluída
B78: HOSP_CIR | C78: =INDEX(Cov_Nome,MATCH(B78,Cov_Cod,0)) -> Cirurgia (com internamento e de ambulatório) | D78: =IF(INDEX(SAU_Status,MATCH("Base|"&$B78,SAU_Key,0))="O",INDEX(SAU_PP,MATCH("Base|"&$B78,SAU_Key,0))*INDEX(RelUni,MATCH($B78,Cov_Cod,0),1)*(1+sig_SAU)/(1-load_SAU)*(1+tax_SAU),IF(INDEX(SAU_Status,MATCH("Base|"&$B78,SAU_Key,0))="B","Incluída","n.d.")) -> Incluída | E78: =IF(INDEX(SAU_Status,MATCH("Base|"&$B78,SAU_Key,0))="O",INDEX(SAU_PP,MATCH("Base|"&$B78,SAU_Key,0))*INDEX(RelUni,MATCH($B78,Cov_Cod,0),2)*(1+sig_SAU)/(1-load_SAU)*(1+tax_SAU),IF(INDEX(SAU_Status,MATCH("Base|"&$B78,SAU_Key,0))="B","Incluída","n.d.")) -> Incluída | F78: =IF(INDEX(SAU_Status,MATCH("Base|"&$B78,SAU_Key,0))="O",INDEX(SAU_PP,MATCH("Base|"&$B78,SAU_Key,0))*INDEX(RelUni,MATCH($B78,Cov_Cod,0),3)*(1+sig_SAU)/(1-load_SAU)*(1+tax_SAU),IF(INDEX(SAU_Status,MATCH("Base|"&$B78,SAU_Key,0))="B","Incluída","n.d.")) -> Incluída | G78: =IF(INDEX(SAU_Status,MATCH("Base|"&$B78,SAU_Key,0))="O",INDEX(SAU_PP,MATCH("Base|"&$B78,SAU_Key,0))*INDEX(RelUni,MATCH($B78,Cov_Cod,0),4)*(1+sig_SAU)/(1-load_SAU)*(1+tax_SAU),IF(INDEX(SAU_Status,MATCH("Base|"&$B78,SAU_Key,0))="B","Incluída","n.d.")) -> Incluída | H78: =IF(INDEX(SAU_Status,MATCH("Base|"&$B78,SAU_Key,0))="O",INDEX(SAU_PP,MATCH("Base|"&$B78,SAU_Key,0))*INDEX(RelUni,MATCH($B78,Cov_Cod,0),5)*(1+sig_SAU)/(1-load_SAU)*(1+tax_SAU),IF(INDEX(SAU_Status,MATCH("Base|"&$B78,SAU_Key,0))="B","Incluída","n.d.")) -> Incluída | I78: =IF(INDEX(SAU_Status,MATCH("Conforto|"&$B78,SAU_Key,0))="O",INDEX(SAU_PP,MATCH("Conforto|"&$B78,SAU_Key,0))*INDEX(RelUni,MATCH($B78,Cov_Cod,0),1)*(1+sig_SAU)/(1-load_SAU)*(1+tax_SAU),IF(INDEX(SAU_Status,MATCH("Conforto|"&$B78,SAU_Key,0))="B","Incluída","n.d.")) -> Incluída | J78: =IF(INDEX(SAU_Status,MATCH("Conforto|"&$B78,SAU_Key,0))="O",INDEX(SAU_PP,MATCH("Conforto|"&$B78,SAU_Key,0))*INDEX(RelUni,MATCH($B78,Cov_Cod,0),2)*(1+sig_SAU)/(1-load_SAU)*(1+tax_SAU),IF(INDEX(SAU_Status,MATCH("Conforto|"&$B78,SAU_Key,0))="B","Incluída","n.d.")) -> Incluída | K78: =IF(INDEX(SAU_Status,MATCH("Conforto|"&$B78,SAU_Key,0))="O",INDEX(SAU_PP,MATCH("Conforto|"&$B78,SAU_Key,0))*INDEX(RelUni,MATCH($B78,Cov_Cod,0),3)*(1+sig_SAU)/(1-load_SAU)*(1+tax_SAU),IF(INDEX(SAU_Status,MATCH("Conforto|"&$B78,SAU_Key,0))="B","Incluída","n.d.")) -> Incluída | L78: =IF(INDEX(SAU_Status,MATCH("Conforto|"&$B78,SAU_Key,0))="O",INDEX(SAU_PP,MATCH("Conforto|"&$B78,SAU_Key,0))*INDEX(RelUni,MATCH($B78,Cov_Cod,0),4)*(1+sig_SAU)/(1-load_SAU)*(1+tax_SAU),IF(INDEX(SAU_Status,MATCH("Conforto|"&$B78,SAU_Key,0))="B","Incluída","n.d.")) -> Incluída | M78: =IF(INDEX(SAU_Status,MATCH("Conforto|"&$B78,SAU_Key,0))="O",INDEX(SAU_PP,MATCH("Conforto|"&$B78,SAU_Key,0))*INDEX(RelUni,MATCH($B78,Cov_Cod,0),5)*(1+sig_SAU)/(1-load_SAU)*(1+tax_SAU),IF(INDEX(SAU_Status,MATCH("Conforto|"&$B78,SAU_Key,0))="B","Incluída","n.d.")) -> Incluída | N78: =IF(INDEX(SAU_Status,MATCH("Premium|"&$B78,SAU_Key,0))="O",INDEX(SAU_PP,MATCH("Premium|"&$B78,SAU_Key,0))*INDEX(RelUni,MATCH($B78,Cov_Cod,0),1)*(1+sig_SAU)/(1-load_SAU)*(1+tax_SAU),IF(INDEX(SAU_Status,MATCH("Premium|"&$B78,SAU_Key,0))="B","Incluída","n.d.")) -> Incluída | O78: =IF(INDEX(SAU_Status,MATCH("Premium|"&$B78,SAU_Key,0))="O",INDEX(SAU_PP,MATCH("Premium|"&$B78,SAU_Key,0))*INDEX(RelUni,MATCH($B78,Cov_Cod,0),2)*(1+sig_SAU)/(1-load_SAU)*(1+tax_SAU),IF(INDEX(SAU_Status,MATCH("Premium|"&$B78,SAU_Key,0))="B","Incluída","n.d.")) -> Incluída | P78: =IF(INDEX(SAU_Status,MATCH("Premium|"&$B78,SAU_Key,0))="O",INDEX(SAU_PP,MATCH("Premium|"&$B78,SAU_Key,0))*INDEX(RelUni,MATCH($B78,Cov_Cod,0),3)*(1+sig_SAU)/(1-load_SAU)*(1+tax_SAU),IF(INDEX(SAU_Status,MATCH("Premium|"&$B78,SAU_Key,0))="B","Incluída","n.d.")) -> Incluída | Q78: =IF(INDEX(SAU_Status,MATCH("Premium|"&$B78,SAU_Key,0))="O",INDEX(SAU_PP,MATCH("Premium|"&$B78,SAU_Key,0))*INDEX(RelUni,MATCH($B78,Cov_Cod,0),4)*(1+sig_SAU)/(1-load_SAU)*(1+tax_SAU),IF(INDEX(SAU_Status,MATCH("Premium|"&$B78,SAU_Key,0))="B","Incluída","n.d.")) -> Incluída | R78: =IF(INDEX(SAU_Status,MATCH("Premium|"&$B78,SAU_Key,0))="O",INDEX(SAU_PP,MATCH("Premium|"&$B78,SAU_Key,0))*INDEX(RelUni,MATCH($B78,Cov_Cod,0),5)*(1+sig_SAU)/(1-load_SAU)*(1+tax_SAU),IF(INDEX(SAU_Status,MATCH("Premium|"&$B78,SAU_Key,0))="B","Incluída","n.d.")) -> Incluída
B79: HOSP_UCI | C79: =INDEX(Cov_Nome,MATCH(B79,Cov_Cod,0)) -> Cuidados Intensivos (UCI) | D79: =IF(INDEX(SAU_Status,MATCH("Base|"&$B79,SAU_Key,0))="O",INDEX(SAU_PP,MATCH("Base|"&$B79,SAU_Key,0))*INDEX(RelUni,MATCH($B79,Cov_Cod,0),1)*(1+sig_SAU)/(1-load_SAU)*(1+tax_SAU),IF(INDEX(SAU_Status,MATCH("Base|"&$B79,SAU_Key,0))="B","Incluída","n.d.")) -> Incluída | E79: =IF(INDEX(SAU_Status,MATCH("Base|"&$B79,SAU_Key,0))="O",INDEX(SAU_PP,MATCH("Base|"&$B79,SAU_Key,0))*INDEX(RelUni,MATCH($B79,Cov_Cod,0),2)*(1+sig_SAU)/(1-load_SAU)*(1+tax_SAU),IF(INDEX(SAU_Status,MATCH("Base|"&$B79,SAU_Key,0))="B","Incluída","n.d.")) -> Incluída | F79: =IF(INDEX(SAU_Status,MATCH("Base|"&$B79,SAU_Key,0))="O",INDEX(SAU_PP,MATCH("Base|"&$B79,SAU_Key,0))*INDEX(RelUni,MATCH($B79,Cov_Cod,0),3)*(1+sig_SAU)/(1-load_SAU)*(1+tax_SAU),IF(INDEX(SAU_Status,MATCH("Base|"&$B79,SAU_Key,0))="B","Incluída","n.d.")) -> Incluída | G79: =IF(INDEX(SAU_Status,MATCH("Base|"&$B79,SAU_Key,0))="O",INDEX(SAU_PP,MATCH("Base|"&$B79,SAU_Key,0))*INDEX(RelUni,MATCH($B79,Cov_Cod,0),4)*(1+sig_SAU)/(1-load_SAU)*(1+tax_SAU),IF(INDEX(SAU_Status,MATCH("Base|"&$B79,SAU_Key,0))="B","Incluída","n.d.")) -> Incluída | H79: =IF(INDEX(SAU_Status,MATCH("Base|"&$B79,SAU_Key,0))="O",INDEX(SAU_PP,MATCH("Base|"&$B79,SAU_Key,0))*INDEX(RelUni,MATCH($B79,Cov_Cod,0),5)*(1+sig_SAU)/(1-load_SAU)*(1+tax_SAU),IF(INDEX(SAU_Status,MATCH("Base|"&$B79,SAU_Key,0))="B","Incluída","n.d.")) -> Incluída | I79: =IF(INDEX(SAU_Status,MATCH("Conforto|"&$B79,SAU_Key,0))="O",INDEX(SAU_PP,MATCH("Conforto|"&$B79,SAU_Key,0))*INDEX(RelUni,MATCH($B79,Cov_Cod,0),1)*(1+sig_SAU)/(1-load_SAU)*(1+tax_SAU),IF(INDEX(SAU_Status,MATCH("Conforto|"&$B79,SAU_Key,0))="B","Incluída","n.d.")) -> Incluída | J79: =IF(INDEX(SAU_Status,MATCH("Conforto|"&$B79,SAU_Key,0))="O",INDEX(SAU_PP,MATCH("Conforto|"&$B79,SAU_Key,0))*INDEX(RelUni,MATCH($B79,Cov_Cod,0),2)*(1+sig_SAU)/(1-load_SAU)*(1+tax_SAU),IF(INDEX(SAU_Status,MATCH("Conforto|"&$B79,SAU_Key,0))="B","Incluída","n.d.")) -> Incluída | K79: =IF(INDEX(SAU_Status,MATCH("Conforto|"&$B79,SAU_Key,0))="O",INDEX(SAU_PP,MATCH("Conforto|"&$B79,SAU_Key,0))*INDEX(RelUni,MATCH($B79,Cov_Cod,0),3)*(1+sig_SAU)/(1-load_SAU)*(1+tax_SAU),IF(INDEX(SAU_Status,MATCH("Conforto|"&$B79,SAU_Key,0))="B","Incluída","n.d.")) -> Incluída | L79: =IF(INDEX(SAU_Status,MATCH("Conforto|"&$B79,SAU_Key,0))="O",INDEX(SAU_PP,MATCH("Conforto|"&$B79,SAU_Key,0))*INDEX(RelUni,MATCH($B79,Cov_Cod,0),4)*(1+sig_SAU)/(1-load_SAU)*(1+tax_SAU),IF(INDEX(SAU_Status,MATCH("Conforto|"&$B79,SAU_Key,0))="B","Incluída","n.d.")) -> Incluída | M79: =IF(INDEX(SAU_Status,MATCH("Conforto|"&$B79,SAU_Key,0))="O",INDEX(SAU_PP,MATCH("Conforto|"&$B79,SAU_Key,0))*INDEX(RelUni,MATCH($B79,Cov_Cod,0),5)*(1+sig_SAU)/(1-load_SAU)*(1+tax_SAU),IF(INDEX(SAU_Status,MATCH("Conforto|"&$B79,SAU_Key,0))="B","Incluída","n.d.")) -> Incluída | N79: =IF(INDEX(SAU_Status,MATCH("Premium|"&$B79,SAU_Key,0))="O",INDEX(SAU_PP,MATCH("Premium|"&$B79,SAU_Key,0))*INDEX(RelUni,MATCH($B79,Cov_Cod,0),1)*(1+sig_SAU)/(1-load_SAU)*(1+tax_SAU),IF(INDEX(SAU_Status,MATCH("Premium|"&$B79,SAU_Key,0))="B","Incluída","n.d.")) -> Incluída | O79: =IF(INDEX(SAU_Status,MATCH("Premium|"&$B79,SAU_Key,0))="O",INDEX(SAU_PP,MATCH("Premium|"&$B79,SAU_Key,0))*INDEX(RelUni,MATCH($B79,Cov_Cod,0),2)*(1+sig_SAU)/(1-load_SAU)*(1+tax_SAU),IF(INDEX(SAU_Status,MATCH("Premium|"&$B79,SAU_Key,0))="B","Incluída","n.d.")) -> Incluída | P79: =IF(INDEX(SAU_Status,MATCH("Premium|"&$B79,SAU_Key,0))="O",INDEX(SAU_PP,MATCH("Premium|"&$B79,SAU_Key,0))*INDEX(RelUni,MATCH($B79,Cov_Cod,0),3)*(1+sig_SAU)/(1-load_SAU)*(1+tax_SAU),IF(INDEX(SAU_Status,MATCH("Premium|"&$B79,SAU_Key,0))="B","Incluída","n.d.")) -> Incluída | Q79: =IF(INDEX(SAU_Status,MATCH("Premium|"&$B79,SAU_Key,0))="O",INDEX(SAU_PP,MATCH("Premium|"&$B79,SAU_Key,0))*INDEX(RelUni,MATCH($B79,Cov_Cod,0),4)*(1+sig_SAU)/(1-load_SAU)*(1+tax_SAU),IF(INDEX(SAU_Status,MATCH("Premium|"&$B79,SAU_Key,0))="B","Incluída","n.d.")) -> Incluída | R79: =IF(INDEX(SAU_Status,MATCH("Premium|"&$B79,SAU_Key,0))="O",INDEX(SAU_PP,MATCH("Premium|"&$B79,SAU_Key,0))*INDEX(RelUni,MATCH($B79,Cov_Cod,0),5)*(1+sig_SAU)/(1-load_SAU)*(1+tax_SAU),IF(INDEX(SAU_Status,MATCH("Premium|"&$B79,SAU_Key,0))="B","Incluída","n.d.")) -> Incluída
B80: AMB_CONS | C80: =INDEX(Cov_Nome,MATCH(B80,Cov_Cod,0)) -> Consultas de Clínica Geral e Especialidade (incl. teleconsulta) | D80: =IF(INDEX(SAU_Status,MATCH("Base|"&$B80,SAU_Key,0))="O",INDEX(SAU_PP,MATCH("Base|"&$B80,SAU_Key,0))*INDEX(RelUni,MATCH($B80,Cov_Cod,0),1)*(1+sig_SAU)/(1-load_SAU)*(1+tax_SAU),IF(INDEX(SAU_Status,MATCH("Base|"&$B80,SAU_Key,0))="B","Incluída","n.d.")) -> 109953.13 | E80: =IF(INDEX(SAU_Status,MATCH("Base|"&$B80,SAU_Key,0))="O",INDEX(SAU_PP,MATCH("Base|"&$B80,SAU_Key,0))*INDEX(RelUni,MATCH($B80,Cov_Cod,0),2)*(1+sig_SAU)/(1-load_SAU)*(1+tax_SAU),IF(INDEX(SAU_Status,MATCH("Base|"&$B80,SAU_Key,0))="B","Incluída","n.d.")) -> 118685.3 | F80: =IF(INDEX(SAU_Status,MATCH("Base|"&$B80,SAU_Key,0))="O",INDEX(SAU_PP,MATCH("Base|"&$B80,SAU_Key,0))*INDEX(RelUni,MATCH($B80,Cov_Cod,0),3)*(1+sig_SAU)/(1-load_SAU)*(1+tax_SAU),IF(INDEX(SAU_Status,MATCH("Base|"&$B80,SAU_Key,0))="B","Incluída","n.d.")) -> 137515.08 | G80: =IF(INDEX(SAU_Status,MATCH("Base|"&$B80,SAU_Key,0))="O",INDEX(SAU_PP,MATCH("Base|"&$B80,SAU_Key,0))*INDEX(RelUni,MATCH($B80,Cov_Cod,0),4)*(1+sig_SAU)/(1-load_SAU)*(1+tax_SAU),IF(INDEX(SAU_Status,MATCH("Base|"&$B80,SAU_Key,0))="B","Incluída","n.d.")) -> 169892.32 | H80: =IF(INDEX(SAU_Status,MATCH("Base|"&$B80,SAU_Key,0))="O",INDEX(SAU_PP,MATCH("Base|"&$B80,SAU_Key,0))*INDEX(RelUni,MATCH($B80,Cov_Cod,0),5)*(1+sig_SAU)/(1-load_SAU)*(1+tax_SAU),IF(INDEX(SAU_Status,MATCH("Base|"&$B80,SAU_Key,0))="B","Incluída","n.d.")) -> 209771.2 | I80: =IF(INDEX(SAU_Status,MATCH("Conforto|"&$B80,SAU_Key,0))="O",INDEX(SAU_PP,MATCH("Conforto|"&$B80,SAU_Key,0))*INDEX(RelUni,MATCH($B80,Cov_Cod,0),1)*(1+sig_SAU)/(1-load_SAU)*(1+tax_SAU),IF(INDEX(SAU_Status,MATCH("Conforto|"&$B80,SAU_Key,0))="B","Incluída","n.d.")) -> Incluída | J80: =IF(INDEX(SAU_Status,MATCH("Conforto|"&$B80,SAU_Key,0))="O",INDEX(SAU_PP,MATCH("Conforto|"&$B80,SAU_Key,0))*INDEX(RelUni,MATCH($B80,Cov_Cod,0),2)*(1+sig_SAU)/(1-load_SAU)*(1+tax_SAU),IF(INDEX(SAU_Status,MATCH("Conforto|"&$B80,SAU_Key,0))="B","Incluída","n.d.")) -> Incluída | K80: =IF(INDEX(SAU_Status,MATCH("Conforto|"&$B80,SAU_Key,0))="O",INDEX(SAU_PP,MATCH("Conforto|"&$B80,SAU_Key,0))*INDEX(RelUni,MATCH($B80,Cov_Cod,0),3)*(1+sig_SAU)/(1-load_SAU)*(1+tax_SAU),IF(INDEX(SAU_Status,MATCH("Conforto|"&$B80,SAU_Key,0))="B","Incluída","n.d.")) -> Incluída | L80: =IF(INDEX(SAU_Status,MATCH("Conforto|"&$B80,SAU_Key,0))="O",INDEX(SAU_PP,MATCH("Conforto|"&$B80,SAU_Key,0))*INDEX(RelUni,MATCH($B80,Cov_Cod,0),4)*(1+sig_SAU)/(1-load_SAU)*(1+tax_SAU),IF(INDEX(SAU_Status,MATCH("Conforto|"&$B80,SAU_Key,0))="B","Incluída","n.d.")) -> Incluída | M80: =IF(INDEX(SAU_Status,MATCH("Conforto|"&$B80,SAU_Key,0))="O",INDEX(SAU_PP,MATCH("Conforto|"&$B80,SAU_Key,0))*INDEX(RelUni,MATCH($B80,Cov_Cod,0),5)*(1+sig_SAU)/(1-load_SAU)*(1+tax_SAU),IF(INDEX(SAU_Status,MATCH("Conforto|"&$B80,SAU_Key,0))="B","Incluída","n.d.")) -> Incluída | N80: =IF(INDEX(SAU_Status,MATCH("Premium|"&$B80,SAU_Key,0))="O",INDEX(SAU_PP,MATCH("Premium|"&$B80,SAU_Key,0))*INDEX(RelUni,MATCH($B80,Cov_Cod,0),1)*(1+sig_SAU)/(1-load_SAU)*(1+tax_SAU),IF(INDEX(SAU_Status,MATCH("Premium|"&$B80,SAU_Key,0))="B","Incluída","n.d.")) -> Incluída | O80: =IF(INDEX(SAU_Status,MATCH("Premium|"&$B80,SAU_Key,0))="O",INDEX(SAU_PP,MATCH("Premium|"&$B80,SAU_Key,0))*INDEX(RelUni,MATCH($B80,Cov_Cod,0),2)*(1+sig_SAU)/(1-load_SAU)*(1+tax_SAU),IF(INDEX(SAU_Status,MATCH("Premium|"&$B80,SAU_Key,0))="B","Incluída","n.d.")) -> Incluída | P80: =IF(INDEX(SAU_Status,MATCH("Premium|"&$B80,SAU_Key,0))="O",INDEX(SAU_PP,MATCH("Premium|"&$B80,SAU_Key,0))*INDEX(RelUni,MATCH($B80,Cov_Cod,0),3)*(1+sig_SAU)/(1-load_SAU)*(1+tax_SAU),IF(INDEX(SAU_Status,MATCH("Premium|"&$B80,SAU_Key,0))="B","Incluída","n.d.")) -> Incluída | Q80: =IF(INDEX(SAU_Status,MATCH("Premium|"&$B80,SAU_Key,0))="O",INDEX(SAU_PP,MATCH("Premium|"&$B80,SAU_Key,0))*INDEX(RelUni,MATCH($B80,Cov_Cod,0),4)*(1+sig_SAU)/(1-load_SAU)*(1+tax_SAU),IF(INDEX(SAU_Status,MATCH("Premium|"&$B80,SAU_Key,0))="B","Incluída","n.d.")) -> Incluída | R80: =IF(INDEX(SAU_Status,MATCH("Premium|"&$B80,SAU_Key,0))="O",INDEX(SAU_PP,MATCH("Premium|"&$B80,SAU_Key,0))*INDEX(RelUni,MATCH($B80,Cov_Cod,0),5)*(1+sig_SAU)/(1-load_SAU)*(1+tax_SAU),IF(INDEX(SAU_Status,MATCH("Premium|"&$B80,SAU_Key,0))="B","Incluída","n.d.")) -> Incluída
B81: AMB_MCDT | C81: =INDEX(Cov_Nome,MATCH(B81,Cov_Cod,0)) -> MCDT — Exames, Análises e Imagiologia | D81: =IF(INDEX(SAU_Status,MATCH("Base|"&$B81,SAU_Key,0))="O",INDEX(SAU_PP,MATCH("Base|"&$B81,SAU_Key,0))*INDEX(RelUni,MATCH($B81,Cov_Cod,0),1)*(1+sig_SAU)/(1-load_SAU)*(1+tax_SAU),IF(INDEX(SAU_Status,MATCH("Base|"&$B81,SAU_Key,0))="B","Incluída","n.d.")) -> 60702.721 | E81: =IF(INDEX(SAU_Status,MATCH("Base|"&$B81,SAU_Key,0))="O",INDEX(SAU_PP,MATCH("Base|"&$B81,SAU_Key,0))*INDEX(RelUni,MATCH($B81,Cov_Cod,0),2)*(1+sig_SAU)/(1-load_SAU)*(1+tax_SAU),IF(INDEX(SAU_Status,MATCH("Base|"&$B81,SAU_Key,0))="B","Incluída","n.d.")) -> 107412.28 | F81: =IF(INDEX(SAU_Status,MATCH("Base|"&$B81,SAU_Key,0))="O",INDEX(SAU_PP,MATCH("Base|"&$B81,SAU_Key,0))*INDEX(RelUni,MATCH($B81,Cov_Cod,0),3)*(1+sig_SAU)/(1-load_SAU)*(1+tax_SAU),IF(INDEX(SAU_Status,MATCH("Base|"&$B81,SAU_Key,0))="B","Incluída","n.d.")) -> 135063.55 | G81: =IF(INDEX(SAU_Status,MATCH("Base|"&$B81,SAU_Key,0))="O",INDEX(SAU_PP,MATCH("Base|"&$B81,SAU_Key,0))*INDEX(RelUni,MATCH($B81,Cov_Cod,0),4)*(1+sig_SAU)/(1-load_SAU)*(1+tax_SAU),IF(INDEX(SAU_Status,MATCH("Base|"&$B81,SAU_Key,0))="B","Incluída","n.d.")) -> 185962.3 | H81: =IF(INDEX(SAU_Status,MATCH("Base|"&$B81,SAU_Key,0))="O",INDEX(SAU_PP,MATCH("Base|"&$B81,SAU_Key,0))*INDEX(RelUni,MATCH($B81,Cov_Cod,0),5)*(1+sig_SAU)/(1-load_SAU)*(1+tax_SAU),IF(INDEX(SAU_Status,MATCH("Base|"&$B81,SAU_Key,0))="B","Incluída","n.d.")) -> 234139.07 | I81: =IF(INDEX(SAU_Status,MATCH("Conforto|"&$B81,SAU_Key,0))="O",INDEX(SAU_PP,MATCH("Conforto|"&$B81,SAU_Key,0))*INDEX(RelUni,MATCH($B81,Cov_Cod,0),1)*(1+sig_SAU)/(1-load_SAU)*(1+tax_SAU),IF(INDEX(SAU_Status,MATCH("Conforto|"&$B81,SAU_Key,0))="B","Incluída","n.d.")) -> Incluída | J81: =IF(INDEX(SAU_Status,MATCH("Conforto|"&$B81,SAU_Key,0))="O",INDEX(SAU_PP,MATCH("Conforto|"&$B81,SAU_Key,0))*INDEX(RelUni,MATCH($B81,Cov_Cod,0),2)*(1+sig_SAU)/(1-load_SAU)*(1+tax_SAU),IF(INDEX(SAU_Status,MATCH("Conforto|"&$B81,SAU_Key,0))="B","Incluída","n.d.")) -> Incluída | K81: =IF(INDEX(SAU_Status,MATCH("Conforto|"&$B81,SAU_Key,0))="O",INDEX(SAU_PP,MATCH("Conforto|"&$B81,SAU_Key,0))*INDEX(RelUni,MATCH($B81,Cov_Cod,0),3)*(1+sig_SAU)/(1-load_SAU)*(1+tax_SAU),IF(INDEX(SAU_Status,MATCH("Conforto|"&$B81,SAU_Key,0))="B","Incluída","n.d.")) -> Incluída | L81: =IF(INDEX(SAU_Status,MATCH("Conforto|"&$B81,SAU_Key,0))="O",INDEX(SAU_PP,MATCH("Conforto|"&$B81,SAU_Key,0))*INDEX(RelUni,MATCH($B81,Cov_Cod,0),4)*(1+sig_SAU)/(1-load_SAU)*(1+tax_SAU),IF(INDEX(SAU_Status,MATCH("Conforto|"&$B81,SAU_Key,0))="B","Incluída","n.d.")) -> Incluída | M81: =IF(INDEX(SAU_Status,MATCH("Conforto|"&$B81,SAU_Key,0))="O",INDEX(SAU_PP,MATCH("Conforto|"&$B81,SAU_Key,0))*INDEX(RelUni,MATCH($B81,Cov_Cod,0),5)*(1+sig_SAU)/(1-load_SAU)*(1+tax_SAU),IF(INDEX(SAU_Status,MATCH("Conforto|"&$B81,SAU_Key,0))="B","Incluída","n.d.")) -> Incluída | N81: =IF(INDEX(SAU_Status,MATCH("Premium|"&$B81,SAU_Key,0))="O",INDEX(SAU_PP,MATCH("Premium|"&$B81,SAU_Key,0))*INDEX(RelUni,MATCH($B81,Cov_Cod,0),1)*(1+sig_SAU)/(1-load_SAU)*(1+tax_SAU),IF(INDEX(SAU_Status,MATCH("Premium|"&$B81,SAU_Key,0))="B","Incluída","n.d.")) -> Incluída | O81: =IF(INDEX(SAU_Status,MATCH("Premium|"&$B81,SAU_Key,0))="O",INDEX(SAU_PP,MATCH("Premium|"&$B81,SAU_Key,0))*INDEX(RelUni,MATCH($B81,Cov_Cod,0),2)*(1+sig_SAU)/(1-load_SAU)*(1+tax_SAU),IF(INDEX(SAU_Status,MATCH("Premium|"&$B81,SAU_Key,0))="B","Incluída","n.d.")) -> Incluída | P81: =IF(INDEX(SAU_Status,MATCH("Premium|"&$B81,SAU_Key,0))="O",INDEX(SAU_PP,MATCH("Premium|"&$B81,SAU_Key,0))*INDEX(RelUni,MATCH($B81,Cov_Cod,0),3)*(1+sig_SAU)/(1-load_SAU)*(1+tax_SAU),IF(INDEX(SAU_Status,MATCH("Premium|"&$B81,SAU_Key,0))="B","Incluída","n.d.")) -> Incluída | Q81: =IF(INDEX(SAU_Status,MATCH("Premium|"&$B81,SAU_Key,0))="O",INDEX(SAU_PP,MATCH("Premium|"&$B81,SAU_Key,0))*INDEX(RelUni,MATCH($B81,Cov_Cod,0),4)*(1+sig_SAU)/(1-load_SAU)*(1+tax_SAU),IF(INDEX(SAU_Status,MATCH("Premium|"&$B81,SAU_Key,0))="B","Incluída","n.d.")) -> Incluída | R81: =IF(INDEX(SAU_Status,MATCH("Premium|"&$B81,SAU_Key,0))="O",INDEX(SAU_PP,MATCH("Premium|"&$B81,SAU_Key,0))*INDEX(RelUni,MATCH($B81,Cov_Cod,0),5)*(1+sig_SAU)/(1-load_SAU)*(1+tax_SAU),IF(INDEX(SAU_Status,MATCH("Premium|"&$B81,SAU_Key,0))="B","Incluída","n.d.")) -> Incluída
B82: MAL | C82: =INDEX(Cov_Nome,MATCH(B82,Cov_Cod,0)) -> Malária e Doenças Endémicas (ambulatório) | D82: =IF(INDEX(SAU_Status,MATCH("Base|"&$B82,SAU_Key,0))="O",INDEX(SAU_PP,MATCH("Base|"&$B82,SAU_Key,0))*INDEX(RelUni,MATCH($B82,Cov_Cod,0),1)*(1+sig_SAU)/(1-load_SAU)*(1+tax_SAU),IF(INDEX(SAU_Status,MATCH("Base|"&$B82,SAU_Key,0))="B","Incluída","n.d.")) -> 27012.127 | E82: =IF(INDEX(SAU_Status,MATCH("Base|"&$B82,SAU_Key,0))="O",INDEX(SAU_PP,MATCH("Base|"&$B82,SAU_Key,0))*INDEX(RelUni,MATCH($B82,Cov_Cod,0),2)*(1+sig_SAU)/(1-load_SAU)*(1+tax_SAU),IF(INDEX(SAU_Status,MATCH("Base|"&$B82,SAU_Key,0))="B","Incluída","n.d.")) -> 17555.409 | F82: =IF(INDEX(SAU_Status,MATCH("Base|"&$B82,SAU_Key,0))="O",INDEX(SAU_PP,MATCH("Base|"&$B82,SAU_Key,0))*INDEX(RelUni,MATCH($B82,Cov_Cod,0),3)*(1+sig_SAU)/(1-load_SAU)*(1+tax_SAU),IF(INDEX(SAU_Status,MATCH("Base|"&$B82,SAU_Key,0))="B","Incluída","n.d.")) -> 16674.715 | G82: =IF(INDEX(SAU_Status,MATCH("Base|"&$B82,SAU_Key,0))="O",INDEX(SAU_PP,MATCH("Base|"&$B82,SAU_Key,0))*INDEX(RelUni,MATCH($B82,Cov_Cod,0),4)*(1+sig_SAU)/(1-load_SAU)*(1+tax_SAU),IF(INDEX(SAU_Status,MATCH("Base|"&$B82,SAU_Key,0))="B","Incluída","n.d.")) -> 18003.549 | H82: =IF(INDEX(SAU_Status,MATCH("Base|"&$B82,SAU_Key,0))="O",INDEX(SAU_PP,MATCH("Base|"&$B82,SAU_Key,0))*INDEX(RelUni,MATCH($B82,Cov_Cod,0),5)*(1+sig_SAU)/(1-load_SAU)*(1+tax_SAU),IF(INDEX(SAU_Status,MATCH("Base|"&$B82,SAU_Key,0))="B","Incluída","n.d.")) -> 20575.484 | I82: =IF(INDEX(SAU_Status,MATCH("Conforto|"&$B82,SAU_Key,0))="O",INDEX(SAU_PP,MATCH("Conforto|"&$B82,SAU_Key,0))*INDEX(RelUni,MATCH($B82,Cov_Cod,0),1)*(1+sig_SAU)/(1-load_SAU)*(1+tax_SAU),IF(INDEX(SAU_Status,MATCH("Conforto|"&$B82,SAU_Key,0))="B","Incluída","n.d.")) -> Incluída | J82: =IF(INDEX(SAU_Status,MATCH("Conforto|"&$B82,SAU_Key,0))="O",INDEX(SAU_PP,MATCH("Conforto|"&$B82,SAU_Key,0))*INDEX(RelUni,MATCH($B82,Cov_Cod,0),2)*(1+sig_SAU)/(1-load_SAU)*(1+tax_SAU),IF(INDEX(SAU_Status,MATCH("Conforto|"&$B82,SAU_Key,0))="B","Incluída","n.d.")) -> Incluída | K82: =IF(INDEX(SAU_Status,MATCH("Conforto|"&$B82,SAU_Key,0))="O",INDEX(SAU_PP,MATCH("Conforto|"&$B82,SAU_Key,0))*INDEX(RelUni,MATCH($B82,Cov_Cod,0),3)*(1+sig_SAU)/(1-load_SAU)*(1+tax_SAU),IF(INDEX(SAU_Status,MATCH("Conforto|"&$B82,SAU_Key,0))="B","Incluída","n.d.")) -> Incluída | L82: =IF(INDEX(SAU_Status,MATCH("Conforto|"&$B82,SAU_Key,0))="O",INDEX(SAU_PP,MATCH("Conforto|"&$B82,SAU_Key,0))*INDEX(RelUni,MATCH($B82,Cov_Cod,0),4)*(1+sig_SAU)/(1-load_SAU)*(1+tax_SAU),IF(INDEX(SAU_Status,MATCH("Conforto|"&$B82,SAU_Key,0))="B","Incluída","n.d.")) -> Incluída | M82: =IF(INDEX(SAU_Status,MATCH("Conforto|"&$B82,SAU_Key,0))="O",INDEX(SAU_PP,MATCH("Conforto|"&$B82,SAU_Key,0))*INDEX(RelUni,MATCH($B82,Cov_Cod,0),5)*(1+sig_SAU)/(1-load_SAU)*(1+tax_SAU),IF(INDEX(SAU_Status,MATCH("Conforto|"&$B82,SAU_Key,0))="B","Incluída","n.d.")) -> Incluída | N82: =IF(INDEX(SAU_Status,MATCH("Premium|"&$B82,SAU_Key,0))="O",INDEX(SAU_PP,MATCH("Premium|"&$B82,SAU_Key,0))*INDEX(RelUni,MATCH($B82,Cov_Cod,0),1)*(1+sig_SAU)/(1-load_SAU)*(1+tax_SAU),IF(INDEX(SAU_Status,MATCH("Premium|"&$B82,SAU_Key,0))="B","Incluída","n.d.")) -> Incluída | O82: =IF(INDEX(SAU_Status,MATCH("Premium|"&$B82,SAU_Key,0))="O",INDEX(SAU_PP,MATCH("Premium|"&$B82,SAU_Key,0))*INDEX(RelUni,MATCH($B82,Cov_Cod,0),2)*(1+sig_SAU)/(1-load_SAU)*(1+tax_SAU),IF(INDEX(SAU_Status,MATCH("Premium|"&$B82,SAU_Key,0))="B","Incluída","n.d.")) -> Incluída | P82: =IF(INDEX(SAU_Status,MATCH("Premium|"&$B82,SAU_Key,0))="O",INDEX(SAU_PP,MATCH("Premium|"&$B82,SAU_Key,0))*INDEX(RelUni,MATCH($B82,Cov_Cod,0),3)*(1+sig_SAU)/(1-load_SAU)*(1+tax_SAU),IF(INDEX(SAU_Status,MATCH("Premium|"&$B82,SAU_Key,0))="B","Incluída","n.d.")) -> Incluída | Q82: =IF(INDEX(SAU_Status,MATCH("Premium|"&$B82,SAU_Key,0))="O",INDEX(SAU_PP,MATCH("Premium|"&$B82,SAU_Key,0))*INDEX(RelUni,MATCH($B82,Cov_Cod,0),4)*(1+sig_SAU)/(1-load_SAU)*(1+tax_SAU),IF(INDEX(SAU_Status,MATCH("Premium|"&$B82,SAU_Key,0))="B","Incluída","n.d.")) -> Incluída | R82: =IF(INDEX(SAU_Status,MATCH("Premium|"&$B82,SAU_Key,0))="O",INDEX(SAU_PP,MATCH("Premium|"&$B82,SAU_Key,0))*INDEX(RelUni,MATCH($B82,Cov_Cod,0),5)*(1+sig_SAU)/(1-load_SAU)*(1+tax_SAU),IF(INDEX(SAU_Status,MATCH("Premium|"&$B82,SAU_Key,0))="B","Incluída","n.d.")) -> Incluída
B83: MAT | C83: =INDEX(Cov_Nome,MATCH(B83,Cov_Cod,0)) -> Maternidade e Parto (Normal e Cesariana) | D83: =IF(INDEX(SAU_Status,MATCH("Base|"&$B83,SAU_Key,0))="O",INDEX(SAU_PP,MATCH("Base|"&$B83,SAU_Key,0))*INDEX(RelUni,MATCH($B83,Cov_Cod,0),1)*(1+sig_SAU)/(1-load_SAU)*(1+tax_SAU),IF(INDEX(SAU_Status,MATCH("Base|"&$B83,SAU_Key,0))="B","Incluída","n.d.")) -> n.d. | E83: =IF(INDEX(SAU_Status,MATCH("Base|"&$B83,SAU_Key,0))="O",INDEX(SAU_PP,MATCH("Base|"&$B83,SAU_Key,0))*INDEX(RelUni,MATCH($B83,Cov_Cod,0),2)*(1+sig_SAU)/(1-load_SAU)*(1+tax_SAU),IF(INDEX(SAU_Status,MATCH("Base|"&$B83,SAU_Key,0))="B","Incluída","n.d.")) -> n.d. | F83: =IF(INDEX(SAU_Status,MATCH("Base|"&$B83,SAU_Key,0))="O",INDEX(SAU_PP,MATCH("Base|"&$B83,SAU_Key,0))*INDEX(RelUni,MATCH($B83,Cov_Cod,0),3)*(1+sig_SAU)/(1-load_SAU)*(1+tax_SAU),IF(INDEX(SAU_Status,MATCH("Base|"&$B83,SAU_Key,0))="B","Incluída","n.d.")) -> n.d. | G83: =IF(INDEX(SAU_Status,MATCH("Base|"&$B83,SAU_Key,0))="O",INDEX(SAU_PP,MATCH("Base|"&$B83,SAU_Key,0))*INDEX(RelUni,MATCH($B83,Cov_Cod,0),4)*(1+sig_SAU)/(1-load_SAU)*(1+tax_SAU),IF(INDEX(SAU_Status,MATCH("Base|"&$B83,SAU_Key,0))="B","Incluída","n.d.")) -> n.d. | H83: =IF(INDEX(SAU_Status,MATCH("Base|"&$B83,SAU_Key,0))="O",INDEX(SAU_PP,MATCH("Base|"&$B83,SAU_Key,0))*INDEX(RelUni,MATCH($B83,Cov_Cod,0),5)*(1+sig_SAU)/(1-load_SAU)*(1+tax_SAU),IF(INDEX(SAU_Status,MATCH("Base|"&$B83,SAU_Key,0))="B","Incluída","n.d.")) -> n.d. | I83: =IF(INDEX(SAU_Status,MATCH("Conforto|"&$B83,SAU_Key,0))="O",INDEX(SAU_PP,MATCH("Conforto|"&$B83,SAU_Key,0))*INDEX(RelUni,MATCH($B83,Cov_Cod,0),1)*(1+sig_SAU)/(1-load_SAU)*(1+tax_SAU),IF(INDEX(SAU_Status,MATCH("Conforto|"&$B83,SAU_Key,0))="B","Incluída","n.d.")) -> 2342.5203 | J83: =IF(INDEX(SAU_Status,MATCH("Conforto|"&$B83,SAU_Key,0))="O",INDEX(SAU_PP,MATCH("Conforto|"&$B83,SAU_Key,0))*INDEX(RelUni,MATCH($B83,Cov_Cod,0),2)*(1+sig_SAU)/(1-load_SAU)*(1+tax_SAU),IF(INDEX(SAU_Status,MATCH("Conforto|"&$B83,SAU_Key,0))="B","Incluída","n.d.")) -> 45442.146 | K83: =IF(INDEX(SAU_Status,MATCH("Conforto|"&$B83,SAU_Key,0))="O",INDEX(SAU_PP,MATCH("Conforto|"&$B83,SAU_Key,0))*INDEX(RelUni,MATCH($B83,Cov_Cod,0),3)*(1+sig_SAU)/(1-load_SAU)*(1+tax_SAU),IF(INDEX(SAU_Status,MATCH("Conforto|"&$B83,SAU_Key,0))="B","Incluída","n.d.")) -> 14995.908 | L83: =IF(INDEX(SAU_Status,MATCH("Conforto|"&$B83,SAU_Key,0))="O",INDEX(SAU_PP,MATCH("Conforto|"&$B83,SAU_Key,0))*INDEX(RelUni,MATCH($B83,Cov_Cod,0),4)*(1+sig_SAU)/(1-load_SAU)*(1+tax_SAU),IF(INDEX(SAU_Status,MATCH("Conforto|"&$B83,SAU_Key,0))="B","Incluída","n.d.")) -> 0 | M83: =IF(INDEX(SAU_Status,MATCH("Conforto|"&$B83,SAU_Key,0))="O",INDEX(SAU_PP,MATCH("Conforto|"&$B83,SAU_Key,0))*INDEX(RelUni,MATCH($B83,Cov_Cod,0),5)*(1+sig_SAU)/(1-load_SAU)*(1+tax_SAU),IF(INDEX(SAU_Status,MATCH("Conforto|"&$B83,SAU_Key,0))="B","Incluída","n.d.")) -> 0 | N83: =IF(INDEX(SAU_Status,MATCH("Premium|"&$B83,SAU_Key,0))="O",INDEX(SAU_PP,MATCH("Premium|"&$B83,SAU_Key,0))*INDEX(RelUni,MATCH($B83,Cov_Cod,0),1)*(1+sig_SAU)/(1-load_SAU)*(1+tax_SAU),IF(INDEX(SAU_Status,MATCH("Premium|"&$B83,SAU_Key,0))="B","Incluída","n.d.")) -> Incluída | O83: =IF(INDEX(SAU_Status,MATCH("Premium|"&$B83,SAU_Key,0))="O",INDEX(SAU_PP,MATCH("Premium|"&$B83,SAU_Key,0))*INDEX(RelUni,MATCH($B83,Cov_Cod,0),2)*(1+sig_SAU)/(1-load_SAU)*(1+tax_SAU),IF(INDEX(SAU_Status,MATCH("Premium|"&$B83,SAU_Key,0))="B","Incluída","n.d.")) -> Incluída | P83: =IF(INDEX(SAU_Status,MATCH("Premium|"&$B83,SAU_Key,0))="O",INDEX(SAU_PP,MATCH("Premium|"&$B83,SAU_Key,0))*INDEX(RelUni,MATCH($B83,Cov_Cod,0),3)*(1+sig_SAU)/(1-load_SAU)*(1+tax_SAU),IF(INDEX(SAU_Status,MATCH("Premium|"&$B83,SAU_Key,0))="B","Incluída","n.d.")) -> Incluída | Q83: =IF(INDEX(SAU_Status,MATCH("Premium|"&$B83,SAU_Key,0))="O",INDEX(SAU_PP,MATCH("Premium|"&$B83,SAU_Key,0))*INDEX(RelUni,MATCH($B83,Cov_Cod,0),4)*(1+sig_SAU)/(1-load_SAU)*(1+tax_SAU),IF(INDEX(SAU_Status,MATCH("Premium|"&$B83,SAU_Key,0))="B","Incluída","n.d.")) -> Incluída | R83: =IF(INDEX(SAU_Status,MATCH("Premium|"&$B83,SAU_Key,0))="O",INDEX(SAU_PP,MATCH("Premium|"&$B83,SAU_Key,0))*INDEX(RelUni,MATCH($B83,Cov_Cod,0),5)*(1+sig_SAU)/(1-load_SAU)*(1+tax_SAU),IF(INDEX(SAU_Status,MATCH("Premium|"&$B83,SAU_Key,0))="B","Incluída","n.d.")) -> Incluída
B84: URG | C84: =INDEX(Cov_Nome,MATCH(B84,Cov_Cod,0)) -> Urgência Hospitalar | D84: =IF(INDEX(SAU_Status,MATCH("Base|"&$B84,SAU_Key,0))="O",INDEX(SAU_PP,MATCH("Base|"&$B84,SAU_Key,0))*INDEX(RelUni,MATCH($B84,Cov_Cod,0),1)*(1+sig_SAU)/(1-load_SAU)*(1+tax_SAU),IF(INDEX(SAU_Status,MATCH("Base|"&$B84,SAU_Key,0))="B","Incluída","n.d.")) -> Incluída | E84: =IF(INDEX(SAU_Status,MATCH("Base|"&$B84,SAU_Key,0))="O",INDEX(SAU_PP,MATCH("Base|"&$B84,SAU_Key,0))*INDEX(RelUni,MATCH($B84,Cov_Cod,0),2)*(1+sig_SAU)/(1-load_SAU)*(1+tax_SAU),IF(INDEX(SAU_Status,MATCH("Base|"&$B84,SAU_Key,0))="B","Incluída","n.d.")) -> Incluída | F84: =IF(INDEX(SAU_Status,MATCH("Base|"&$B84,SAU_Key,0))="O",INDEX(SAU_PP,MATCH("Base|"&$B84,SAU_Key,0))*INDEX(RelUni,MATCH($B84,Cov_Cod,0),3)*(1+sig_SAU)/(1-load_SAU)*(1+tax_SAU),IF(INDEX(SAU_Status,MATCH("Base|"&$B84,SAU_Key,0))="B","Incluída","n.d.")) -> Incluída | G84: =IF(INDEX(SAU_Status,MATCH("Base|"&$B84,SAU_Key,0))="O",INDEX(SAU_PP,MATCH("Base|"&$B84,SAU_Key,0))*INDEX(RelUni,MATCH($B84,Cov_Cod,0),4)*(1+sig_SAU)/(1-load_SAU)*(1+tax_SAU),IF(INDEX(SAU_Status,MATCH("Base|"&$B84,SAU_Key,0))="B","Incluída","n.d.")) -> Incluída | H84: =IF(INDEX(SAU_Status,MATCH("Base|"&$B84,SAU_Key,0))="O",INDEX(SAU_PP,MATCH("Base|"&$B84,SAU_Key,0))*INDEX(RelUni,MATCH($B84,Cov_Cod,0),5)*(1+sig_SAU)/(1-load_SAU)*(1+tax_SAU),IF(INDEX(SAU_Status,MATCH("Base|"&$B84,SAU_Key,0))="B","Incluída","n.d.")) -> Incluída | I84: =IF(INDEX(SAU_Status,MATCH("Conforto|"&$B84,SAU_Key,0))="O",INDEX(SAU_PP,MATCH("Conforto|"&$B84,SAU_Key,0))*INDEX(RelUni,MATCH($B84,Cov_Cod,0),1)*(1+sig_SAU)/(1-load_SAU)*(1+tax_SAU),IF(INDEX(SAU_Status,MATCH("Conforto|"&$B84,SAU_Key,0))="B","Incluída","n.d.")) -> Incluída | J84: =IF(INDEX(SAU_Status,MATCH("Conforto|"&$B84,SAU_Key,0))="O",INDEX(SAU_PP,MATCH("Conforto|"&$B84,SAU_Key,0))*INDEX(RelUni,MATCH($B84,Cov_Cod,0),2)*(1+sig_SAU)/(1-load_SAU)*(1+tax_SAU),IF(INDEX(SAU_Status,MATCH("Conforto|"&$B84,SAU_Key,0))="B","Incluída","n.d.")) -> Incluída | K84: =IF(INDEX(SAU_Status,MATCH("Conforto|"&$B84,SAU_Key,0))="O",INDEX(SAU_PP,MATCH("Conforto|"&$B84,SAU_Key,0))*INDEX(RelUni,MATCH($B84,Cov_Cod,0),3)*(1+sig_SAU)/(1-load_SAU)*(1+tax_SAU),IF(INDEX(SAU_Status,MATCH("Conforto|"&$B84,SAU_Key,0))="B","Incluída","n.d.")) -> Incluída | L84: =IF(INDEX(SAU_Status,MATCH("Conforto|"&$B84,SAU_Key,0))="O",INDEX(SAU_PP,MATCH("Conforto|"&$B84,SAU_Key,0))*INDEX(RelUni,MATCH($B84,Cov_Cod,0),4)*(1+sig_SAU)/(1-load_SAU)*(1+tax_SAU),IF(INDEX(SAU_Status,MATCH("Conforto|"&$B84,SAU_Key,0))="B","Incluída","n.d.")) -> Incluída | M84: =IF(INDEX(SAU_Status,MATCH("Conforto|"&$B84,SAU_Key,0))="O",INDEX(SAU_PP,MATCH("Conforto|"&$B84,SAU_Key,0))*INDEX(RelUni,MATCH($B84,Cov_Cod,0),5)*(1+sig_SAU)/(1-load_SAU)*(1+tax_SAU),IF(INDEX(SAU_Status,MATCH("Conforto|"&$B84,SAU_Key,0))="B","Incluída","n.d.")) -> Incluída | N84: =IF(INDEX(SAU_Status,MATCH("Premium|"&$B84,SAU_Key,0))="O",INDEX(SAU_PP,MATCH("Premium|"&$B84,SAU_Key,0))*INDEX(RelUni,MATCH($B84,Cov_Cod,0),1)*(1+sig_SAU)/(1-load_SAU)*(1+tax_SAU),IF(INDEX(SAU_Status,MATCH("Premium|"&$B84,SAU_Key,0))="B","Incluída","n.d.")) -> Incluída | O84: =IF(INDEX(SAU_Status,MATCH("Premium|"&$B84,SAU_Key,0))="O",INDEX(SAU_PP,MATCH("Premium|"&$B84,SAU_Key,0))*INDEX(RelUni,MATCH($B84,Cov_Cod,0),2)*(1+sig_SAU)/(1-load_SAU)*(1+tax_SAU),IF(INDEX(SAU_Status,MATCH("Premium|"&$B84,SAU_Key,0))="B","Incluída","n.d.")) -> Incluída | P84: =IF(INDEX(SAU_Status,MATCH("Premium|"&$B84,SAU_Key,0))="O",INDEX(SAU_PP,MATCH("Premium|"&$B84,SAU_Key,0))*INDEX(RelUni,MATCH($B84,Cov_Cod,0),3)*(1+sig_SAU)/(1-load_SAU)*(1+tax_SAU),IF(INDEX(SAU_Status,MATCH("Premium|"&$B84,SAU_Key,0))="B","Incluída","n.d.")) -> Incluída | Q84: =IF(INDEX(SAU_Status,MATCH("Premium|"&$B84,SAU_Key,0))="O",INDEX(SAU_PP,MATCH("Premium|"&$B84,SAU_Key,0))*INDEX(RelUni,MATCH($B84,Cov_Cod,0),4)*(1+sig_SAU)/(1-load_SAU)*(1+tax_SAU),IF(INDEX(SAU_Status,MATCH("Premium|"&$B84,SAU_Key,0))="B","Incluída","n.d.")) -> Incluída | R84: =IF(INDEX(SAU_Status,MATCH("Premium|"&$B84,SAU_Key,0))="O",INDEX(SAU_PP,MATCH("Premium|"&$B84,SAU_Key,0))*INDEX(RelUni,MATCH($B84,Cov_Cod,0),5)*(1+sig_SAU)/(1-load_SAU)*(1+tax_SAU),IF(INDEX(SAU_Status,MATCH("Premium|"&$B84,SAU_Key,0))="B","Incluída","n.d.")) -> Incluída
B85: AMBUL | C85: =INDEX(Cov_Nome,MATCH(B85,Cov_Cod,0)) -> Transporte em Ambulância / Emergência Médica | D85: =IF(INDEX(SAU_Status,MATCH("Base|"&$B85,SAU_Key,0))="O",INDEX(SAU_PP,MATCH("Base|"&$B85,SAU_Key,0))*INDEX(RelUni,MATCH($B85,Cov_Cod,0),1)*(1+sig_SAU)/(1-load_SAU)*(1+tax_SAU),IF(INDEX(SAU_Status,MATCH("Base|"&$B85,SAU_Key,0))="B","Incluída","n.d.")) -> Incluída | E85: =IF(INDEX(SAU_Status,MATCH("Base|"&$B85,SAU_Key,0))="O",INDEX(SAU_PP,MATCH("Base|"&$B85,SAU_Key,0))*INDEX(RelUni,MATCH($B85,Cov_Cod,0),2)*(1+sig_SAU)/(1-load_SAU)*(1+tax_SAU),IF(INDEX(SAU_Status,MATCH("Base|"&$B85,SAU_Key,0))="B","Incluída","n.d.")) -> Incluída | F85: =IF(INDEX(SAU_Status,MATCH("Base|"&$B85,SAU_Key,0))="O",INDEX(SAU_PP,MATCH("Base|"&$B85,SAU_Key,0))*INDEX(RelUni,MATCH($B85,Cov_Cod,0),3)*(1+sig_SAU)/(1-load_SAU)*(1+tax_SAU),IF(INDEX(SAU_Status,MATCH("Base|"&$B85,SAU_Key,0))="B","Incluída","n.d.")) -> Incluída | G85: =IF(INDEX(SAU_Status,MATCH("Base|"&$B85,SAU_Key,0))="O",INDEX(SAU_PP,MATCH("Base|"&$B85,SAU_Key,0))*INDEX(RelUni,MATCH($B85,Cov_Cod,0),4)*(1+sig_SAU)/(1-load_SAU)*(1+tax_SAU),IF(INDEX(SAU_Status,MATCH("Base|"&$B85,SAU_Key,0))="B","Incluída","n.d.")) -> Incluída | H85: =IF(INDEX(SAU_Status,MATCH("Base|"&$B85,SAU_Key,0))="O",INDEX(SAU_PP,MATCH("Base|"&$B85,SAU_Key,0))*INDEX(RelUni,MATCH($B85,Cov_Cod,0),5)*(1+sig_SAU)/(1-load_SAU)*(1+tax_SAU),IF(INDEX(SAU_Status,MATCH("Base|"&$B85,SAU_Key,0))="B","Incluída","n.d.")) -> Incluída | I85: =IF(INDEX(SAU_Status,MATCH("Conforto|"&$B85,SAU_Key,0))="O",INDEX(SAU_PP,MATCH("Conforto|"&$B85,SAU_Key,0))*INDEX(RelUni,MATCH($B85,Cov_Cod,0),1)*(1+sig_SAU)/(1-load_SAU)*(1+tax_SAU),IF(INDEX(SAU_Status,MATCH("Conforto|"&$B85,SAU_Key,0))="B","Incluída","n.d.")) -> Incluída | J85: =IF(INDEX(SAU_Status,MATCH("Conforto|"&$B85,SAU_Key,0))="O",INDEX(SAU_PP,MATCH("Conforto|"&$B85,SAU_Key,0))*INDEX(RelUni,MATCH($B85,Cov_Cod,0),2)*(1+sig_SAU)/(1-load_SAU)*(1+tax_SAU),IF(INDEX(SAU_Status,MATCH("Conforto|"&$B85,SAU_Key,0))="B","Incluída","n.d.")) -> Incluída | K85: =IF(INDEX(SAU_Status,MATCH("Conforto|"&$B85,SAU_Key,0))="O",INDEX(SAU_PP,MATCH("Conforto|"&$B85,SAU_Key,0))*INDEX(RelUni,MATCH($B85,Cov_Cod,0),3)*(1+sig_SAU)/(1-load_SAU)*(1+tax_SAU),IF(INDEX(SAU_Status,MATCH("Conforto|"&$B85,SAU_Key,0))="B","Incluída","n.d.")) -> Incluída | L85: =IF(INDEX(SAU_Status,MATCH("Conforto|"&$B85,SAU_Key,0))="O",INDEX(SAU_PP,MATCH("Conforto|"&$B85,SAU_Key,0))*INDEX(RelUni,MATCH($B85,Cov_Cod,0),4)*(1+sig_SAU)/(1-load_SAU)*(1+tax_SAU),IF(INDEX(SAU_Status,MATCH("Conforto|"&$B85,SAU_Key,0))="B","Incluída","n.d.")) -> Incluída | M85: =IF(INDEX(SAU_Status,MATCH("Conforto|"&$B85,SAU_Key,0))="O",INDEX(SAU_PP,MATCH("Conforto|"&$B85,SAU_Key,0))*INDEX(RelUni,MATCH($B85,Cov_Cod,0),5)*(1+sig_SAU)/(1-load_SAU)*(1+tax_SAU),IF(INDEX(SAU_Status,MATCH("Conforto|"&$B85,SAU_Key,0))="B","Incluída","n.d.")) -> Incluída | N85: =IF(INDEX(SAU_Status,MATCH("Premium|"&$B85,SAU_Key,0))="O",INDEX(SAU_PP,MATCH("Premium|"&$B85,SAU_Key,0))*INDEX(RelUni,MATCH($B85,Cov_Cod,0),1)*(1+sig_SAU)/(1-load_SAU)*(1+tax_SAU),IF(INDEX(SAU_Status,MATCH("Premium|"&$B85,SAU_Key,0))="B","Incluída","n.d.")) -> Incluída | O85: =IF(INDEX(SAU_Status,MATCH("Premium|"&$B85,SAU_Key,0))="O",INDEX(SAU_PP,MATCH("Premium|"&$B85,SAU_Key,0))*INDEX(RelUni,MATCH($B85,Cov_Cod,0),2)*(1+sig_SAU)/(1-load_SAU)*(1+tax_SAU),IF(INDEX(SAU_Status,MATCH("Premium|"&$B85,SAU_Key,0))="B","Incluída","n.d.")) -> Incluída | P85: =IF(INDEX(SAU_Status,MATCH("Premium|"&$B85,SAU_Key,0))="O",INDEX(SAU_PP,MATCH("Premium|"&$B85,SAU_Key,0))*INDEX(RelUni,MATCH($B85,Cov_Cod,0),3)*(1+sig_SAU)/(1-load_SAU)*(1+tax_SAU),IF(INDEX(SAU_Status,MATCH("Premium|"&$B85,SAU_Key,0))="B","Incluída","n.d.")) -> Incluída | Q85: =IF(INDEX(SAU_Status,MATCH("Premium|"&$B85,SAU_Key,0))="O",INDEX(SAU_PP,MATCH("Premium|"&$B85,SAU_Key,0))*INDEX(RelUni,MATCH($B85,Cov_Cod,0),4)*(1+sig_SAU)/(1-load_SAU)*(1+tax_SAU),IF(INDEX(SAU_Status,MATCH("Premium|"&$B85,SAU_Key,0))="B","Incluída","n.d.")) -> Incluída | R85: =IF(INDEX(SAU_Status,MATCH("Premium|"&$B85,SAU_Key,0))="O",INDEX(SAU_PP,MATCH("Premium|"&$B85,SAU_Key,0))*INDEX(RelUni,MATCH($B85,Cov_Cod,0),5)*(1+sig_SAU)/(1-load_SAU)*(1+tax_SAU),IF(INDEX(SAU_Status,MATCH("Premium|"&$B85,SAU_Key,0))="B","Incluída","n.d.")) -> Incluída
B86: MED | C86: =INDEX(Cov_Nome,MATCH(B86,Cov_Cod,0)) -> Medicamentos em Ambulatório (Farmácia) | D86: =IF(INDEX(SAU_Status,MATCH("Base|"&$B86,SAU_Key,0))="O",INDEX(SAU_PP,MATCH("Base|"&$B86,SAU_Key,0))*INDEX(RelUni,MATCH($B86,Cov_Cod,0),1)*(1+sig_SAU)/(1-load_SAU)*(1+tax_SAU),IF(INDEX(SAU_Status,MATCH("Base|"&$B86,SAU_Key,0))="B","Incluída","n.d.")) -> n.d. | E86: =IF(INDEX(SAU_Status,MATCH("Base|"&$B86,SAU_Key,0))="O",INDEX(SAU_PP,MATCH("Base|"&$B86,SAU_Key,0))*INDEX(RelUni,MATCH($B86,Cov_Cod,0),2)*(1+sig_SAU)/(1-load_SAU)*(1+tax_SAU),IF(INDEX(SAU_Status,MATCH("Base|"&$B86,SAU_Key,0))="B","Incluída","n.d.")) -> n.d. | F86: =IF(INDEX(SAU_Status,MATCH("Base|"&$B86,SAU_Key,0))="O",INDEX(SAU_PP,MATCH("Base|"&$B86,SAU_Key,0))*INDEX(RelUni,MATCH($B86,Cov_Cod,0),3)*(1+sig_SAU)/(1-load_SAU)*(1+tax_SAU),IF(INDEX(SAU_Status,MATCH("Base|"&$B86,SAU_Key,0))="B","Incluída","n.d.")) -> n.d. | G86: =IF(INDEX(SAU_Status,MATCH("Base|"&$B86,SAU_Key,0))="O",INDEX(SAU_PP,MATCH("Base|"&$B86,SAU_Key,0))*INDEX(RelUni,MATCH($B86,Cov_Cod,0),4)*(1+sig_SAU)/(1-load_SAU)*(1+tax_SAU),IF(INDEX(SAU_Status,MATCH("Base|"&$B86,SAU_Key,0))="B","Incluída","n.d.")) -> n.d. | H86: =IF(INDEX(SAU_Status,MATCH("Base|"&$B86,SAU_Key,0))="O",INDEX(SAU_PP,MATCH("Base|"&$B86,SAU_Key,0))*INDEX(RelUni,MATCH($B86,Cov_Cod,0),5)*(1+sig_SAU)/(1-load_SAU)*(1+tax_SAU),IF(INDEX(SAU_Status,MATCH("Base|"&$B86,SAU_Key,0))="B","Incluída","n.d.")) -> n.d. | I86: =IF(INDEX(SAU_Status,MATCH("Conforto|"&$B86,SAU_Key,0))="O",INDEX(SAU_PP,MATCH("Conforto|"&$B86,SAU_Key,0))*INDEX(RelUni,MATCH($B86,Cov_Cod,0),1)*(1+sig_SAU)/(1-load_SAU)*(1+tax_SAU),IF(INDEX(SAU_Status,MATCH("Conforto|"&$B86,SAU_Key,0))="B","Incluída","n.d.")) -> 68830.98 | J86: =IF(INDEX(SAU_Status,MATCH("Conforto|"&$B86,SAU_Key,0))="O",INDEX(SAU_PP,MATCH("Conforto|"&$B86,SAU_Key,0))*INDEX(RelUni,MATCH($B86,Cov_Cod,0),2)*(1+sig_SAU)/(1-load_SAU)*(1+tax_SAU),IF(INDEX(SAU_Status,MATCH("Conforto|"&$B86,SAU_Key,0))="B","Incluída","n.d.")) -> 126109.91 | K86: =IF(INDEX(SAU_Status,MATCH("Conforto|"&$B86,SAU_Key,0))="O",INDEX(SAU_PP,MATCH("Conforto|"&$B86,SAU_Key,0))*INDEX(RelUni,MATCH($B86,Cov_Cod,0),3)*(1+sig_SAU)/(1-load_SAU)*(1+tax_SAU),IF(INDEX(SAU_Status,MATCH("Conforto|"&$B86,SAU_Key,0))="B","Incluída","n.d.")) -> 178960.55 | L86: =IF(INDEX(SAU_Status,MATCH("Conforto|"&$B86,SAU_Key,0))="O",INDEX(SAU_PP,MATCH("Conforto|"&$B86,SAU_Key,0))*INDEX(RelUni,MATCH($B86,Cov_Cod,0),4)*(1+sig_SAU)/(1-load_SAU)*(1+tax_SAU),IF(INDEX(SAU_Status,MATCH("Conforto|"&$B86,SAU_Key,0))="B","Incluída","n.d.")) -> 280030.31 | M86: =IF(INDEX(SAU_Status,MATCH("Conforto|"&$B86,SAU_Key,0))="O",INDEX(SAU_PP,MATCH("Conforto|"&$B86,SAU_Key,0))*INDEX(RelUni,MATCH($B86,Cov_Cod,0),5)*(1+sig_SAU)/(1-load_SAU)*(1+tax_SAU),IF(INDEX(SAU_Status,MATCH("Conforto|"&$B86,SAU_Key,0))="B","Incluída","n.d.")) -> 360038.97 | N86: =IF(INDEX(SAU_Status,MATCH("Premium|"&$B86,SAU_Key,0))="O",INDEX(SAU_PP,MATCH("Premium|"&$B86,SAU_Key,0))*INDEX(RelUni,MATCH($B86,Cov_Cod,0),1)*(1+sig_SAU)/(1-load_SAU)*(1+tax_SAU),IF(INDEX(SAU_Status,MATCH("Premium|"&$B86,SAU_Key,0))="B","Incluída","n.d.")) -> Incluída | O86: =IF(INDEX(SAU_Status,MATCH("Premium|"&$B86,SAU_Key,0))="O",INDEX(SAU_PP,MATCH("Premium|"&$B86,SAU_Key,0))*INDEX(RelUni,MATCH($B86,Cov_Cod,0),2)*(1+sig_SAU)/(1-load_SAU)*(1+tax_SAU),IF(INDEX(SAU_Status,MATCH("Premium|"&$B86,SAU_Key,0))="B","Incluída","n.d.")) -> Incluída | P86: =IF(INDEX(SAU_Status,MATCH("Premium|"&$B86,SAU_Key,0))="O",INDEX(SAU_PP,MATCH("Premium|"&$B86,SAU_Key,0))*INDEX(RelUni,MATCH($B86,Cov_Cod,0),3)*(1+sig_SAU)/(1-load_SAU)*(1+tax_SAU),IF(INDEX(SAU_Status,MATCH("Premium|"&$B86,SAU_Key,0))="B","Incluída","n.d.")) -> Incluída | Q86: =IF(INDEX(SAU_Status,MATCH("Premium|"&$B86,SAU_Key,0))="O",INDEX(SAU_PP,MATCH("Premium|"&$B86,SAU_Key,0))*INDEX(RelUni,MATCH($B86,Cov_Cod,0),4)*(1+sig_SAU)/(1-load_SAU)*(1+tax_SAU),IF(INDEX(SAU_Status,MATCH("Premium|"&$B86,SAU_Key,0))="B","Incluída","n.d.")) -> Incluída | R86: =IF(INDEX(SAU_Status,MATCH("Premium|"&$B86,SAU_Key,0))="O",INDEX(SAU_PP,MATCH("Premium|"&$B86,SAU_Key,0))*INDEX(RelUni,MATCH($B86,Cov_Cod,0),5)*(1+sig_SAU)/(1-load_SAU)*(1+tax_SAU),IF(INDEX(SAU_Status,MATCH("Premium|"&$B86,SAU_Key,0))="B","Incluída","n.d.")) -> Incluída
B87: DENT | C87: =INDEX(Cov_Nome,MATCH(B87,Cov_Cod,0)) -> Estomatologia (tratamentos) | D87: =IF(INDEX(SAU_Status,MATCH("Base|"&$B87,SAU_Key,0))="O",INDEX(SAU_PP,MATCH("Base|"&$B87,SAU_Key,0))*INDEX(RelUni,MATCH($B87,Cov_Cod,0),1)*(1+sig_SAU)/(1-load_SAU)*(1+tax_SAU),IF(INDEX(SAU_Status,MATCH("Base|"&$B87,SAU_Key,0))="B","Incluída","n.d.")) -> n.d. | E87: =IF(INDEX(SAU_Status,MATCH("Base|"&$B87,SAU_Key,0))="O",INDEX(SAU_PP,MATCH("Base|"&$B87,SAU_Key,0))*INDEX(RelUni,MATCH($B87,Cov_Cod,0),2)*(1+sig_SAU)/(1-load_SAU)*(1+tax_SAU),IF(INDEX(SAU_Status,MATCH("Base|"&$B87,SAU_Key,0))="B","Incluída","n.d.")) -> n.d. | F87: =IF(INDEX(SAU_Status,MATCH("Base|"&$B87,SAU_Key,0))="O",INDEX(SAU_PP,MATCH("Base|"&$B87,SAU_Key,0))*INDEX(RelUni,MATCH($B87,Cov_Cod,0),3)*(1+sig_SAU)/(1-load_SAU)*(1+tax_SAU),IF(INDEX(SAU_Status,MATCH("Base|"&$B87,SAU_Key,0))="B","Incluída","n.d.")) -> n.d. | G87: =IF(INDEX(SAU_Status,MATCH("Base|"&$B87,SAU_Key,0))="O",INDEX(SAU_PP,MATCH("Base|"&$B87,SAU_Key,0))*INDEX(RelUni,MATCH($B87,Cov_Cod,0),4)*(1+sig_SAU)/(1-load_SAU)*(1+tax_SAU),IF(INDEX(SAU_Status,MATCH("Base|"&$B87,SAU_Key,0))="B","Incluída","n.d.")) -> n.d. | H87: =IF(INDEX(SAU_Status,MATCH("Base|"&$B87,SAU_Key,0))="O",INDEX(SAU_PP,MATCH("Base|"&$B87,SAU_Key,0))*INDEX(RelUni,MATCH($B87,Cov_Cod,0),5)*(1+sig_SAU)/(1-load_SAU)*(1+tax_SAU),IF(INDEX(SAU_Status,MATCH("Base|"&$B87,SAU_Key,0))="B","Incluída","n.d.")) -> n.d. | I87: =IF(INDEX(SAU_Status,MATCH("Conforto|"&$B87,SAU_Key,0))="O",INDEX(SAU_PP,MATCH("Conforto|"&$B87,SAU_Key,0))*INDEX(RelUni,MATCH($B87,Cov_Cod,0),1)*(1+sig_SAU)/(1-load_SAU)*(1+tax_SAU),IF(INDEX(SAU_Status,MATCH("Conforto|"&$B87,SAU_Key,0))="B","Incluída","n.d.")) -> 44598.282 | J87: =IF(INDEX(SAU_Status,MATCH("Conforto|"&$B87,SAU_Key,0))="O",INDEX(SAU_PP,MATCH("Conforto|"&$B87,SAU_Key,0))*INDEX(RelUni,MATCH($B87,Cov_Cod,0),2)*(1+sig_SAU)/(1-load_SAU)*(1+tax_SAU),IF(INDEX(SAU_Status,MATCH("Conforto|"&$B87,SAU_Key,0))="B","Incluída","n.d.")) -> 56224.839 | K87: =IF(INDEX(SAU_Status,MATCH("Conforto|"&$B87,SAU_Key,0))="O",INDEX(SAU_PP,MATCH("Conforto|"&$B87,SAU_Key,0))*INDEX(RelUni,MATCH($B87,Cov_Cod,0),3)*(1+sig_SAU)/(1-load_SAU)*(1+tax_SAU),IF(INDEX(SAU_Status,MATCH("Conforto|"&$B87,SAU_Key,0))="B","Incluída","n.d.")) -> 60076.509 | L87: =IF(INDEX(SAU_Status,MATCH("Conforto|"&$B87,SAU_Key,0))="O",INDEX(SAU_PP,MATCH("Conforto|"&$B87,SAU_Key,0))*INDEX(RelUni,MATCH($B87,Cov_Cod,0),4)*(1+sig_SAU)/(1-load_SAU)*(1+tax_SAU),IF(INDEX(SAU_Status,MATCH("Conforto|"&$B87,SAU_Key,0))="B","Incluída","n.d.")) -> 56257.963 | M87: =IF(INDEX(SAU_Status,MATCH("Conforto|"&$B87,SAU_Key,0))="O",INDEX(SAU_PP,MATCH("Conforto|"&$B87,SAU_Key,0))*INDEX(RelUni,MATCH($B87,Cov_Cod,0),5)*(1+sig_SAU)/(1-load_SAU)*(1+tax_SAU),IF(INDEX(SAU_Status,MATCH("Conforto|"&$B87,SAU_Key,0))="B","Incluída","n.d.")) -> 41974.853 | N87: =IF(INDEX(SAU_Status,MATCH("Premium|"&$B87,SAU_Key,0))="O",INDEX(SAU_PP,MATCH("Premium|"&$B87,SAU_Key,0))*INDEX(RelUni,MATCH($B87,Cov_Cod,0),1)*(1+sig_SAU)/(1-load_SAU)*(1+tax_SAU),IF(INDEX(SAU_Status,MATCH("Premium|"&$B87,SAU_Key,0))="B","Incluída","n.d.")) -> Incluída | O87: =IF(INDEX(SAU_Status,MATCH("Premium|"&$B87,SAU_Key,0))="O",INDEX(SAU_PP,MATCH("Premium|"&$B87,SAU_Key,0))*INDEX(RelUni,MATCH($B87,Cov_Cod,0),2)*(1+sig_SAU)/(1-load_SAU)*(1+tax_SAU),IF(INDEX(SAU_Status,MATCH("Premium|"&$B87,SAU_Key,0))="B","Incluída","n.d.")) -> Incluída | P87: =IF(INDEX(SAU_Status,MATCH("Premium|"&$B87,SAU_Key,0))="O",INDEX(SAU_PP,MATCH("Premium|"&$B87,SAU_Key,0))*INDEX(RelUni,MATCH($B87,Cov_Cod,0),3)*(1+sig_SAU)/(1-load_SAU)*(1+tax_SAU),IF(INDEX(SAU_Status,MATCH("Premium|"&$B87,SAU_Key,0))="B","Incluída","n.d.")) -> Incluída | Q87: =IF(INDEX(SAU_Status,MATCH("Premium|"&$B87,SAU_Key,0))="O",INDEX(SAU_PP,MATCH("Premium|"&$B87,SAU_Key,0))*INDEX(RelUni,MATCH($B87,Cov_Cod,0),4)*(1+sig_SAU)/(1-load_SAU)*(1+tax_SAU),IF(INDEX(SAU_Status,MATCH("Premium|"&$B87,SAU_Key,0))="B","Incluída","n.d.")) -> Incluída | R87: =IF(INDEX(SAU_Status,MATCH("Premium|"&$B87,SAU_Key,0))="O",INDEX(SAU_PP,MATCH("Premium|"&$B87,SAU_Key,0))*INDEX(RelUni,MATCH($B87,Cov_Cod,0),5)*(1+sig_SAU)/(1-load_SAU)*(1+tax_SAU),IF(INDEX(SAU_Status,MATCH("Premium|"&$B87,SAU_Key,0))="B","Incluída","n.d.")) -> Incluída
B88: PROT | C88: =INDEX(Cov_Nome,MATCH(B88,Cov_Cod,0)) -> Próteses Dentárias | D88: =IF(INDEX(SAU_Status,MATCH("Base|"&$B88,SAU_Key,0))="O",INDEX(SAU_PP,MATCH("Base|"&$B88,SAU_Key,0))*INDEX(RelUni,MATCH($B88,Cov_Cod,0),1)*(1+sig_SAU)/(1-load_SAU)*(1+tax_SAU),IF(INDEX(SAU_Status,MATCH("Base|"&$B88,SAU_Key,0))="B","Incluída","n.d.")) -> n.d. | E88: =IF(INDEX(SAU_Status,MATCH("Base|"&$B88,SAU_Key,0))="O",INDEX(SAU_PP,MATCH("Base|"&$B88,SAU_Key,0))*INDEX(RelUni,MATCH($B88,Cov_Cod,0),2)*(1+sig_SAU)/(1-load_SAU)*(1+tax_SAU),IF(INDEX(SAU_Status,MATCH("Base|"&$B88,SAU_Key,0))="B","Incluída","n.d.")) -> n.d. | F88: =IF(INDEX(SAU_Status,MATCH("Base|"&$B88,SAU_Key,0))="O",INDEX(SAU_PP,MATCH("Base|"&$B88,SAU_Key,0))*INDEX(RelUni,MATCH($B88,Cov_Cod,0),3)*(1+sig_SAU)/(1-load_SAU)*(1+tax_SAU),IF(INDEX(SAU_Status,MATCH("Base|"&$B88,SAU_Key,0))="B","Incluída","n.d.")) -> n.d. | G88: =IF(INDEX(SAU_Status,MATCH("Base|"&$B88,SAU_Key,0))="O",INDEX(SAU_PP,MATCH("Base|"&$B88,SAU_Key,0))*INDEX(RelUni,MATCH($B88,Cov_Cod,0),4)*(1+sig_SAU)/(1-load_SAU)*(1+tax_SAU),IF(INDEX(SAU_Status,MATCH("Base|"&$B88,SAU_Key,0))="B","Incluída","n.d.")) -> n.d. | H88: =IF(INDEX(SAU_Status,MATCH("Base|"&$B88,SAU_Key,0))="O",INDEX(SAU_PP,MATCH("Base|"&$B88,SAU_Key,0))*INDEX(RelUni,MATCH($B88,Cov_Cod,0),5)*(1+sig_SAU)/(1-load_SAU)*(1+tax_SAU),IF(INDEX(SAU_Status,MATCH("Base|"&$B88,SAU_Key,0))="B","Incluída","n.d.")) -> n.d. | I88: =IF(INDEX(SAU_Status,MATCH("Conforto|"&$B88,SAU_Key,0))="O",INDEX(SAU_PP,MATCH("Conforto|"&$B88,SAU_Key,0))*INDEX(RelUni,MATCH($B88,Cov_Cod,0),1)*(1+sig_SAU)/(1-load_SAU)*(1+tax_SAU),IF(INDEX(SAU_Status,MATCH("Conforto|"&$B88,SAU_Key,0))="B","Incluída","n.d.")) -> 446.72813 | J88: =IF(INDEX(SAU_Status,MATCH("Conforto|"&$B88,SAU_Key,0))="O",INDEX(SAU_PP,MATCH("Conforto|"&$B88,SAU_Key,0))*INDEX(RelUni,MATCH($B88,Cov_Cod,0),2)*(1+sig_SAU)/(1-load_SAU)*(1+tax_SAU),IF(INDEX(SAU_Status,MATCH("Conforto|"&$B88,SAU_Key,0))="B","Incluída","n.d.")) -> 4467.2813 | K88: =IF(INDEX(SAU_Status,MATCH("Conforto|"&$B88,SAU_Key,0))="O",INDEX(SAU_PP,MATCH("Conforto|"&$B88,SAU_Key,0))*INDEX(RelUni,MATCH($B88,Cov_Cod,0),3)*(1+sig_SAU)/(1-load_SAU)*(1+tax_SAU),IF(INDEX(SAU_Status,MATCH("Conforto|"&$B88,SAU_Key,0))="B","Incluída","n.d.")) -> 9828.0188 | L88: =IF(INDEX(SAU_Status,MATCH("Conforto|"&$B88,SAU_Key,0))="O",INDEX(SAU_PP,MATCH("Conforto|"&$B88,SAU_Key,0))*INDEX(RelUni,MATCH($B88,Cov_Cod,0),4)*(1+sig_SAU)/(1-load_SAU)*(1+tax_SAU),IF(INDEX(SAU_Status,MATCH("Conforto|"&$B88,SAU_Key,0))="B","Incluída","n.d.")) -> 15635.484 | M88: =IF(INDEX(SAU_Status,MATCH("Conforto|"&$B88,SAU_Key,0))="O",INDEX(SAU_PP,MATCH("Conforto|"&$B88,SAU_Key,0))*INDEX(RelUni,MATCH($B88,Cov_Cod,0),5)*(1+sig_SAU)/(1-load_SAU)*(1+tax_SAU),IF(INDEX(SAU_Status,MATCH("Conforto|"&$B88,SAU_Key,0))="B","Incluída","n.d.")) -> 17869.125 | N88: =IF(INDEX(SAU_Status,MATCH("Premium|"&$B88,SAU_Key,0))="O",INDEX(SAU_PP,MATCH("Premium|"&$B88,SAU_Key,0))*INDEX(RelUni,MATCH($B88,Cov_Cod,0),1)*(1+sig_SAU)/(1-load_SAU)*(1+tax_SAU),IF(INDEX(SAU_Status,MATCH("Premium|"&$B88,SAU_Key,0))="B","Incluída","n.d.")) -> Incluída | O88: =IF(INDEX(SAU_Status,MATCH("Premium|"&$B88,SAU_Key,0))="O",INDEX(SAU_PP,MATCH("Premium|"&$B88,SAU_Key,0))*INDEX(RelUni,MATCH($B88,Cov_Cod,0),2)*(1+sig_SAU)/(1-load_SAU)*(1+tax_SAU),IF(INDEX(SAU_Status,MATCH("Premium|"&$B88,SAU_Key,0))="B","Incluída","n.d.")) -> Incluída | P88: =IF(INDEX(SAU_Status,MATCH("Premium|"&$B88,SAU_Key,0))="O",INDEX(SAU_PP,MATCH("Premium|"&$B88,SAU_Key,0))*INDEX(RelUni,MATCH($B88,Cov_Cod,0),3)*(1+sig_SAU)/(1-load_SAU)*(1+tax_SAU),IF(INDEX(SAU_Status,MATCH("Premium|"&$B88,SAU_Key,0))="B","Incluída","n.d.")) -> Incluída | Q88: =IF(INDEX(SAU_Status,MATCH("Premium|"&$B88,SAU_Key,0))="O",INDEX(SAU_PP,MATCH("Premium|"&$B88,SAU_Key,0))*INDEX(RelUni,MATCH($B88,Cov_Cod,0),4)*(1+sig_SAU)/(1-load_SAU)*(1+tax_SAU),IF(INDEX(SAU_Status,MATCH("Premium|"&$B88,SAU_Key,0))="B","Incluída","n.d.")) -> Incluída | R88: =IF(INDEX(SAU_Status,MATCH("Premium|"&$B88,SAU_Key,0))="O",INDEX(SAU_PP,MATCH("Premium|"&$B88,SAU_Key,0))*INDEX(RelUni,MATCH($B88,Cov_Cod,0),5)*(1+sig_SAU)/(1-load_SAU)*(1+tax_SAU),IF(INDEX(SAU_Status,MATCH("Premium|"&$B88,SAU_Key,0))="B","Incluída","n.d.")) -> Incluída
... B93: HEMO | C93: =INDEX(Cov_Nome,MATCH(B93,Cov_Cod,0)) -> Doenças Crónicas — Hemodiálise | D93: =IF(INDEX(SAU_Status,MATCH("Base|"&$B93,SAU_Key,0))="O",INDEX(SAU_PP,MATCH("Base|"&$B93,SAU_Key,0))*INDEX(RelUni,MATCH($B93,Cov_Cod,0),1)*(1+sig_SAU)/(1-load_SAU)*(1+tax_SAU),IF(INDEX(SAU_Status,MATCH("Base|"&$B93,SAU_Key,0))="B","Incluída","n.d.")) -> 467.10975 | E93: =IF(INDEX(SAU_Status,MATCH("Base|"&$B93,SAU_Key,0))="O",INDEX(SAU_PP,MATCH("Base|"&$B93,SAU_Key,0))*INDEX(RelUni,MATCH($B93,Cov_Cod,0),2)*(1+sig_SAU)/(1-load_SAU)*(1+tax_SAU),IF(INDEX(SAU_Status,MATCH("Base|"&$B93,SAU_Key,0))="B","Incluída","n.d.")) -> 2224.0794 | F93: =IF(INDEX(SAU_Status,MATCH("Base|"&$B93,SAU_Key,0))="O",INDEX(SAU_PP,MATCH("Base|"&$B93,SAU_Key,0))*INDEX(RelUni,MATCH($B93,Cov_Cod,0),3)*(1+sig_SAU)/(1-load_SAU)*(1+tax_SAU),IF(INDEX(SAU_Status,MATCH("Base|"&$B93,SAU_Key,0))="B","Incluída","n.d.")) -> 5523.5728 | G93: =IF(INDEX(SAU_Status,MATCH("Base|"&$B93,SAU_Key,0))="O",INDEX(SAU_PP,MATCH("Base|"&$B93,SAU_Key,0))*INDEX(RelUni,MATCH($B93,Cov_Cod,0),4)*(1+sig_SAU)/(1-load_SAU)*(1+tax_SAU),IF(INDEX(SAU_Status,MATCH("Base|"&$B93,SAU_Key,0))="B","Incluída","n.d.")) -> 12118.903 | H93: =IF(INDEX(SAU_Status,MATCH("Base|"&$B93,SAU_Key,0))="O",INDEX(SAU_PP,MATCH("Base|"&$B93,SAU_Key,0))*INDEX(RelUni,MATCH($B93,Cov_Cod,0),5)*(1+sig_SAU)/(1-load_SAU)*(1+tax_SAU),IF(INDEX(SAU_Status,MATCH("Base|"&$B93,SAU_Key,0))="B","Incluída","n.d.")) -> 16417.534 | I93: =IF(INDEX(SAU_Status,MATCH("Conforto|"&$B93,SAU_Key,0))="O",INDEX(SAU_PP,MATCH("Conforto|"&$B93,SAU_Key,0))*INDEX(RelUni,MATCH($B93,Cov_Cod,0),1)*(1+sig_SAU)/(1-load_SAU)*(1+tax_SAU),IF(INDEX(SAU_Status,MATCH("Conforto|"&$B93,SAU_Key,0))="B","Incluída","n.d.")) -> 892.27773 | J93: =IF(INDEX(SAU_Status,MATCH("Conforto|"&$B93,SAU_Key,0))="O",INDEX(SAU_PP,MATCH("Conforto|"&$B93,SAU_Key,0))*INDEX(RelUni,MATCH($B93,Cov_Cod,0),2)*(1+sig_SAU)/(1-load_SAU)*(1+tax_SAU),IF(INDEX(SAU_Status,MATCH("Conforto|"&$B93,SAU_Key,0))="B","Incluída","n.d.")) -> 4248.4587 | K93: =IF(INDEX(SAU_Status,MATCH("Conforto|"&$B93,SAU_Key,0))="O",INDEX(SAU_PP,MATCH("Conforto|"&$B93,SAU_Key,0))*INDEX(RelUni,MATCH($B93,Cov_Cod,0),3)*(1+sig_SAU)/(1-load_SAU)*(1+tax_SAU),IF(INDEX(SAU_Status,MATCH("Conforto|"&$B93,SAU_Key,0))="B","Incluída","n.d.")) -> 10551.184 | L93: =IF(INDEX(SAU_Status,MATCH("Conforto|"&$B93,SAU_Key,0))="O",INDEX(SAU_PP,MATCH("Conforto|"&$B93,SAU_Key,0))*INDEX(RelUni,MATCH($B93,Cov_Cod,0),4)*(1+sig_SAU)/(1-load_SAU)*(1+tax_SAU),IF(INDEX(SAU_Status,MATCH("Conforto|"&$B93,SAU_Key,0))="B","Incluída","n.d.")) -> 23149.65 | M93: =IF(INDEX(SAU_Status,MATCH("Conforto|"&$B93,SAU_Key,0))="O",INDEX(SAU_PP,MATCH("Conforto|"&$B93,SAU_Key,0))*INDEX(RelUni,MATCH($B93,Cov_Cod,0),5)*(1+sig_SAU)/(1-load_SAU)*(1+tax_SAU),IF(INDEX(SAU_Status,MATCH("Conforto|"&$B93,SAU_Key,0))="B","Incluída","n.d.")) -> 31360.938 | N93: =IF(INDEX(SAU_Status,MATCH("Premium|"&$B93,SAU_Key,0))="O",INDEX(SAU_PP,MATCH("Premium|"&$B93,SAU_Key,0))*INDEX(RelUni,MATCH($B93,Cov_Cod,0),1)*(1+sig_SAU)/(1-load_SAU)*(1+tax_SAU),IF(INDEX(SAU_Status,MATCH("Premium|"&$B93,SAU_Key,0))="B","Incluída","n.d.")) -> Incluída | O93: =IF(INDEX(SAU_Status,MATCH("Premium|"&$B93,SAU_Key,0))="O",INDEX(SAU_PP,MATCH("Premium|"&$B93,SAU_Key,0))*INDEX(RelUni,MATCH($B93,Cov_Cod,0),2)*(1+sig_SAU)/(1-load_SAU)*(1+tax_SAU),IF(INDEX(SAU_Status,MATCH("Premium|"&$B93,SAU_Key,0))="B","Incluída","n.d.")) -> Incluída | P93: =IF(INDEX(SAU_Status,MATCH("Premium|"&$B93,SAU_Key,0))="O",INDEX(SAU_PP,MATCH("Premium|"&$B93,SAU_Key,0))*INDEX(RelUni,MATCH($B93,Cov_Cod,0),3)*(1+sig_SAU)/(1-load_SAU)*(1+tax_SAU),IF(INDEX(SAU_Status,MATCH("Premium|"&$B93,SAU_Key,0))="B","Incluída","n.d.")) -> Incluída | Q93: =IF(INDEX(SAU_Status,MATCH("Premium|"&$B93,SAU_Key,0))="O",INDEX(SAU_PP,MATCH("Premium|"&$B93,SAU_Key,0))*INDEX(RelUni,MATCH($B93,Cov_Cod,0),4)*(1+sig_SAU)/(1-load_SAU)*(1+tax_SAU),IF(INDEX(SAU_Status,MATCH("Premium|"&$B93,SAU_Key,0))="B","Incluída","n.d.")) -> Incluída | R93: =IF(INDEX(SAU_Status,MATCH("Premium|"&$B93,SAU_Key,0))="O",INDEX(SAU_PP,MATCH("Premium|"&$B93,SAU_Key,0))*INDEX(RelUni,MATCH($B93,Cov_Cod,0),5)*(1+sig_SAU)/(1-load_SAU)*(1+tax_SAU),IF(INDEX(SAU_Status,MATCH("Premium|"&$B93,SAU_Key,0))="B","Incluída","n.d.")) -> Incluída
B95: "Incluída" = cobertura de base no plano (já no pacote base §2); "n.d." = não disponível no plano. Maternidade: prémio unisex diluído — no Calculador a tarifa é aplicada por género.

Sheet Matriz_SAG
A1: MATRIZ TARIFÁRIA SAG — SEGURO DE SAÚDE GRUPO / EMPRESARIAL | TARIFAÇÃO COLECTIVA
A2: Planos por Categoria Profissional (Colaboradores / Quadros Médios / Administração). Prémio padrão por pessoa antes de factores colectivos (dimensão, regime de adesão, sector, região), experience rating e modalidade ASO — ver secções 4 a 7.
A3: Parâmetros aplicados → | B3: σ | C3: =sig_SAG -> 0.05 | D3: e_a+e_c+m | E3: =load_SAG -> 0.21 | F3: Impostos | G3: =tax_SAG -> 0.01 | H3: Trend | I3: =f_trend -> 1.182194
A4: Fórmulas: Prémio Puro = λ × μ ajustado × Trend × Factor LEV | Prémio de Risco Técnico = Prémio Puro × (1+σ) | Prémio Comercial Bruto = PRT / (1 − (e_a+e_c+m)) | Prémio Total = PCB × (1 + impostos). Valores por Pessoa Segura/anuidade na célula de referência da cobertura (ver Premissas §D).
A5: Chave | B5: Plano / Categoria | C5: Código | D5: Cobertura | E5: Grupo | F5: Estatuto (B/O/—) | G5: Capital / Sublimite anual (Kz) | H5: Frequência λ | I5: μ Ponderado (Kz) | J5: Factor de Rede | K5: Dedução sublimite quarto (Kz) | L5: μ Ajustado (Kz) | M5: Factor Trend | N5: Custo médio por sinistrado (Kz) | O5: CV | P5: σ ln | Q5: μ ln | R5: Factor Limitação de Capital (LEV) | S5: PRÉMIO PURO (Kz) | T5: Carregamento Volatilidade σ (Kz) | U5: PRÉMIO DE RISCO TÉCNICO (Kz) | V5: PRÉMIO COMERCIAL BRUTO (Kz) | W5: Despesas Gestão e_a (Kz) | X5: Comissões e_c (Kz) | Y5: Margem m (Kz) | Z5: Impostos e Taxas (Kz) | AA5: PRÉMIO TOTAL ANUAL (Kz) | AB5: Taxa de Risco Pura (‰ do capital)
A6: =B6&"|"&C6 -> Colaboradores|HOSP_INT | B6: Colaboradores | C6: HOSP_INT | D6: =INDEX(Cov_Nome,MATCH(C6,Cov_Cod,0)) -> Internamento Hospitalar Médico (incl. malária grave) | E6: =INDEX(Cov_Grupo,MATCH(C6,Cov_Cod,0)) -> Principal | F6: B | G6: 10000000 | H6: =INDEX(Cov_Lambda,MATCH(C6,Cov_Cod,0)) -> 0.045 | I6: =INDEX(Cov_Mu,MATCH(C6,Cov_Cod,0)) -> 854500 | J6: =IF(INDEX(Cov_FR,MATCH(C6,Cov_Cod,0))="S",INDEX(PF_Factor,MATCH("SAG|"&B6,PF_Key,0)),1) -> 0.9 | K6: =IF(C6="HOSP_INT",los_int,IF(C6="HOSP_CIR",los_cir,0))*MAX(0,room_ref*J6-INDEX(PF_Room,MATCH("SAG|"&B6,PF_Key,0))) -> 96000 | L6: =MAX(0,I6*J6-K6) -> 673050 | M6: =f_trend -> 1.182194 | N6: =H6*L6*M6/(1-EXP(-H6)) -> 813712.64 | O6: =INDEX(Cov_CV,MATCH(C6,Cov_Cod,0)) -> 1.5 | P6: =SQRT(LN(1+O6^2)) -> 1.0856588 | Q6: =LN(N6)-P6^2/2 -> 13.020035 | R6: =IF(G6<=0,1,NORMSDIST((LN(G6)-Q6-P6^2)/P6)+G6/N6*(1-NORMSDIST((LN(G6)-Q6)/P6))) -> 0.98802617 | S6: =IF(F6="—",0,H6*L6*M6*R6) -> 35376.678 | T6: =S6*sig_SAG -> 1768.8339 | U6: =S6+T6 -> 37145.511 | V6: =U6/(1-load_SAG) -> 47019.635 | W6: =V6*ea_SAG -> 4701.9635 | X6: =V6*ec_SAG -> 3291.3744 | Y6: =V6*m_SAG -> 1880.7854 | Z6: =V6*tax_SAG -> 470.19635 | AA6: =V6+Z6 -> 47489.831 | AB6: =IF(G6>0,S6/G6*1000,"n.a.") -> 3.5376678
A7: =B7&"|"&C7 -> Colaboradores|HOSP_CIR | B7: Colaboradores | C7: HOSP_CIR | D7: =INDEX(Cov_Nome,MATCH(C7,Cov_Cod,0)) -> Cirurgia (com internamento e de ambulatório) | E7: =INDEX(Cov_Grupo,MATCH(C7,Cov_Cod,0)) -> Principal | F7: B | G7: 10000000 | H7: =INDEX(Cov_Lambda,MATCH(C7,Cov_Cod,0)) -> 0.024 | I7: =INDEX(Cov_Mu,MATCH(C7,Cov_Cod,0)) -> 2032500 | J7: =IF(INDEX(Cov_FR,MATCH(C7,Cov_Cod,0))="S",INDEX(PF_Factor,MATCH("SAG|"&B7,PF_Key,0)),1) -> 0.9 | K7: =IF(C7="HOSP_INT",los_int,IF(C7="HOSP_CIR",los_cir,0))*MAX(0,room_ref*J7-INDEX(PF_Room,MATCH("SAG|"&B7,PF_Key,0))) -> 60000 | L7: =MAX(0,I7*J7-K7) -> 1769250 | M7: =f_trend -> 1.182194 | N7: =H7*L7*M7/(1-EXP(-H7)) -> 2116796.3 | O7: =INDEX(Cov_CV,MATCH(C7,Cov_Cod,0)) -> 1.3 | P7: =SQRT(LN(1+O7^2)) -> 0.99475685 | Q7: =LN(N7)-P7^2/2 -> 14.070644 | R7: =IF(G7<=0,1,NORMSDIST((LN(G7)-Q7-P7^2)/P7)+G7/N7*(1-NORMSDIST((LN(G7)-Q7)/P7))) -> 0.94967842 | S7: =IF(F7="—",0,H7*L7*M7*R7) -> 47672.263 | T7: =S7*sig_SAG -> 2383.6131 | U7: =S7+T7 -> 50055.876 | V7: =U7/(1-load_SAG) -> 63361.868 | W7: =V7*ea_SAG -> 6336.1868 | X7: =V7*ec_SAG -> 4435.3308 | Y7: =V7*m_SAG -> 2534.4747 | Z7: =V7*tax_SAG -> 633.61868 | AA7: =V7+Z7 -> 63995.487 | AB7: =IF(G7>0,S7/G7*1000,"n.a.") -> 4.7672263
A8: =B8&"|"&C8 -> Colaboradores|HOSP_UCI | B8: Colaboradores | C8: HOSP_UCI | D8: =INDEX(Cov_Nome,MATCH(C8,Cov_Cod,0)) -> Cuidados Intensivos (UCI) | E8: =INDEX(Cov_Grupo,MATCH(C8,Cov_Cod,0)) -> Principal | F8: B | G8: =INDEX(PF_UCI,MATCH("SAG|"&B8,PF_Key,0)) -> 4000000 | H8: =INDEX(Cov_Lambda,MATCH(C8,Cov_Cod,0)) -> 0.0035 | I8: =INDEX(Cov_Mu,MATCH(C8,Cov_Cod,0)) -> 2835000 | J8: =IF(INDEX(Cov_FR,MATCH(C8,Cov_Cod,0))="S",INDEX(PF_Factor,MATCH("SAG|"&B8,PF_Key,0)),1) -> 0.9 | K8: =IF(C8="HOSP_INT",los_int,IF(C8="HOSP_CIR",los_cir,0))*MAX(0,room_ref*J8-INDEX(PF_Room,MATCH("SAG|"&B8,PF_Key,0))) -> 0 | L8: =MAX(0,I8*J8-K8) -> 2551500 | M8: =f_trend -> 1.182194 | N8: =H8*L8*M8/(1-EXP(-H8)) -> 3021649.7 | O8: =INDEX(Cov_CV,MATCH(C8,Cov_Cod,0)) -> 1.2 | P8: =SQRT(LN(1+O8^2)) -> 0.94445648 | Q8: =LN(N8)-P8^2/2 -> 14.475314 | R8: =IF(G8<=0,1,NORMSDIST((LN(G8)-Q8-P8^2)/P8)+G8/N8*(1-NORMSDIST((LN(G8)-Q8)/P8))) -> 0.72284528 | S8: =IF(F8="—",0,H8*L8*M8*R8) -> 7631.2857 | T8: =S8*sig_SAG -> 381.56429 | U8: =S8+T8 -> 8012.85 | V8: =U8/(1-load_SAG) -> 10142.848 | W8: =V8*ea_SAG -> 1014.2848 | X8: =V8*ec_SAG -> 709.99937 | Y8: =V8*m_SAG -> 405.71393 | Z8: =V8*tax_SAG -> 101.42848 | AA8: =V8+Z8 -> 10244.277 | AB8: =IF(G8>0,S8/G8*1000,"n.a.") -> 1.9078214
A9: =B9&"|"&C9 -> Colaboradores|AMB_CONS | B9: Colaboradores | C9: AMB_CONS | D9: =INDEX(Cov_Nome,MATCH(C9,Cov_Cod,0)) -> Consultas de Clínica Geral e Especialidade (incl. teleconsulta) | E9: =INDEX(Cov_Grupo,MATCH(C9,Cov_Cod,0)) -> Principal | F9: B | G9: 2000000 | H9: =INDEX(Cov_Lambda,MATCH(C9,Cov_Cod,0)) -> 2.6 | I9: =INDEX(Cov_Mu,MATCH(C9,Cov_Cod,0)) -> 24000 | J9: =IF(INDEX(Cov_FR,MATCH(C9,Cov_Cod,0))="S",INDEX(PF_Factor,MATCH("SAG|"&B9,PF_Key,0)),1) -> 0.9 | K9: =IF(C9="HOSP_INT",los_int,IF(C9="HOSP_CIR",los_cir,0))*MAX(0,room_ref*J9-INDEX(PF_Room,MATCH("SAG|"&B9,PF_Key,0))) -> 0 | L9: =MAX(0,I9*J9-K9) -> 21600 | M9: =f_trend -> 1.182194 | N9: =H9*L9*M9/(1-EXP(-H9)) -> 71718.829 | O9: =INDEX(Cov_CV,MATCH(C9,Cov_Cod,0)) -> 1 | P9: =SQRT(LN(1+O9^2)) -> 0.83255461 | Q9: =LN(N9)-P9^2/2 -> 10.833935 | R9: =IF(G9<=0,1,NORMSDIST((LN(G9)-Q9-P9^2)/P9)+G9/N9*(1-NORMSDIST((LN(G9)-Q9)/P9))) -> 0.99997064 | S9: =IF(F9="—",0,H9*L9*M9*R9) -> 66390.066 | T9: =S9*sig_SAG -> 3319.5033 | U9: =S9+T9 -> 69709.569 | V9: =U9/(1-load_SAG) -> 88239.961 | W9: =V9*ea_SAG -> 8823.9961 | X9: =V9*ec_SAG -> 6176.7973 | Y9: =V9*m_SAG -> 3529.5985 | Z9: =V9*tax_SAG -> 882.39961 | AA9: =V9+Z9 -> 89122.361 | AB9: =IF(G9>0,S9/G9*1000,"n.a.") -> 33.195033
A10: =B10&"|"&C10 -> Colaboradores|AMB_MCDT | B10: Colaboradores | C10: AMB_MCDT | D10: =INDEX(Cov_Nome,MATCH(C10,Cov_Cod,0)) -> MCDT — Exames, Análises e Imagiologia | E10: =INDEX(Cov_Grupo,MATCH(C10,Cov_Cod,0)) -> Principal | F10: B | G10: 2000000 | H10: =INDEX(Cov_Lambda,MATCH(C10,Cov_Cod,0)) -> 3.8 | I10: =INDEX(Cov_Mu,MATCH(C10,Cov_Cod,0)) -> 14600 | J10: =IF(INDEX(Cov_FR,MATCH(C10,Cov_Cod,0))="S",INDEX(PF_Factor,MATCH("SAG|"&B10,PF_Key,0)),1) -> 0.9 | K10: =IF(C10="HOSP_INT",los_int,IF(C10="HOSP_CIR",los_cir,0))*MAX(0,room_ref*J10-INDEX(PF_Room,MATCH("SAG|"&B10,PF_Key,0))) -> 0 | L10: =MAX(0,I10*J10-K10) -> 13140 | M10: =f_trend -> 1.182194 | N10: =H10*L10*M10/(1-EXP(-H10)) -> 60380.059 | O10: =INDEX(Cov_CV,MATCH(C10,Cov_Cod,0)) -> 1.5 | P10: =SQRT(LN(1+O10^2)) -> 1.0856588 | Q10: =LN(N10)-P10^2/2 -> 10.419087 | R10: =IF(G10<=0,1,NORMSDIST((LN(G10)-Q10-P10^2)/P10)+G10/N10*(1-NORMSDIST((LN(G10)-Q10)/P10))) -> 0.99906997 | S10: =IF(F10="—",0,H10*L10*M10*R10) -> 58974.411 | T10: =S10*sig_SAG -> 2948.7206 | U10: =S10+T10 -> 61923.132 | V10: =U10/(1-load_SAG) -> 78383.711 | W10: =V10*ea_SAG -> 7838.3711 | X10: =V10*ec_SAG -> 5486.8598 | Y10: =V10*m_SAG -> 3135.3485 | Z10: =V10*tax_SAG -> 783.83711 | AA10: =V10+Z10 -> 79167.549 | AB10: =IF(G10>0,S10/G10*1000,"n.a.") -> 29.487206
A11: =B11&"|"&C11 -> Colaboradores|MAL | B11: Colaboradores | C11: MAL | D11: =INDEX(Cov_Nome,MATCH(C11,Cov_Cod,0)) -> Malária e Doenças Endémicas (ambulatório) | E11: =INDEX(Cov_Grupo,MATCH(C11,Cov_Cod,0)) -> Principal | F11: B | G11: 2000000 | H11: =INDEX(Cov_Lambda,MATCH(C11,Cov_Cod,0)) -> 0.3 | I11: =INDEX(Cov_Mu,MATCH(C11,Cov_Cod,0)) -> 36500 | J11: =IF(INDEX(Cov_FR,MATCH(C11,Cov_Cod,0))="S",INDEX(PF_Factor,MATCH("SAG|"&B11,PF_Key,0)),1) -> 0.9 | K11: =IF(C11="HOSP_INT",los_int,IF(C11="HOSP_CIR",los_cir,0))*MAX(0,room_ref*J11-INDEX(PF_Room,MATCH("SAG|"&B11,PF_Key,0))) -> 0 | L11: =MAX(0,I11*J11-K11) -> 32850 | M11: =f_trend -> 1.182194 | N11: =H11*L11*M11/(1-EXP(-H11)) -> 44951.161 | O11: =INDEX(Cov_CV,MATCH(C11,Cov_Cod,0)) -> 0.8 | P11: =SQRT(LN(1+O11^2)) -> 0.70334646 | Q11: =LN(N11)-P11^2/2 -> 10.465984 | R11: =IF(G11<=0,1,NORMSDIST((LN(G11)-Q11-P11^2)/P11)+G11/N11*(1-NORMSDIST((LN(G11)-Q11)/P11))) -> 0.99999997 | S11: =IF(F11="—",0,H11*L11*M11*R11) -> 11650.522 | T11: =S11*sig_SAG -> 582.52608 | U11: =S11+T11 -> 12233.048 | V11: =U11/(1-load_SAG) -> 15484.87 | W11: =V11*ea_SAG -> 1548.487 | X11: =V11*ec_SAG -> 1083.9409 | Y11: =V11*m_SAG -> 619.39482 | Z11: =V11*tax_SAG -> 154.8487 | AA11: =V11+Z11 -> 15639.719 | AB11: =IF(G11>0,S11/G11*1000,"n.a.") -> 5.8252608
A12: =B12&"|"&C12 -> Colaboradores|MAT | B12: Colaboradores | C12: MAT | D12: =INDEX(Cov_Nome,MATCH(C12,Cov_Cod,0)) -> Maternidade e Parto (Normal e Cesariana) | E12: =INDEX(Cov_Grupo,MATCH(C12,Cov_Cod,0)) -> Principal | F12: B | G12: 800000 | H12: =INDEX(Cov_Lambda,MATCH(C12,Cov_Cod,0)) -> 0.075 | I12: =INDEX(Cov_Mu,MATCH(C12,Cov_Cod,0)) -> 885640 | J12: =IF(INDEX(Cov_FR,MATCH(C12,Cov_Cod,0))="S",INDEX(PF_Factor,MATCH("SAG|"&B12,PF_Key,0)),1) -> 0.9 | K12: =IF(C12="HOSP_INT",los_int,IF(C12="HOSP_CIR",los_cir,0))*MAX(0,room_ref*J12-INDEX(PF_Room,MATCH("SAG|"&B12,PF_Key,0))) -> 0 | L12: =MAX(0,I12*J12-K12) -> 797076 | M12: =f_trend -> 1.182194 | N12: =H12*L12*M12/(1-EXP(-H12)) -> 978076.32 | O12: =INDEX(Cov_CV,MATCH(C12,Cov_Cod,0)) -> 0.5 | P12: =SQRT(LN(1+O12^2)) -> 0.47238073 | Q12: =LN(N12)-P12^2/2 -> 13.681771 | R12: =IF(G12<=0,1,NORMSDIST((LN(G12)-Q12-P12^2)/P12)+G12/N12*(1-NORMSDIST((LN(G12)-Q12)/P12))) -> 0.72445707 | S12: =IF(F12="—",0,H12*L12*M12*R12) -> 51199.109 | T12: =S12*sig_SAG -> 2559.9555 | U12: =S12+T12 -> 53759.065 | V12: =U12/(1-load_SAG) -> 68049.449 | W12: =V12*ea_SAG -> 6804.9449 | X12: =V12*ec_SAG -> 4763.4614 | Y12: =V12*m_SAG -> 2721.978 | Z12: =V12*tax_SAG -> 680.49449 | AA12: =V12+Z12 -> 68729.943 | AB12: =IF(G12>0,S12/G12*1000,"n.a.") -> 63.998886
A13: =B13&"|"&C13 -> Colaboradores|URG | B13: Colaboradores | C13: URG | D13: =INDEX(Cov_Nome,MATCH(C13,Cov_Cod,0)) -> Urgência Hospitalar | E13: =INDEX(Cov_Grupo,MATCH(C13,Cov_Cod,0)) -> Principal | F13: B | G13: 400000 | H13: =INDEX(Cov_Lambda,MATCH(C13,Cov_Cod,0)) -> 0.42 | I13: =INDEX(Cov_Mu,MATCH(C13,Cov_Cod,0)) -> 43300 | J13: =IF(INDEX(Cov_FR,MATCH(C13,Cov_Cod,0))="S",INDEX(PF_Factor,MATCH("SAG|"&B13,PF_Key,0)),1) -> 0.9 | K13: =IF(C13="HOSP_INT",los_int,IF(C13="HOSP_CIR",los_cir,0))*MAX(0,room_ref*J13-INDEX(PF_Room,MATCH("SAG|"&B13,PF_Key,0))) -> 0 | L13: =MAX(0,I13*J13-K13) -> 38970 | M13: =f_trend -> 1.182194 | N13: =H13*L13*M13/(1-EXP(-H13)) -> 56420.069 | O13: =INDEX(Cov_CV,MATCH(C13,Cov_Cod,0)) -> 1 | P13: =SQRT(LN(1+O13^2)) -> 0.83255461 | Q13: =LN(N13)-P13^2/2 -> 10.594007 | R13: =IF(G13<=0,1,NORMSDIST((LN(G13)-Q13-P13^2)/P13)+G13/N13*(1-NORMSDIST((LN(G13)-Q13)/P13))) -> 0.99352555 | S13: =IF(F13="—",0,H13*L13*M13*R13) -> 19224.165 | T13: =S13*sig_SAG -> 961.20826 | U13: =S13+T13 -> 20185.373 | V13: =U13/(1-load_SAG) -> 25551.106 | W13: =V13*ea_SAG -> 2555.1106 | X13: =V13*ec_SAG -> 1788.5774 | Y13: =V13*m_SAG -> 1022.0442 | Z13: =V13*tax_SAG -> 255.51106 | AA13: =V13+Z13 -> 25806.617 | AB13: =IF(G13>0,S13/G13*1000,"n.a.") -> 48.060413
A14: =B14&"|"&C14 -> Colaboradores|AMBUL | B14: Colaboradores | C14: AMBUL | D14: =INDEX(Cov_Nome,MATCH(C14,Cov_Cod,0)) -> Transporte em Ambulância / Emergência Médica | E14: =INDEX(Cov_Grupo,MATCH(C14,Cov_Cod,0)) -> Principal | F14: B | G14: 200000 | H14: =INDEX(Cov_Lambda,MATCH(C14,Cov_Cod,0)) -> 0.018 | I14: =INDEX(Cov_Mu,MATCH(C14,Cov_Cod,0)) -> 76000 | J14: =IF(INDEX(Cov_FR,MATCH(C14,Cov_Cod,0))="S",INDEX(PF_Factor,MATCH("SAG|"&B14,PF_Key,0)),1) -> 1 | K14: =IF(C14="HOSP_INT",los_int,IF(C14="HOSP_CIR",los_cir,0))*MAX(0,room_ref*J14-INDEX(PF_Room,MATCH("SAG|"&B14,PF_Key,0))) -> 0 | L14: =MAX(0,I14*J14-K14) -> 76000 | M14: =f_trend -> 1.182194 | N14: =H14*L14*M14/(1-EXP(-H14)) -> 90657.791 | O14: =INDEX(Cov_CV,MATCH(C14,Cov_Cod,0)) -> 0.6 | P14: =SQRT(LN(1+O14^2)) -> 0.55451303 | Q14: =LN(N14)-P14^2/2 -> 11.261105 | R14: =IF(G14<=0,1,NORMSDIST((LN(G14)-Q14-P14^2)/P14)+G14/N14*(1-NORMSDIST((LN(G14)-Q14)/P14))) -> 0.97231107 | S14: =IF(F14="—",0,H14*L14*M14*R14) -> 1572.4617 | T14: =S14*sig_SAG -> 78.623085 | U14: =S14+T14 -> 1651.0848 | V14: =U14/(1-load_SAG) -> 2089.9807 | W14: =V14*ea_SAG -> 208.99807 | X14: =V14*ec_SAG -> 146.29865 | Y14: =V14*m_SAG -> 83.59923 | Z14: =V14*tax_SAG -> 20.899807 | AA14: =V14+Z14 -> 2110.8805 | AB14: =IF(G14>0,S14/G14*1000,"n.a.") -> 7.8623085
A15: =B15&"|"&C15 -> Colaboradores|MED | B15: Colaboradores | C15: MED | D15: =INDEX(Cov_Nome,MATCH(C15,Cov_Cod,0)) -> Medicamentos em Ambulatório (Farmácia) | E15: =INDEX(Cov_Grupo,MATCH(C15,Cov_Cod,0)) -> Principal | F15: O | G15: 300000 | H15: =INDEX(Cov_Lambda,MATCH(C15,Cov_Cod,0)) -> 3.4 | I15: =INDEX(Cov_Mu,MATCH(C15,Cov_Cod,0)) -> 17400 | J15: =IF(INDEX(Cov_FR,MATCH(C15,Cov_Cod,0))="S",INDEX(PF_Factor,MATCH("SAG|"&B15,PF_Key,0)),1) -> 1 | K15: =IF(C15="HOSP_INT",los_int,IF(C15="HOSP_CIR",los_cir,0))*MAX(0,room_ref*J15-INDEX(PF_Room,MATCH("SAG|"&B15,PF_Key,0))) -> 0 | L15: =MAX(0,I15*J15-K15) -> 17400 | M15: =f_trend -> 1.182194 | N15: =H15*L15*M15/(1-EXP(-H15)) -> 72353.262 | O15: =INDEX(Cov_CV,MATCH(C15,Cov_Cod,0)) -> 1.2 | P15: =SQRT(LN(1+O15^2)) -> 0.94445648 | Q15: =LN(N15)-P15^2/2 -> 10.743317 | R15: =IF(G15<=0,1,NORMSDIST((LN(G15)-Q15-P15^2)/P15)+G15/N15*(1-NORMSDIST((LN(G15)-Q15)/P15))) -> 0.94868914 | S15: =IF(F15="—",0,H15*L15*M15*R15) -> 66349.988 | T15: =S15*sig_SAG -> 3317.4994 | U15: =S15+T15 -> 69667.487 | V15: =U15/(1-load_SAG) -> 88186.693 | W15: =V15*ea_SAG -> 8818.6693 | X15: =V15*ec_SAG -> 6173.0685 | Y15: =V15*m_SAG -> 3527.4677 | Z15: =V15*tax_SAG -> 881.86693 | AA15: =V15+Z15 -> 89068.559 | AB15: =IF(G15>0,S15/G15*1000,"n.a.") -> 221.16663
A16: =B16&"|"&C16 -> Colaboradores|DENT | B16: Colaboradores | C16: DENT | D16: =INDEX(Cov_Nome,MATCH(C16,Cov_Cod,0)) -> Estomatologia (tratamentos) | E16: =INDEX(Cov_Grupo,MATCH(C16,Cov_Cod,0)) -> Extensão | F16: O | G16: 200000 | H16: =INDEX(Cov_Lambda,MATCH(C16,Cov_Cod,0)) -> 0.85 | I16: =INDEX(Cov_Mu,MATCH(C16,Cov_Cod,0)) -> 34500 | J16: =IF(INDEX(Cov_FR,MATCH(C16,Cov_Cod,0))="S",INDEX(PF_Factor,MATCH("SAG|"&B16,PF_Key,0)),1) -> 0.9 | K16: =IF(C16="HOSP_INT",los_int,IF(C16="HOSP_CIR",los_cir,0))*MAX(0,room_ref*J16-INDEX(PF_Room,MATCH("SAG|"&B16,PF_Key,0))) -> 0 | L16: =MAX(0,I16*J16-K16) -> 31050 | M16: =f_trend -> 1.182194 | N16: =H16*L16*M16/(1-EXP(-H16)) -> 54491.563 | O16: =INDEX(Cov_CV,MATCH(C16,Cov_Cod,0)) -> 1 | P16: =SQRT(LN(1+O16^2)) -> 0.83255461 | Q16: =LN(N16)-P16^2/2 -> 10.559228 | R16: =IF(G16<=0,1,NORMSDIST((LN(G16)-Q16-P16^2)/P16)+G16/N16*(1-NORMSDIST((LN(G16)-Q16)/P16))) -> 0.96194384 | S16: =IF(F16="—",0,H16*L16*M16*R16) -> 30013.663 | T16: =S16*sig_SAG -> 1500.6831 | U16: =S16+T16 -> 31514.346 | V16: =U16/(1-load_SAG) -> 39891.577 | W16: =V16*ea_SAG -> 3989.1577 | X16: =V16*ec_SAG -> 2792.4104 | Y16: =V16*m_SAG -> 1595.6631 | Z16: =V16*tax_SAG -> 398.91577 | AA16: =V16+Z16 -> 40290.493 | AB16: =IF(G16>0,S16/G16*1000,"n.a.") -> 150.06831
A17: =B17&"|"&C17 -> Colaboradores|PROT | B17: Colaboradores | C17: PROT | D17: =INDEX(Cov_Nome,MATCH(C17,Cov_Cod,0)) -> Próteses Dentárias | E17: =INDEX(Cov_Grupo,MATCH(C17,Cov_Cod,0)) -> Extensão | F17: O | G17: 100000 | H17: =INDEX(Cov_Lambda,MATCH(C17,Cov_Cod,0)) -> 0.02 | I17: =INDEX(Cov_Mu,MATCH(C17,Cov_Cod,0)) -> 304000 | J17: =IF(INDEX(Cov_FR,MATCH(C17,Cov_Cod,0))="S",INDEX(PF_Factor,MATCH("SAG|"&B17,PF_Key,0)),1) -> 1 | K17: =IF(C17="HOSP_INT",los_int,IF(C17="HOSP_CIR",los_cir,0))*MAX(0,room_ref*J17-INDEX(PF_Room,MATCH("SAG|"&B17,PF_Key,0))) -> 0 | L17: =MAX(0,I17*J17-K17) -> 304000 | M17: =f_trend -> 1.182194 | N17: =H17*L17*M17/(1-EXP(-H17)) -> 362992.83 | O17: =INDEX(Cov_CV,MATCH(C17,Cov_Cod,0)) -> 0.7 | P17: =SQRT(LN(1+O17^2)) -> 0.63148723 | Q17: =LN(N17)-P17^2/2 -> 12.60275 | R17: =IF(G17<=0,1,NORMSDIST((LN(G17)-Q17-P17^2)/P17)+G17/N17*(1-NORMSDIST((LN(G17)-Q17)/P17))) -> 0.27306875 | S17: =IF(F17="—",0,H17*L17*M17*R17) -> 1962.7471 | T17: =S17*sig_SAG -> 98.137353 | U17: =S17+T17 -> 2060.8844 | V17: =U17/(1-load_SAG) -> 2608.7144 | W17: =V17*ea_SAG -> 260.87144 | X17: =V17*ec_SAG -> 182.61001 | Y17: =V17*m_SAG -> 104.34858 | Z17: =V17*tax_SAG -> 26.087144 | AA17: =V17+Z17 -> 2634.8016 | AB17: =IF(G17>0,S17/G17*1000,"n.a.") -> 19.627471
A18: =B18&"|"&C18 -> Colaboradores|OPT | B18: Colaboradores | C18: OPT | D18: =INDEX(Cov_Nome,MATCH(C18,Cov_Cod,0)) -> Óptica — Lentes e Armações | E18: =INDEX(Cov_Grupo,MATCH(C18,Cov_Cod,0)) -> Extensão | F18: O | G18: 80000 | H18: =INDEX(Cov_Lambda,MATCH(C18,Cov_Cod,0)) -> 0.22 | I18: =INDEX(Cov_Mu,MATCH(C18,Cov_Cod,0)) -> 102500 | J18: =IF(INDEX(Cov_FR,MATCH(C18,Cov_Cod,0))="S",INDEX(PF_Factor,MATCH("SAG|"&B18,PF_Key,0)),1) -> 1 | K18: =IF(C18="HOSP_INT",los_int,IF(C18="HOSP_CIR",los_cir,0))*MAX(0,room_ref*J18-INDEX(PF_Room,MATCH("SAG|"&B18,PF_Key,0))) -> 0 | L18: =MAX(0,I18*J18-K18) -> 102500 | M18: =f_trend -> 1.182194 | N18: =H18*L18*M18/(1-EXP(-H18)) -> 134992.47 | O18: =INDEX(Cov_CV,MATCH(C18,Cov_Cod,0)) -> 0.5 | P18: =SQRT(LN(1+O18^2)) -> 0.47238073 | Q18: =LN(N18)-P18^2/2 -> 11.701402 | R18: =IF(G18<=0,1,NORMSDIST((LN(G18)-Q18-P18^2)/P18)+G18/N18*(1-NORMSDIST((LN(G18)-Q18)/P18))) -> 0.56848874 | S18: =IF(F18="—",0,H18*L18*M18*R18) -> 15155.043 | T18: =S18*sig_SAG -> 757.75213 | U18: =S18+T18 -> 15912.795 | V18: =U18/(1-load_SAG) -> 20142.778 | W18: =V18*ea_SAG -> 2014.2778 | X18: =V18*ec_SAG -> 1409.9945 | Y18: =V18*m_SAG -> 805.71113 | Z18: =V18*tax_SAG -> 201.42778 | AA18: =V18+Z18 -> 20344.206 | AB18: =IF(G18>0,S18/G18*1000,"n.a.") -> 189.43803
A19: =B19&"|"&C19 -> Colaboradores|PREV | B19: Colaboradores | C19: PREV | D19: =INDEX(Cov_Nome,MATCH(C19,Cov_Cod,0)) -> Medicina Preventiva e Check-up Anual | E19: =INDEX(Cov_Grupo,MATCH(C19,Cov_Cod,0)) -> Extensão | F19: O | G19: 100000 | H19: =INDEX(Cov_Lambda,MATCH(C19,Cov_Cod,0)) -> 0.55 | I19: =INDEX(Cov_Mu,MATCH(C19,Cov_Cod,0)) -> 76000 | J19: =IF(INDEX(Cov_FR,MATCH(C19,Cov_Cod,0))="S",INDEX(PF_Factor,MATCH("SAG|"&B19,PF_Key,0)),1) -> 1 | K19: =IF(C19="HOSP_INT",los_int,IF(C19="HOSP_CIR",los_cir,0))*MAX(0,room_ref*J19-INDEX(PF_Room,MATCH("SAG|"&B19,PF_Key,0))) -> 0 | L19: =MAX(0,I19*J19-K19) -> 76000 | M19: =f_trend -> 1.182194 | N19: =H19*L19*M19/(1-EXP(-H19)) -> 116808.15 | O19: =INDEX(Cov_CV,MATCH(C19,Cov_Cod,0)) -> 0.3 | P19: =SQRT(LN(1+O19^2)) -> 0.29356038 | Q19: =LN(N19)-P19^2/2 -> 11.625199 | R19: =IF(G19<=0,1,NORMSDIST((LN(G19)-Q19-P19^2)/P19)+G19/N19*(1-NORMSDIST((LN(G19)-Q19)/P19))) -> 0.80507433 | S19: =IF(F19="—",0,H19*L19*M19*R19) -> 39783.319 | T19: =S19*sig_SAG -> 1989.1659 | U19: =S19+T19 -> 41772.485 | V19: =U19/(1-load_SAG) -> 52876.563 | W19: =V19*ea_SAG -> 5287.6563 | X19: =V19*ec_SAG -> 3701.3594 | Y19: =V19*m_SAG -> 2115.0625 | Z19: =V19*tax_SAG -> 528.76563 | AA19: =V19+Z19 -> 53405.329 | AB19: =IF(G19>0,S19/G19*1000,"n.a.") -> 397.83319
A20: =B20&"|"&C20 -> Colaboradores|EVAC | B20: Colaboradores | C20: EVAC | D20: =INDEX(Cov_Nome,MATCH(C20,Cov_Cod,0)) -> Evacuação Médica e Cobertura no Estrangeiro | E20: =INDEX(Cov_Grupo,MATCH(C20,Cov_Cod,0)) -> Extensão | F20: — | G20: 0 | H20: =INDEX(Cov_Lambda,MATCH(C20,Cov_Cod,0)) -> 0.0012 | I20: =INDEX(Cov_Mu,MATCH(C20,Cov_Cod,0)) -> 44700960 | J20: =IF(INDEX(Cov_FR,MATCH(C20,Cov_Cod,0))="S",INDEX(PF_Factor,MATCH("SAG|"&B20,PF_Key,0)),1) -> 1 | K20: =IF(C20="HOSP_INT",los_int,IF(C20="HOSP_CIR",los_cir,0))*MAX(0,room_ref*J20-INDEX(PF_Room,MATCH("SAG|"&B20,PF_Key,0))) -> 0 | L20: =MAX(0,I20*J20-K20) -> 44700960 | M20: =f_trend -> 1.182194 | N20: =H20*L20*M20/(1-EXP(-H20)) -> 52876920 | O20: =INDEX(Cov_CV,MATCH(C20,Cov_Cod,0)) -> 1 | P20: =SQRT(LN(1+O20^2)) -> 0.83255461 | Q20: =LN(N20)-P20^2/2 -> 17.436904 | R20: =IF(G20<=0,1,NORMSDIST((LN(G20)-Q20-P20^2)/P20)+G20/N20*(1-NORMSDIST((LN(G20)-Q20)/P20))) -> 1 | S20: =IF(F20="—",0,H20*L20*M20*R20) -> 0 | T20: =S20*sig_SAG -> 0 | U20: =S20+T20 -> 0 | V20: =U20/(1-load_SAG) -> 0 | W20: =V20*ea_SAG -> 0 | X20: =V20*ec_SAG -> 0 | Y20: =V20*m_SAG -> 0 | Z20: =V20*tax_SAG -> 0 | AA20: =V20+Z20 -> 0 | AB20: =IF(G20>0,S20/G20*1000,"n.a.") -> n.a.
... A24: =B24&"|"&C24 -> Quadros Médios|HOSP_CIR | B24: Quadros Médios | C24: HOSP_CIR | D24: =INDEX(Cov_Nome,MATCH(C24,Cov_Cod,0)) -> Cirurgia (com internamento e de ambulatório) | E24: =INDEX(Cov_Grupo,MATCH(C24,Cov_Cod,0)) -> Principal | F24: B | G24: 25000000 | H24: =INDEX(Cov_Lambda,MATCH(C24,Cov_Cod,0)) -> 0.024 | I24: =INDEX(Cov_Mu,MATCH(C24,Cov_Cod,0)) -> 2032500 | J24: =IF(INDEX(Cov_FR,MATCH(C24,Cov_Cod,0))="S",INDEX(PF_Factor,MATCH("SAG|"&B24,PF_Key,0)),1) -> 1.05 | K24: =IF(C24="HOSP_INT",los_int,IF(C24="HOSP_CIR",los_cir,0))*MAX(0,room_ref*J24-INDEX(PF_Room,MATCH("SAG|"&B24,PF_Key,0))) -> 0 | L24: =MAX(0,I24*J24-K24) -> 2134125 | M24: =f_trend -> 1.182194 | N24: =H24*L24*M24/(1-EXP(-H24)) -> 2553346.3 | O24: =INDEX(Cov_CV,MATCH(C24,Cov_Cod,0)) -> 1.3 | P24: =SQRT(LN(1+O24^2)) -> 0.99475685 | Q24: =LN(N24)-P24^2/2 -> 14.258145 | R24: =IF(G24<=0,1,NORMSDIST((LN(G24)-Q24-P24^2)/P24)+G24/N24*(1-NORMSDIST((LN(G24)-Q24)/P24))) -> 0.9894959 | S24: =IF(F24="—",0,H24*L24*M24*R24) -> 59914.763 | T24: =S24*sig_SAG -> 2995.7381 | U24: =S24+T24 -> 62910.501 | V24: =U24/(1-load_SAG) -> 79633.546 | W24: =V24*ea_SAG -> 7963.3546 | X24: =V24*ec_SAG -> 5574.3482 | Y24: =V24*m_SAG -> 3185.3418 | Z24: =V24*tax_SAG -> 796.33546 | AA24: =V24+Z24 -> 80429.881 | AB24: =IF(G24>0,S24/G24*1000,"n.a.") -> 2.3965905
A25: =B25&"|"&C25 -> Quadros Médios|HOSP_UCI | B25: Quadros Médios | C25: HOSP_UCI | D25: =INDEX(Cov_Nome,MATCH(C25,Cov_Cod,0)) -> Cuidados Intensivos (UCI) | E25: =INDEX(Cov_Grupo,MATCH(C25,Cov_Cod,0)) -> Principal | F25: B | G25: =INDEX(PF_UCI,MATCH("SAG|"&B25,PF_Key,0)) -> 8000000 | H25: =INDEX(Cov_Lambda,MATCH(C25,Cov_Cod,0)) -> 0.0035 | I25: =INDEX(Cov_Mu,MATCH(C25,Cov_Cod,0)) -> 2835000 | J25: =IF(INDEX(Cov_FR,MATCH(C25,Cov_Cod,0))="S",INDEX(PF_Factor,MATCH("SAG|"&B25,PF_Key,0)),1) -> 1.05 | K25: =IF(C25="HOSP_INT",los_int,IF(C25="HOSP_CIR",los_cir,0))*MAX(0,room_ref*J25-INDEX(PF_Room,MATCH("SAG|"&B25,PF_Key,0))) -> 0 | L25: =MAX(0,I25*J25-K25) -> 2976750 | M25: =f_trend -> 1.182194 | N25: =H25*L25*M25/(1-EXP(-H25)) -> 3525258 | O25: =INDEX(Cov_CV,MATCH(C25,Cov_Cod,0)) -> 1.2 | P25: =SQRT(LN(1+O25^2)) -> 0.94445648 | Q25: =LN(N25)-P25^2/2 -> 14.629465 | R25: =IF(G25<=0,1,NORMSDIST((LN(G25)-Q25-P25^2)/P25)+G25/N25*(1-NORMSDIST((LN(G25)-Q25)/P25))) -> 0.85829785 | S25: =IF(F25="—",0,H25*L25*M25*R25) -> 10571.514 | T25: =S25*sig_SAG -> 528.57569 | U25: =S25+T25 -> 11100.09 | V25: =U25/(1-load_SAG) -> 14050.746 | W25: =V25*ea_SAG -> 1405.0746 | X25: =V25*ec_SAG -> 983.55224 | Y25: =V25*m_SAG -> 562.02985 | Z25: =V25*tax_SAG -> 140.50746 | AA25: =V25+Z25 -> 14191.254 | AB25: =IF(G25>0,S25/G25*1000,"n.a.") -> 1.3214392
A26: =B26&"|"&C26 -> Quadros Médios|AMB_CONS | B26: Quadros Médios | C26: AMB_CONS | D26: =INDEX(Cov_Nome,MATCH(C26,Cov_Cod,0)) -> Consultas de Clínica Geral e Especialidade (incl. teleconsulta) | E26: =INDEX(Cov_Grupo,MATCH(C26,Cov_Cod,0)) -> Principal | F26: B | G26: 5000000 | H26: =INDEX(Cov_Lambda,MATCH(C26,Cov_Cod,0)) -> 2.6 | I26: =INDEX(Cov_Mu,MATCH(C26,Cov_Cod,0)) -> 24000 | J26: =IF(INDEX(Cov_FR,MATCH(C26,Cov_Cod,0))="S",INDEX(PF_Factor,MATCH("SAG|"&B26,PF_Key,0)),1) -> 1.05 | K26: =IF(C26="HOSP_INT",los_int,IF(C26="HOSP_CIR",los_cir,0))*MAX(0,room_ref*J26-INDEX(PF_Room,MATCH("SAG|"&B26,PF_Key,0))) -> 0 | L26: =MAX(0,I26*J26-K26) -> 25200 | M26: =f_trend -> 1.182194 | N26: =H26*L26*M26/(1-EXP(-H26)) -> 83671.967 | O26: =INDEX(Cov_CV,MATCH(C26,Cov_Cod,0)) -> 1 | P26: =SQRT(LN(1+O26^2)) -> 0.83255461 | Q26: =LN(N26)-P26^2/2 -> 10.988086 | R26: =IF(G26<=0,1,NORMSDIST((LN(G26)-Q26-P26^2)/P26)+G26/N26*(1-NORMSDIST((LN(G26)-Q26)/P26))) -> 0.9999995 | S26: =IF(F26="—",0,H26*L26*M26*R26) -> 77457.312 | T26: =S26*sig_SAG -> 3872.8656 | U26: =S26+T26 -> 81330.177 | V26: =U26/(1-load_SAG) -> 102949.59 | W26: =V26*ea_SAG -> 10294.959 | X26: =V26*ec_SAG -> 7206.4714 | Y26: =V26*m_SAG -> 4117.9837 | Z26: =V26*tax_SAG -> 1029.4959 | AA26: =V26+Z26 -> 103979.09 | AB26: =IF(G26>0,S26/G26*1000,"n.a.") -> 15.491462
A27: =B27&"|"&C27 -> Quadros Médios|AMB_MCDT | B27: Quadros Médios | C27: AMB_MCDT | D27: =INDEX(Cov_Nome,MATCH(C27,Cov_Cod,0)) -> MCDT — Exames, Análises e Imagiologia | E27: =INDEX(Cov_Grupo,MATCH(C27,Cov_Cod,0)) -> Principal | F27: B | G27: 5000000 | H27: =INDEX(Cov_Lambda,MATCH(C27,Cov_Cod,0)) -> 3.8 | I27: =INDEX(Cov_Mu,MATCH(C27,Cov_Cod,0)) -> 14600 | J27: =IF(INDEX(Cov_FR,MATCH(C27,Cov_Cod,0))="S",INDEX(PF_Factor,MATCH("SAG|"&B27,PF_Key,0)),1) -> 1.05 | K27: =IF(C27="HOSP_INT",los_int,IF(C27="HOSP_CIR",los_cir,0))*MAX(0,room_ref*J27-INDEX(PF_Room,MATCH("SAG|"&B27,PF_Key,0))) -> 0 | L27: =MAX(0,I27*J27-K27) -> 15330 | M27: =f_trend -> 1.182194 | N27: =H27*L27*M27/(1-EXP(-H27)) -> 70443.403 | O27: =INDEX(Cov_CV,MATCH(C27,Cov_Cod,0)) -> 1.5 | P27: =SQRT(LN(1+O27^2)) -> 1.0856588 | Q27: =LN(N27)-P27^2/2 -> 10.573237 | R27: =IF(G27<=0,1,NORMSDIST((LN(G27)-Q27-P27^2)/P27)+G27/N27*(1-NORMSDIST((LN(G27)-Q27)/P27))) -> 0.99992085 | S27: =IF(F27="—",0,H27*L27*M27*R27) -> 68862.078 | T27: =S27*sig_SAG -> 3443.1039 | U27: =S27+T27 -> 72305.182 | V27: =U27/(1-load_SAG) -> 91525.547 | W27: =V27*ea_SAG -> 9152.5547 | X27: =V27*ec_SAG -> 6406.7883 | Y27: =V27*m_SAG -> 3661.0219 | Z27: =V27*tax_SAG -> 915.25547 | AA27: =V27+Z27 -> 92440.803 | AB27: =IF(G27>0,S27/G27*1000,"n.a.") -> 13.772416
A28: =B28&"|"&C28 -> Quadros Médios|MAL | B28: Quadros Médios | C28: MAL | D28: =INDEX(Cov_Nome,MATCH(C28,Cov_Cod,0)) -> Malária e Doenças Endémicas (ambulatório) | E28: =INDEX(Cov_Grupo,MATCH(C28,Cov_Cod,0)) -> Principal | F28: B | G28: 5000000 | H28: =INDEX(Cov_Lambda,MATCH(C28,Cov_Cod,0)) -> 0.3 | I28: =INDEX(Cov_Mu,MATCH(C28,Cov_Cod,0)) -> 36500 | J28: =IF(INDEX(Cov_FR,MATCH(C28,Cov_Cod,0))="S",INDEX(PF_Factor,MATCH("SAG|"&B28,PF_Key,0)),1) -> 1.05 | K28: =IF(C28="HOSP_INT",los_int,IF(C28="HOSP_CIR",los_cir,0))*MAX(0,room_ref*J28-INDEX(PF_Room,MATCH("SAG|"&B28,PF_Key,0))) -> 0 | L28: =MAX(0,I28*J28-K28) -> 38325 | M28: =f_trend -> 1.182194 | N28: =H28*L28*M28/(1-EXP(-H28)) -> 52443.021 | O28: =INDEX(Cov_CV,MATCH(C28,Cov_Cod,0)) -> 0.8 | P28: =SQRT(LN(1+O28^2)) -> 0.70334646 | Q28: =LN(N28)-P28^2/2 -> 10.620134 | R28: =IF(G28<=0,1,NORMSDIST((LN(G28)-Q28-P28^2)/P28)+G28/N28*(1-NORMSDIST((LN(G28)-Q28)/P28))) -> 1 | S28: =IF(F28="—",0,H28*L28*M28*R28) -> 13592.276 | T28: =S28*sig_SAG -> 679.61378 | U28: =S28+T28 -> 14271.889 | V28: =U28/(1-load_SAG) -> 18065.683 | W28: =V28*ea_SAG -> 1806.5683 | X28: =V28*ec_SAG -> 1264.5978 | Y28: =V28*m_SAG -> 722.62731 | Z28: =V28*tax_SAG -> 180.65683 | AA28: =V28+Z28 -> 18246.339 | AB28: =IF(G28>0,S28/G28*1000,"n.a.") -> 2.7184551
A29: =B29&"|"&C29 -> Quadros Médios|MAT | B29: Quadros Médios | C29: MAT | D29: =INDEX(Cov_Nome,MATCH(C29,Cov_Cod,0)) -> Maternidade e Parto (Normal e Cesariana) | E29: =INDEX(Cov_Grupo,MATCH(C29,Cov_Cod,0)) -> Principal | F29: B | G29: 1500000 | H29: =INDEX(Cov_Lambda,MATCH(C29,Cov_Cod,0)) -> 0.075 | I29: =INDEX(Cov_Mu,MATCH(C29,Cov_Cod,0)) -> 885640 | J29: =IF(INDEX(Cov_FR,MATCH(C29,Cov_Cod,0))="S",INDEX(PF_Factor,MATCH("SAG|"&B29,PF_Key,0)),1) -> 1.05 | K29: =IF(C29="HOSP_INT",los_int,IF(C29="HOSP_CIR",los_cir,0))*MAX(0,room_ref*J29-INDEX(PF_Room,MATCH("SAG|"&B29,PF_Key,0))) -> 0 | L29: =MAX(0,I29*J29-K29) -> 929922 | M29: =f_trend -> 1.182194 | N29: =H29*L29*M29/(1-EXP(-H29)) -> 1141089 | O29: =INDEX(Cov_CV,MATCH(C29,Cov_Cod,0)) -> 0.5 | P29: =SQRT(LN(1+O29^2)) -> 0.47238073 | Q29: =LN(N29)-P29^2/2 -> 13.835922 | R29: =IF(G29<=0,1,NORMSDIST((LN(G29)-Q29-P29^2)/P29)+G29/N29*(1-NORMSDIST((LN(G29)-Q29)/P29))) -> 0.90687082 | S29: =IF(F29="—",0,H29*L29*M29*R29) -> 74772.511 | T29: =S29*sig_SAG -> 3738.6255 | U29: =S29+T29 -> 78511.136 | V29: =U29/(1-load_SAG) -> 99381.185 | W29: =V29*ea_SAG -> 9938.1185 | X29: =V29*ec_SAG -> 6956.683 | Y29: =V29*m_SAG -> 3975.2474 | Z29: =V29*tax_SAG -> 993.81185 | AA29: =V29+Z29 -> 100375 | AB29: =IF(G29>0,S29/G29*1000,"n.a.") -> 49.848341
A30: =B30&"|"&C30 -> Quadros Médios|URG | B30: Quadros Médios | C30: URG | D30: =INDEX(Cov_Nome,MATCH(C30,Cov_Cod,0)) -> Urgência Hospitalar | E30: =INDEX(Cov_Grupo,MATCH(C30,Cov_Cod,0)) -> Principal | F30: B | G30: 800000 | H30: =INDEX(Cov_Lambda,MATCH(C30,Cov_Cod,0)) -> 0.42 | I30: =INDEX(Cov_Mu,MATCH(C30,Cov_Cod,0)) -> 43300 | J30: =IF(INDEX(Cov_FR,MATCH(C30,Cov_Cod,0))="S",INDEX(PF_Factor,MATCH("SAG|"&B30,PF_Key,0)),1) -> 1.05 | K30: =IF(C30="HOSP_INT",los_int,IF(C30="HOSP_CIR",los_cir,0))*MAX(0,room_ref*J30-INDEX(PF_Room,MATCH("SAG|"&B30,PF_Key,0))) -> 0 | L30: =MAX(0,I30*J30-K30) -> 45465 | M30: =f_trend -> 1.182194 | N30: =H30*L30*M30/(1-EXP(-H30)) -> 65823.414 | O30: =INDEX(Cov_CV,MATCH(C30,Cov_Cod,0)) -> 1 | P30: =SQRT(LN(1+O30^2)) -> 0.83255461 | Q30: =LN(N30)-P30^2/2 -> 10.748157 | R30: =IF(G30<=0,1,NORMSDIST((LN(G30)-Q30-P30^2)/P30)+G30/N30*(1-NORMSDIST((LN(G30)-Q30)/P30))) -> 0.99897079 | S30: =IF(F30="—",0,H30*L30*M30*R30) -> 22551.115 | T30: =S30*sig_SAG -> 1127.5558 | U30: =S30+T30 -> 23678.671 | V30: =U30/(1-load_SAG) -> 29973.002 | W30: =V30*ea_SAG -> 2997.3002 | X30: =V30*ec_SAG -> 2098.1101 | Y30: =V30*m_SAG -> 1198.9201 | Z30: =V30*tax_SAG -> 299.73002 | AA30: =V30+Z30 -> 30272.732 | AB30: =IF(G30>0,S30/G30*1000,"n.a.") -> 28.188894
A31: =B31&"|"&C31 -> Quadros Médios|AMBUL | B31: Quadros Médios | C31: AMBUL | D31: =INDEX(Cov_Nome,MATCH(C31,Cov_Cod,0)) -> Transporte em Ambulância / Emergência Médica | E31: =INDEX(Cov_Grupo,MATCH(C31,Cov_Cod,0)) -> Principal | F31: B | G31: 400000 | H31: =INDEX(Cov_Lambda,MATCH(C31,Cov_Cod,0)) -> 0.018 | I31: =INDEX(Cov_Mu,MATCH(C31,Cov_Cod,0)) -> 76000 | J31: =IF(INDEX(Cov_FR,MATCH(C31,Cov_Cod,0))="S",INDEX(PF_Factor,MATCH("SAG|"&B31,PF_Key,0)),1) -> 1 | K31: =IF(C31="HOSP_INT",los_int,IF(C31="HOSP_CIR",los_cir,0))*MAX(0,room_ref*J31-INDEX(PF_Room,MATCH("SAG|"&B31,PF_Key,0))) -> 0 | L31: =MAX(0,I31*J31-K31) -> 76000 | M31: =f_trend -> 1.182194 | N31: =H31*L31*M31/(1-EXP(-H31)) -> 90657.791 | O31: =INDEX(Cov_CV,MATCH(C31,Cov_Cod,0)) -> 0.6 | P31: =SQRT(LN(1+O31^2)) -> 0.55451303 | Q31: =LN(N31)-P31^2/2 -> 11.261105 | R31: =IF(G31<=0,1,NORMSDIST((LN(G31)-Q31-P31^2)/P31)+G31/N31*(1-NORMSDIST((LN(G31)-Q31)/P31))) -> 0.99871115 | S31: =IF(F31="—",0,H31*L31*M31*R31) -> 1615.157 | T31: =S31*sig_SAG -> 80.75785 | U31: =S31+T31 -> 1695.9149 | V31: =U31/(1-load_SAG) -> 2146.7277 | W31: =V31*ea_SAG -> 214.67277 | X31: =V31*ec_SAG -> 150.27094 | Y31: =V31*m_SAG -> 85.869106 | Z31: =V31*tax_SAG -> 21.467277 | AA31: =V31+Z31 -> 2168.1949 | AB31: =IF(G31>0,S31/G31*1000,"n.a.") -> 4.0378925
A32: =B32&"|"&C32 -> Quadros Médios|MED | B32: Quadros Médios | C32: MED | D32: =INDEX(Cov_Nome,MATCH(C32,Cov_Cod,0)) -> Medicamentos em Ambulatório (Farmácia) | E32: =INDEX(Cov_Grupo,MATCH(C32,Cov_Cod,0)) -> Principal | F32: O | G32: 750000 | H32: =INDEX(Cov_Lambda,MATCH(C32,Cov_Cod,0)) -> 3.4 | I32: =INDEX(Cov_Mu,MATCH(C32,Cov_Cod,0)) -> 17400 | J32: =IF(INDEX(Cov_FR,MATCH(C32,Cov_Cod,0))="S",INDEX(PF_Factor,MATCH("SAG|"&B32,PF_Key,0)),1) -> 1 | K32: =IF(C32="HOSP_INT",los_int,IF(C32="HOSP_CIR",los_cir,0))*MAX(0,room_ref*J32-INDEX(PF_Room,MATCH("SAG|"&B32,PF_Key,0))) -> 0 | L32: =MAX(0,I32*J32-K32) -> 17400 | M32: =f_trend -> 1.182194 | N32: =H32*L32*M32/(1-EXP(-H32)) -> 72353.262 | O32: =INDEX(Cov_CV,MATCH(C32,Cov_Cod,0)) -> 1.2 | P32: =SQRT(LN(1+O32^2)) -> 0.94445648 | Q32: =LN(N32)-P32^2/2 -> 10.743317 | R32: =IF(G32<=0,1,NORMSDIST((LN(G32)-Q32-P32^2)/P32)+G32/N32*(1-NORMSDIST((LN(G32)-Q32)/P32))) -> 0.99401736 | S32: =IF(F32="—",0,H32*L32*M32*R32) -> 69520.179 | T32: =S32*sig_SAG -> 3476.009 | U32: =S32+T32 -> 72996.188 | V32: =U32/(1-load_SAG) -> 92400.238 | W32: =V32*ea_SAG -> 9240.0238 | X32: =V32*ec_SAG -> 6468.0167 | Y32: =V32*m_SAG -> 3696.0095 | Z32: =V32*tax_SAG -> 924.00238 | AA32: =V32+Z32 -> 93324.241 | AB32: =IF(G32>0,S32/G32*1000,"n.a.") -> 92.693572
A33: =B33&"|"&C33 -> Quadros Médios|DENT | B33: Quadros Médios | C33: DENT | D33: =INDEX(Cov_Nome,MATCH(C33,Cov_Cod,0)) -> Estomatologia (tratamentos) | E33: =INDEX(Cov_Grupo,MATCH(C33,Cov_Cod,0)) -> Extensão | F33: O | G33: 500000 | H33: =INDEX(Cov_Lambda,MATCH(C33,Cov_Cod,0)) -> 0.85 | I33: =INDEX(Cov_Mu,MATCH(C33,Cov_Cod,0)) -> 34500 | J33: =IF(INDEX(Cov_FR,MATCH(C33,Cov_Cod,0))="S",INDEX(PF_Factor,MATCH("SAG|"&B33,PF_Key,0)),1) -> 1.05 | K33: =IF(C33="HOSP_INT",los_int,IF(C33="HOSP_CIR",los_cir,0))*MAX(0,room_ref*J33-INDEX(PF_Room,MATCH("SAG|"&B33,PF_Key,0))) -> 0 | L33: =MAX(0,I33*J33-K33) -> 36225 | M33: =f_trend -> 1.182194 | N33: =H33*L33*M33/(1-EXP(-H33)) -> 63573.49 | O33: =INDEX(Cov_CV,MATCH(C33,Cov_Cod,0)) -> 1 | P33: =SQRT(LN(1+O33^2)) -> 0.83255461 | Q33: =LN(N33)-P33^2/2 -> 10.713378 | R33: =IF(G33<=0,1,NORMSDIST((LN(G33)-Q33-P33^2)/P33)+G33/N33*(1-NORMSDIST((LN(G33)-Q33)/P33))) -> 0.99532752 | S33: =IF(F33="—",0,H33*L33*M33*R33) -> 36231.147 | T33: =S33*sig_SAG -> 1811.5574 | U33: =S33+T33 -> 38042.704 | V33: =U33/(1-load_SAG) -> 48155.322 | W33: =V33*ea_SAG -> 4815.5322 | X33: =V33*ec_SAG -> 3370.8725 | Y33: =V33*m_SAG -> 1926.2129 | Z33: =V33*tax_SAG -> 481.55322 | AA33: =V33+Z33 -> 48636.875 | AB33: =IF(G33>0,S33/G33*1000,"n.a.") -> 72.462294
A34: =B34&"|"&C34 -> Quadros Médios|PROT | B34: Quadros Médios | C34: PROT | D34: =INDEX(Cov_Nome,MATCH(C34,Cov_Cod,0)) -> Próteses Dentárias | E34: =INDEX(Cov_Grupo,MATCH(C34,Cov_Cod,0)) -> Extensão | F34: O | G34: 250000 | H34: =INDEX(Cov_Lambda,MATCH(C34,Cov_Cod,0)) -> 0.02 | I34: =INDEX(Cov_Mu,MATCH(C34,Cov_Cod,0)) -> 304000 | J34: =IF(INDEX(Cov_FR,MATCH(C34,Cov_Cod,0))="S",INDEX(PF_Factor,MATCH("SAG|"&B34,PF_Key,0)),1) -> 1 | K34: =IF(C34="HOSP_INT",los_int,IF(C34="HOSP_CIR",los_cir,0))*MAX(0,room_ref*J34-INDEX(PF_Room,MATCH("SAG|"&B34,PF_Key,0))) -> 0 | L34: =MAX(0,I34*J34-K34) -> 304000 | M34: =f_trend -> 1.182194 | N34: =H34*L34*M34/(1-EXP(-H34)) -> 362992.83 | O34: =INDEX(Cov_CV,MATCH(C34,Cov_Cod,0)) -> 0.7 | P34: =SQRT(LN(1+O34^2)) -> 0.63148723 | Q34: =LN(N34)-P34^2/2 -> 12.60275 | R34: =IF(G34<=0,1,NORMSDIST((LN(G34)-Q34-P34^2)/P34)+G34/N34*(1-NORMSDIST((LN(G34)-Q34)/P34))) -> 0.60131553 | S34: =IF(F34="—",0,H34*L34*M34*R34) -> 4322.0994 | T34: =S34*sig_SAG -> 216.10497 | U34: =S34+T34 -> 4538.2043 | V34: =U34/(1-load_SAG) -> 5744.5625 | W34: =V34*ea_SAG -> 574.45625 | X34: =V34*ec_SAG -> 402.11937 | Y34: =V34*m_SAG -> 229.7825 | Z34: =V34*tax_SAG -> 57.445625 | AA34: =V34+Z34 -> 5802.0081 | AB34: =IF(G34>0,S34/G34*1000,"n.a.") -> 17.288397
A35: =B35&"|"&C35 -> Quadros Médios|OPT | B35: Quadros Médios | C35: OPT | D35: =INDEX(Cov_Nome,MATCH(C35,Cov_Cod,0)) -> Óptica — Lentes e Armações | E35: =INDEX(Cov_Grupo,MATCH(C35,Cov_Cod,0)) -> Extensão | F35: O | G35: 200000 | H35: =INDEX(Cov_Lambda,MATCH(C35,Cov_Cod,0)) -> 0.22 | I35: =INDEX(Cov_Mu,MATCH(C35,Cov_Cod,0)) -> 102500 | J35: =IF(INDEX(Cov_FR,MATCH(C35,Cov_Cod,0))="S",INDEX(PF_Factor,MATCH("SAG|"&B35,PF_Key,0)),1) -> 1 | K35: =IF(C35="HOSP_INT",los_int,IF(C35="HOSP_CIR",los_cir,0))*MAX(0,room_ref*J35-INDEX(PF_Room,MATCH("SAG|"&B35,PF_Key,0))) -> 0 | L35: =MAX(0,I35*J35-K35) -> 102500 | M35: =f_trend -> 1.182194 | N35: =H35*L35*M35/(1-EXP(-H35)) -> 134992.47 | O35: =INDEX(Cov_CV,MATCH(C35,Cov_Cod,0)) -> 0.5 | P35: =SQRT(LN(1+O35^2)) -> 0.47238073 | Q35: =LN(N35)-P35^2/2 -> 11.701402 | R35: =IF(G35<=0,1,NORMSDIST((LN(G35)-Q35-P35^2)/P35)+G35/N35*(1-NORMSDIST((LN(G35)-Q35)/P35))) -> 0.93579367 | S35: =IF(F35="—",0,H35*L35*M35*R35) -> 24946.832 | T35: =S35*sig_SAG -> 1247.3416 | U35: =S35+T35 -> 26194.173 | V35: =U35/(1-load_SAG) -> 33157.182 | W35: =V35*ea_SAG -> 3315.7182 | X35: =V35*ec_SAG -> 2321.0027 | Y35: =V35*m_SAG -> 1326.2873 | Z35: =V35*tax_SAG -> 331.57182 | AA35: =V35+Z35 -> 33488.753 | AB35: =IF(G35>0,S35/G35*1000,"n.a.") -> 124.73416
A36: =B36&"|"&C36 -> Quadros Médios|PREV | B36: Quadros Médios | C36: PREV | D36: =INDEX(Cov_Nome,MATCH(C36,Cov_Cod,0)) -> Medicina Preventiva e Check-up Anual | E36: =INDEX(Cov_Grupo,MATCH(C36,Cov_Cod,0)) -> Extensão | F36: O | G36: 200000 | H36: =INDEX(Cov_Lambda,MATCH(C36,Cov_Cod,0)) -> 0.55 | I36: =INDEX(Cov_Mu,MATCH(C36,Cov_Cod,0)) -> 76000 | J36: =IF(INDEX(Cov_FR,MATCH(C36,Cov_Cod,0))="S",INDEX(PF_Factor,MATCH("SAG|"&B36,PF_Key,0)),1) -> 1 | K36: =IF(C36="HOSP_INT",los_int,IF(C36="HOSP_CIR",los_cir,0))*MAX(0,room_ref*J36-INDEX(PF_Room,MATCH("SAG|"&B36,PF_Key,0))) -> 0 | L36: =MAX(0,I36*J36-K36) -> 76000 | M36: =f_trend -> 1.182194 | N36: =H36*L36*M36/(1-EXP(-H36)) -> 116808.15 | O36: =INDEX(Cov_CV,MATCH(C36,Cov_Cod,0)) -> 0.3 | P36: =SQRT(LN(1+O36^2)) -> 0.29356038 | Q36: =LN(N36)-P36^2/2 -> 11.625199 | R36: =IF(G36<=0,1,NORMSDIST((LN(G36)-Q36-P36^2)/P36)+G36/N36*(1-NORMSDIST((LN(G36)-Q36)/P36))) -> 0.99498361 | S36: =IF(F36="—",0,H36*L36*M36*R36) -> 49167.821 | T36: =S36*sig_SAG -> 2458.391 | U36: =S36+T36 -> 51626.212 | V36: =U36/(1-load_SAG) -> 65349.635 | W36: =V36*ea_SAG -> 6534.9635 | X36: =V36*ec_SAG -> 4574.4745 | Y36: =V36*m_SAG -> 2613.9854 | Z36: =V36*tax_SAG -> 653.49635 | AA36: =V36+Z36 -> 66003.132 | AB36: =IF(G36>0,S36/G36*1000,"n.a.") -> 245.8391
A37: =B37&"|"&C37 -> Quadros Médios|EVAC | B37: Quadros Médios | C37: EVAC | D37: =INDEX(Cov_Nome,MATCH(C37,Cov_Cod,0)) -> Evacuação Médica e Cobertura no Estrangeiro | E37: =INDEX(Cov_Grupo,MATCH(C37,Cov_Cod,0)) -> Extensão | F37: O | G37: 30000000 | H37: =INDEX(Cov_Lambda,MATCH(C37,Cov_Cod,0)) -> 0.0012 | I37: =INDEX(Cov_Mu,MATCH(C37,Cov_Cod,0)) -> 44700960 | J37: =IF(INDEX(Cov_FR,MATCH(C37,Cov_Cod,0))="S",INDEX(PF_Factor,MATCH("SAG|"&B37,PF_Key,0)),1) -> 1 | K37: =IF(C37="HOSP_INT",los_int,IF(C37="HOSP_CIR",los_cir,0))*MAX(0,room_ref*J37-INDEX(PF_Room,MATCH("SAG|"&B37,PF_Key,0))) -> 0 | L37: =MAX(0,I37*J37-K37) -> 44700960 | M37: =f_trend -> 1.182194 | N37: =H37*L37*M37/(1-EXP(-H37)) -> 52876920 | O37: =INDEX(Cov_CV,MATCH(C37,Cov_Cod,0)) -> 1 | P37: =SQRT(LN(1+O37^2)) -> 0.83255461 | Q37: =LN(N37)-P37^2/2 -> 17.436904 | R37: =IF(G37<=0,1,NORMSDIST((LN(G37)-Q37-P37^2)/P37)+G37/N37*(1-NORMSDIST((LN(G37)-Q37)/P37))) -> 0.47916307 | S37: =IF(F37="—",0,H37*L37*M37*R37) -> 30385.766 | T37: =S37*sig_SAG -> 1519.2883 | U37: =S37+T37 -> 31905.054 | V37: =U37/(1-load_SAG) -> 40386.144 | W37: =V37*ea_SAG -> 4038.6144 | X37: =V37*ec_SAG -> 2827.0301 | Y37: =V37*m_SAG -> 1615.4458 | Z37: =V37*tax_SAG -> 403.86144 | AA37: =V37+Z37 -> 40790.006 | AB37: =IF(G37>0,S37/G37*1000,"n.a.") -> 1.0128589
... A41: =B41&"|"&C41 -> Administração|HOSP_CIR | B41: Administração | C41: HOSP_CIR | D41: =INDEX(Cov_Nome,MATCH(C41,Cov_Cod,0)) -> Cirurgia (com internamento e de ambulatório) | E41: =INDEX(Cov_Grupo,MATCH(C41,Cov_Cod,0)) -> Principal | F41: B | G41: 60000000 | H41: =INDEX(Cov_Lambda,MATCH(C41,Cov_Cod,0)) -> 0.024 | I41: =INDEX(Cov_Mu,MATCH(C41,Cov_Cod,0)) -> 2032500 | J41: =IF(INDEX(Cov_FR,MATCH(C41,Cov_Cod,0))="S",INDEX(PF_Factor,MATCH("SAG|"&B41,PF_Key,0)),1) -> 1.35 | K41: =IF(C41="HOSP_INT",los_int,IF(C41="HOSP_CIR",los_cir,0))*MAX(0,room_ref*J41-INDEX(PF_Room,MATCH("SAG|"&B41,PF_Key,0))) -> 0 | L41: =MAX(0,I41*J41-K41) -> 2743875 | M41: =f_trend -> 1.182194 | N41: =H41*L41*M41/(1-EXP(-H41)) -> 3282873.8 | O41: =INDEX(Cov_CV,MATCH(C41,Cov_Cod,0)) -> 1.3 | P41: =SQRT(LN(1+O41^2)) -> 0.99475685 | Q41: =LN(N41)-P41^2/2 -> 14.509459 | R41: =IF(G41<=0,1,NORMSDIST((LN(G41)-Q41-P41^2)/P41)+G41/N41*(1-NORMSDIST((LN(G41)-Q41)/P41))) -> 0.99807343 | S41: =IF(F41="—",0,H41*L41*M41*R41) -> 77701.036 | T41: =S41*sig_SAG -> 3885.0518 | U41: =S41+T41 -> 81586.088 | V41: =U41/(1-load_SAG) -> 103273.53 | W41: =V41*ea_SAG -> 10327.353 | X41: =V41*ec_SAG -> 7229.147 | Y41: =V41*m_SAG -> 4130.9412 | Z41: =V41*tax_SAG -> 1032.7353 | AA41: =V41+Z41 -> 104306.26 | AB41: =IF(G41>0,S41/G41*1000,"n.a.") -> 1.2950173
A42: =B42&"|"&C42 -> Administração|HOSP_UCI | B42: Administração | C42: HOSP_UCI | D42: =INDEX(Cov_Nome,MATCH(C42,Cov_Cod,0)) -> Cuidados Intensivos (UCI) | E42: =INDEX(Cov_Grupo,MATCH(C42,Cov_Cod,0)) -> Principal | F42: B | G42: =INDEX(PF_UCI,MATCH("SAG|"&B42,PF_Key,0)) -> 20000000 | H42: =INDEX(Cov_Lambda,MATCH(C42,Cov_Cod,0)) -> 0.0035 | I42: =INDEX(Cov_Mu,MATCH(C42,Cov_Cod,0)) -> 2835000 | J42: =IF(INDEX(Cov_FR,MATCH(C42,Cov_Cod,0))="S",INDEX(PF_Factor,MATCH("SAG|"&B42,PF_Key,0)),1) -> 1.35 | K42: =IF(C42="HOSP_INT",los_int,IF(C42="HOSP_CIR",los_cir,0))*MAX(0,room_ref*J42-INDEX(PF_Room,MATCH("SAG|"&B42,PF_Key,0))) -> 0 | L42: =MAX(0,I42*J42-K42) -> 3827250 | M42: =f_trend -> 1.182194 | N42: =H42*L42*M42/(1-EXP(-H42)) -> 4532474.6 | O42: =INDEX(Cov_CV,MATCH(C42,Cov_Cod,0)) -> 1.2 | P42: =SQRT(LN(1+O42^2)) -> 0.94445648 | Q42: =LN(N42)-P42^2/2 -> 14.88078 | R42: =IF(G42<=0,1,NORMSDIST((LN(G42)-Q42-P42^2)/P42)+G42/N42*(1-NORMSDIST((LN(G42)-Q42)/P42))) -> 0.95459029 | S42: =IF(F42="—",0,H42*L42*M42*R42) -> 15116.827 | T42: =S42*sig_SAG -> 755.84135 | U42: =S42+T42 -> 15872.668 | V42: =U42/(1-load_SAG) -> 20091.985 | W42: =V42*ea_SAG -> 2009.1985 | X42: =V42*ec_SAG -> 1406.439 | Y42: =V42*m_SAG -> 803.67941 | Z42: =V42*tax_SAG -> 200.91985 | AA42: =V42+Z42 -> 20292.905 | AB42: =IF(G42>0,S42/G42*1000,"n.a.") -> 0.75584135
A43: =B43&"|"&C43 -> Administração|AMB_CONS | B43: Administração | C43: AMB_CONS | D43: =INDEX(Cov_Nome,MATCH(C43,Cov_Cod,0)) -> Consultas de Clínica Geral e Especialidade (incl. teleconsulta) | E43: =INDEX(Cov_Grupo,MATCH(C43,Cov_Cod,0)) -> Principal | F43: B | G43: 12000000 | H43: =INDEX(Cov_Lambda,MATCH(C43,Cov_Cod,0)) -> 2.6 | I43: =INDEX(Cov_Mu,MATCH(C43,Cov_Cod,0)) -> 24000 | J43: =IF(INDEX(Cov_FR,MATCH(C43,Cov_Cod,0))="S",INDEX(PF_Factor,MATCH("SAG|"&B43,PF_Key,0)),1) -> 1.35 | K43: =IF(C43="HOSP_INT",los_int,IF(C43="HOSP_CIR",los_cir,0))*MAX(0,room_ref*J43-INDEX(PF_Room,MATCH("SAG|"&B43,PF_Key,0))) -> 0 | L43: =MAX(0,I43*J43-K43) -> 32400 | M43: =f_trend -> 1.182194 | N43: =H43*L43*M43/(1-EXP(-H43)) -> 107578.24 | O43: =INDEX(Cov_CV,MATCH(C43,Cov_Cod,0)) -> 1 | P43: =SQRT(LN(1+O43^2)) -> 0.83255461 | Q43: =LN(N43)-P43^2/2 -> 11.2394 | R43: =IF(G43<=0,1,NORMSDIST((LN(G43)-Q43-P43^2)/P43)+G43/N43*(1-NORMSDIST((LN(G43)-Q43)/P43))) -> 0.99999999 | S43: =IF(F43="—",0,H43*L43*M43*R43) -> 99588.022 | T43: =S43*sig_SAG -> 4979.4011 | U43: =S43+T43 -> 104567.42 | V43: =U43/(1-load_SAG) -> 132363.83 | W43: =V43*ea_SAG -> 13236.383 | X43: =V43*ec_SAG -> 9265.4678 | Y43: =V43*m_SAG -> 5294.553 | Z43: =V43*tax_SAG -> 1323.6383 | AA43: =V43+Z43 -> 133687.46 | AB43: =IF(G43>0,S43/G43*1000,"n.a.") -> 8.2990018
A44: =B44&"|"&C44 -> Administração|AMB_MCDT | B44: Administração | C44: AMB_MCDT | D44: =INDEX(Cov_Nome,MATCH(C44,Cov_Cod,0)) -> MCDT — Exames, Análises e Imagiologia | E44: =INDEX(Cov_Grupo,MATCH(C44,Cov_Cod,0)) -> Principal | F44: B | G44: 12000000 | H44: =INDEX(Cov_Lambda,MATCH(C44,Cov_Cod,0)) -> 3.8 | I44: =INDEX(Cov_Mu,MATCH(C44,Cov_Cod,0)) -> 14600 | J44: =IF(INDEX(Cov_FR,MATCH(C44,Cov_Cod,0))="S",INDEX(PF_Factor,MATCH("SAG|"&B44,PF_Key,0)),1) -> 1.35 | K44: =IF(C44="HOSP_INT",los_int,IF(C44="HOSP_CIR",los_cir,0))*MAX(0,room_ref*J44-INDEX(PF_Room,MATCH("SAG|"&B44,PF_Key,0))) -> 0 | L44: =MAX(0,I44*J44-K44) -> 19710 | M44: =f_trend -> 1.182194 | N44: =H44*L44*M44/(1-EXP(-H44)) -> 90570.089 | O44: =INDEX(Cov_CV,MATCH(C44,Cov_Cod,0)) -> 1.5 | P44: =SQRT(LN(1+O44^2)) -> 1.0856588 | Q44: =LN(N44)-P44^2/2 -> 10.824552 | R44: =IF(G44<=0,1,NORMSDIST((LN(G44)-Q44-P44^2)/P44)+G44/N44*(1-NORMSDIST((LN(G44)-Q44)/P44))) -> 0.99999247 | S44: =IF(F44="—",0,H44*L44*M44*R44) -> 88543.299 | T44: =S44*sig_SAG -> 4427.165 | U44: =S44+T44 -> 92970.464 | V44: =U44/(1-load_SAG) -> 117684.13 | W44: =V44*ea_SAG -> 11768.413 | X44: =V44*ec_SAG -> 8237.8892 | Y44: =V44*m_SAG -> 4707.3653 | Z44: =V44*tax_SAG -> 1176.8413 | AA44: =V44+Z44 -> 118860.97 | AB44: =IF(G44>0,S44/G44*1000,"n.a.") -> 7.3786083
A45: =B45&"|"&C45 -> Administração|MAL | B45: Administração | C45: MAL | D45: =INDEX(Cov_Nome,MATCH(C45,Cov_Cod,0)) -> Malária e Doenças Endémicas (ambulatório) | E45: =INDEX(Cov_Grupo,MATCH(C45,Cov_Cod,0)) -> Principal | F45: B | G45: 12000000 | H45: =INDEX(Cov_Lambda,MATCH(C45,Cov_Cod,0)) -> 0.3 | I45: =INDEX(Cov_Mu,MATCH(C45,Cov_Cod,0)) -> 36500 | J45: =IF(INDEX(Cov_FR,MATCH(C45,Cov_Cod,0))="S",INDEX(PF_Factor,MATCH("SAG|"&B45,PF_Key,0)),1) -> 1.35 | K45: =IF(C45="HOSP_INT",los_int,IF(C45="HOSP_CIR",los_cir,0))*MAX(0,room_ref*J45-INDEX(PF_Room,MATCH("SAG|"&B45,PF_Key,0))) -> 0 | L45: =MAX(0,I45*J45-K45) -> 49275 | M45: =f_trend -> 1.182194 | N45: =H45*L45*M45/(1-EXP(-H45)) -> 67426.741 | O45: =INDEX(Cov_CV,MATCH(C45,Cov_Cod,0)) -> 0.8 | P45: =SQRT(LN(1+O45^2)) -> 0.70334646 | Q45: =LN(N45)-P45^2/2 -> 10.871449 | R45: =IF(G45<=0,1,NORMSDIST((LN(G45)-Q45-P45^2)/P45)+G45/N45*(1-NORMSDIST((LN(G45)-Q45)/P45))) -> 1 | S45: =IF(F45="—",0,H45*L45*M45*R45) -> 17475.783 | T45: =S45*sig_SAG -> 873.78914 | U45: =S45+T45 -> 18349.572 | V45: =U45/(1-load_SAG) -> 23227.306 | W45: =V45*ea_SAG -> 2322.7306 | X45: =V45*ec_SAG -> 1625.9114 | Y45: =V45*m_SAG -> 929.09225 | Z45: =V45*tax_SAG -> 232.27306 | AA45: =V45+Z45 -> 23459.579 | AB45: =IF(G45>0,S45/G45*1000,"n.a.") -> 1.4563152
A46: =B46&"|"&C46 -> Administração|MAT | B46: Administração | C46: MAT | D46: =INDEX(Cov_Nome,MATCH(C46,Cov_Cod,0)) -> Maternidade e Parto (Normal e Cesariana) | E46: =INDEX(Cov_Grupo,MATCH(C46,Cov_Cod,0)) -> Principal | F46: B | G46: 3000000 | H46: =INDEX(Cov_Lambda,MATCH(C46,Cov_Cod,0)) -> 0.075 | I46: =INDEX(Cov_Mu,MATCH(C46,Cov_Cod,0)) -> 885640 | J46: =IF(INDEX(Cov_FR,MATCH(C46,Cov_Cod,0))="S",INDEX(PF_Factor,MATCH("SAG|"&B46,PF_Key,0)),1) -> 1.35 | K46: =IF(C46="HOSP_INT",los_int,IF(C46="HOSP_CIR",los_cir,0))*MAX(0,room_ref*J46-INDEX(PF_Room,MATCH("SAG|"&B46,PF_Key,0))) -> 0 | L46: =MAX(0,I46*J46-K46) -> 1195614 | M46: =f_trend -> 1.182194 | N46: =H46*L46*M46/(1-EXP(-H46)) -> 1467114.5 | O46: =INDEX(Cov_CV,MATCH(C46,Cov_Cod,0)) -> 0.5 | P46: =SQRT(LN(1+O46^2)) -> 0.47238073 | Q46: =LN(N46)-P46^2/2 -> 14.087236 | R46: =IF(G46<=0,1,NORMSDIST((LN(G46)-Q46-P46^2)/P46)+G46/N46*(1-NORMSDIST((LN(G46)-Q46)/P46))) -> 0.98122231 | S46: =IF(F46="—",0,H46*L46*M46*R46) -> 104017.98 | T46: =S46*sig_SAG -> 5200.8991 | U46: =S46+T46 -> 109218.88 | V46: =U46/(1-load_SAG) -> 138251.75 | W46: =V46*ea_SAG -> 13825.175 | X46: =V46*ec_SAG -> 9677.6223 | Y46: =V46*m_SAG -> 5530.0699 | Z46: =V46*tax_SAG -> 1382.5175 | AA46: =V46+Z46 -> 139634.27 | AB46: =IF(G46>0,S46/G46*1000,"n.a.") -> 34.672661
A47: =B47&"|"&C47 -> Administração|URG | B47: Administração | C47: URG | D47: =INDEX(Cov_Nome,MATCH(C47,Cov_Cod,0)) -> Urgência Hospitalar | E47: =INDEX(Cov_Grupo,MATCH(C47,Cov_Cod,0)) -> Principal | F47: B | G47: 1500000 | H47: =INDEX(Cov_Lambda,MATCH(C47,Cov_Cod,0)) -> 0.42 | I47: =INDEX(Cov_Mu,MATCH(C47,Cov_Cod,0)) -> 43300 | J47: =IF(INDEX(Cov_FR,MATCH(C47,Cov_Cod,0))="S",INDEX(PF_Factor,MATCH("SAG|"&B47,PF_Key,0)),1) -> 1.35 | K47: =IF(C47="HOSP_INT",los_int,IF(C47="HOSP_CIR",los_cir,0))*MAX(0,room_ref*J47-INDEX(PF_Room,MATCH("SAG|"&B47,PF_Key,0))) -> 0 | L47: =MAX(0,I47*J47-K47) -> 58455 | M47: =f_trend -> 1.182194 | N47: =H47*L47*M47/(1-EXP(-H47)) -> 84630.103 | O47: =INDEX(Cov_CV,MATCH(C47,Cov_Cod,0)) -> 1 | P47: =SQRT(LN(1+O47^2)) -> 0.83255461 | Q47: =LN(N47)-P47^2/2 -> 10.999472 | R47: =IF(G47<=0,1,NORMSDIST((LN(G47)-Q47-P47^2)/P47)+G47/N47*(1-NORMSDIST((LN(G47)-Q47)/P47))) -> 0.99977155 | S47: =IF(F47="—",0,H47*L47*M47*R47) -> 29017.532 | T47: =S47*sig_SAG -> 1450.8766 | U47: =S47+T47 -> 30468.409 | V47: =U47/(1-load_SAG) -> 38567.606 | W47: =V47*ea_SAG -> 3856.7606 | X47: =V47*ec_SAG -> 2699.7324 | Y47: =V47*m_SAG -> 1542.7043 | Z47: =V47*tax_SAG -> 385.67606 | AA47: =V47+Z47 -> 38953.282 | AB47: =IF(G47>0,S47/G47*1000,"n.a.") -> 19.345022
A48: =B48&"|"&C48 -> Administração|AMBUL | B48: Administração | C48: AMBUL | D48: =INDEX(Cov_Nome,MATCH(C48,Cov_Cod,0)) -> Transporte em Ambulância / Emergência Médica | E48: =INDEX(Cov_Grupo,MATCH(C48,Cov_Cod,0)) -> Principal | F48: B | G48: 800000 | H48: =INDEX(Cov_Lambda,MATCH(C48,Cov_Cod,0)) -> 0.018 | I48: =INDEX(Cov_Mu,MATCH(C48,Cov_Cod,0)) -> 76000 | J48: =IF(INDEX(Cov_FR,MATCH(C48,Cov_Cod,0))="S",INDEX(PF_Factor,MATCH("SAG|"&B48,PF_Key,0)),1) -> 1 | K48: =IF(C48="HOSP_INT",los_int,IF(C48="HOSP_CIR",los_cir,0))*MAX(0,room_ref*J48-INDEX(PF_Room,MATCH("SAG|"&B48,PF_Key,0))) -> 0 | L48: =MAX(0,I48*J48-K48) -> 76000 | M48: =f_trend -> 1.182194 | N48: =H48*L48*M48/(1-EXP(-H48)) -> 90657.791 | O48: =INDEX(Cov_CV,MATCH(C48,Cov_Cod,0)) -> 0.6 | P48: =SQRT(LN(1+O48^2)) -> 0.55451303 | Q48: =LN(N48)-P48^2/2 -> 11.261105 | R48: =IF(G48<=0,1,NORMSDIST((LN(G48)-Q48-P48^2)/P48)+G48/N48*(1-NORMSDIST((LN(G48)-Q48)/P48))) -> 0.99998432 | S48: =IF(F48="—",0,H48*L48*M48*R48) -> 1617.216 | T48: =S48*sig_SAG -> 80.860802 | U48: =S48+T48 -> 1698.0768 | V48: =U48/(1-load_SAG) -> 2149.4644 | W48: =V48*ea_SAG -> 214.94644 | X48: =V48*ec_SAG -> 150.4625 | Y48: =V48*m_SAG -> 85.978574 | Z48: =V48*tax_SAG -> 21.494644 | AA48: =V48+Z48 -> 2170.959 | AB48: =IF(G48>0,S48/G48*1000,"n.a.") -> 2.02152
